Workbook

Sheet Daily Sale 
A1: SR# | B1: Item Name | C1: Date | D1: Time | E1: Total Head Count | F1: Rate | G1: Amount | I1: SR# | J1: Item Name | K1: Date | L1: Time | M1: Total Head Count | N1: Rate | O1: Amount
A2: 1 | B2: Chay | C2: 16/12/2025 | D2: Midnight | E2: =G2/F2 -> 194.28571 | F2: 35 | G2: 6800 | I2: 1 | J2: Chay | K2: 17/12/2025 | L2: Midnight | M2: 205 | N2: 35 | O2: =N2*M2 -> 7175
A3: 2 | B3: Paratha | C3: 16/12/2025 | D3: Breakfast | E3: 661 | F3: 35 | G3: =F3*E3 -> 23135 | I3: 2 | J3: Paratha | K3: 17/12/2025 | L3: Breakfast | M3: 700 | N3: 35 | O3: =N3*M3 -> 24500
A4: 3 | B4: Cahanna | C4: 16/12/2025 | D4: Breakfast | E4: 79 | F4: 80 | G4: =F4*E4 -> 6320 | I4: 3 | J4: Allo Ghotala | K4: 17/12/2025 | L4: Breakfast | M4: 85 | N4: 70 | O4: =N4*M4 -> 5950
A5: 4 | B5: Chay | C5: 16/12/2025 | D5: Breakfast | E5: =423+14 -> 437 | F5: 35 | G5: =F5*E5 -> 15295 | I5: 4 | J5: Chay | K5: 17/12/2025 | L5: Breakfast | M5: 450 | N5: 35 | O5: =N5*M5 -> 15750
A6: 5 | B6: Dall | C6: 16/12/2025 | D6: Lunch | E6: 327 | F6: 80 | G6: =F6*E6 -> 26160 | I6: 5 | J6: Sabzi | K6: 17/12/2025 | L6: Lunch | M6: 200 | N6: 80 | O6: =N6*M6 -> 16000
A7: 6 | B7: Rice | C7: 16/12/2025 | D7: Lunch | E7: 31 | F7: 100 | G7: =F7*E7 -> 3100 | I7: 6 | J7: Chicken Qorma | K7: 17/12/2025 | L7: Lunch | M7: 25 | N7: 200 | O7: =N7*M7 -> 5000
A8: 7 | B8: Chicken Karahi | C8: 16/12/2025 | D8: Lunch | E8: 6 | F8: 200 | G8: =F8*E8 -> 1200 | I8: 7 | J8: Chicken curry | K8: 17/12/2025 | L8: Lunch | M8: 250 | N8: 110 | O8: =N8*M8 -> 27500
A9: 8 | B9: Roti | C9: 16/12/2025 | D9: Lunch | E9: 1504 | F9: 15 | G9: =F9*E9 -> 22560 | I9: 8 | J9: Roti | K9: 17/12/2025 | L9: Lunch | M9: 2000 | N9: 15 | O9: =N9*M9 -> 30000
A10: 9 | B10: Chay | C10: 16/12/2025 | D10: Lunch | E10: 128 | F10: 35 | G10: =F10*E10 -> 4480 | I10: 9 | J10: Chay | K10: 17/12/2025 | L10: Lunch | M10: 200 | N10: 35 | O10: =N10*M10 -> 7000
A11: 10 | B11: Chay | C11: 16/12/2025 | D11: Afternoon | E11: 399 | F11: 35 | G11: =F11*E11 -> 13965 | I11: 10 | J11: Chay | K11: 17/12/2025 | L11: Afternoon | M11: 504 | N11: 35 | O11: =N11*M11 -> 17640
A12: 11 | B12: Sabzi | C12: 16/12/2025 | D12: Dinner | E12: 95 | F12: 80 | G12: =F12*E12 -> 7600 | I12: 11 | J12: Sabzi | K12: 17/12/2025 | L12: Dinner | M12: 100 | N12: 80 | O12: =N12*M12 -> 8000
A13: 12 | B13: Roti | C13: 16/12/2025 | D13: Dinner | E13: 651 | F13: 15 | G13: =F13*E13 -> 9765 | I13: 12 | J13: Roti | K13: 17/12/2025 | L13: Dinner | M13: 800 | N13: 15 | O13: =N13*M13 -> 12000
A14: 13 | B14: Chay | C14: 16/12/2025 | D14: Dinner | E14: 33.428571 | F14: 35 | G14: =F14*E14 -> 1170 | I14: 13 | J14: Chay | K14: 17/12/2025 | L14: Dinner | M14: 150 | N14: 35 | O14: =N14*M14 -> 5250
A15: Cash From Sale for tuck Shop | G15: =280+150 -> 430 | I15: Cash From Sale for tuck Shop | O15: =70+120+80+180 -> 450
A16: Total Cash In Hand Amount | G16: =SUM(G2:G14)-G15 -> 141120 | I16: TOTAL AMOUNT OF KITCHN | O16: =SUM(O2:O14)-O15 -> 181315
I17: 1 | J17: Channa Chat | K17: 17/12/2025 | L17: All Day | M17: 130 | N17: 120 | O17: =N17*M17 -> 15600
A18: CREDIT AMOUNT | I18: 2 | J18: Juice | K18: 17/12/2025 | L18: All Day | M18: 110 | N18: 150 | O18: =N18*M18 -> 16500
A19: SR# | B19: Department Name | C19: Date | D19: Time | E19: Amount | G19: G.Total | I19: TOTAL AMOUNT OF JUICE COUNTER | O19: =SUM(O17:O18) -> 32100
A20: 1 | B20: Steaching Deprt | C20: 16/12/2025 | D20: Breakfast, Lunch, Dinner | E20: 5480 | G20: =E20 -> 5480 | I20: Total Cash In Hand Amount | O20: =O16+O19 -> 213415
A21: 2 | B21: Dying | C21: 16/12/2025 | D21: Lunch, | E21: 345 | G21: =E21 -> 345 | I21: CREDIT AMOUNT
A22: 3 | B22: Admin | C22: 16/12/2025 | D22: Lunch | E22: 1125 | G22: =E22 -> 1125 | I22: SR# | J22: Department Name | K22: Date | L22: Time | M22: Amount | O22: G.Total
A23: 4 | B23: Printing | C23: 16/12/2025 | D23: Lunch | E23: 885 | G23: =E23 -> 885 | I23: 1 | J23: Dying | K23: 17/12/2025 | L23: Lunch | M23: 335 | O23: =M23 -> 335
A24: 5 | B24: Sampl | C24: 16/12/2025 | D24: Lunch | E24: 2090 | G24: =E24 -> 2090 | I24: 2 | J24: Admin | K24: 17/12/2025 | L24: Breakfast, Lunch | M24: 1520 | O24: =M24 -> 1520
A25: 6 | B25: Flow HCM | C25: 16/12/2025 | D25: Lunch | E25: 405 | G25: =E25 -> 405 | I25: 3 | J25: Senior Mess | K25: 17/12/2025 | L25: Lunch | M25: 1905 | O25: =M25 -> 1905
A26: 7 | B26: Senior Mess | C26: 16/12/2025 | D26: Lunch, Dinner | E26: 2090 | G26: =E26 -> 2090 | I26: 4 | J26: HR | K26: 17/12/2025 | L26: Lunch | M26: 1190 | O26: =M26 -> 1190
A27: TOTAL AMOUNT | G27: =SUM(G20:G26) -> 12420 | I27: TOTAL AMOUNT | O27: =SUM(O23:O26) -> 4950
A28: GRAND TOTAL AMOUNT | G28: =G16+G27 -> 153540 | I28: GRAND TOTAL AMOUNT | O28: =O20+O27 -> 218365
I30: SR# | J30: Item Name | K30: Date | L30: Time | M30: Total Head Count | N30: Rate | O30: Amount
I31: 1 | J31: Chay | K31: 19/12/2025 | L31: Midnight | M31: 189.42857 | N31: 35 | O31: =N31*M31 -> 6630
I32: 2 | J32: Paratha | K32: 19/12/2025 | L32: Breakfast | M32: 496 | N32: 35 | O32: =N32*M32 -> 17360
A33: SR# | B33: Item Name | C33: Date | D33: Time | E33: Total Head Count | F33: Rate | G33: Amount | I33: 3 | J33: Chana | K33: 19/12/2025 | L33: Breakfast | M33: 7 | N33: 80 | O33: =N33*M33 -> 560
A34: 1 | B34: Chay | C34: 18/12/2025 | D34: Midnight | E34: 182.57 | F34: 35 | G34: =F34*E34 -> 6389.95 | I34: 4 | J34: Chay | K34: 19/12/2025 | L34: Breakfast | M34: 385 | N34: 35 | O34: =N34*M34 -> 13475
A35: 2 | B35: Paratha | C35: 18/12/2025 | D35: Breakfast | E35: 412 | F35: 35 | G35: =F35*E35 -> 14420 | I35: 5 | J35: Dall | K35: 19/12/2025 | L35: Lunch | M35: 40 | N35: 80 | O35: =N35*M35 -> 3200
A36: 3 | B36: Anda Ghotala | C36: 18/12/2025 | D36: Breakfast | E36: 48 | F36: 70 | G36: =F36*E36 -> 3360 | I36: 6 | J36: Chay | K36: 19/12/2025 | L36: Lunch | M36: 99.42857 | N36: 35 | O36: =N36*M36 -> 3479.9999
A37: 4 | B37: Chay | C37: 18/12/2025 | D37: Breakfast | E37: 469 | F37: 35 | G37: =F37*E37 -> 16415 | I37: 7 | J37: Chicken Biryani | K37: 19/12/2025 | L37: Lunch | M37: 590 | N37: 180 | O37: =N37*M37 -> 106200
A38: 5 | B38: Pulao | C38: 18/12/2025 | D38: Lunch | E38: 91 | F38: 120 | G38: =F38*E38 -> 10920 | I38: 8 | J38: Roti | K38: 19/12/2025 | L38: Lunch | M38: 580 | N38: 15 | O38: =N38*M38 -> 8700
A39: 6 | B39: Anda Ghotala | C39: 18/12/2025 | D39: Lunch | E39: 38 | F39: 70 | G39: =F39*E39 -> 2660 | I39: 9 | J39: Chay | K39: 19/12/2025 | L39: Afternoon | M39: 343.71429 | N39: 35 | O39: =N39*M39 -> 12030
A40: 7 | B40: Dall | C40: 18/12/2025 | D40: Lunch | E40: 158 | F40: 80 | G40: =F40*E40 -> 12640 | I40: 10 | J40: Dall | K40: 19/12/2025 | L40: Dinner | M40: 39 | N40: 80 | O40: =N40*M40 -> 3120
A41: 8 | B41: Chay | C41: 18/12/2025 | D41: Lunch | E41: 136 | F41: 35 | G41: =F41*E41 -> 4760 | I41: 11 | J41: Pulao | K41: 19/12/2025 | L41: Dinner | M41: 66 | N41: 120 | O41: =N41*M41 -> 7920
A42: 9 | B42: Chicken Biryani | C42: 18/12/2025 | D42: Lunch | E42: 15 | F42: 180 | G42: =F42*E42 -> 2700 | I42: 12 | J42: Roti | K42: 19/12/2025 | L42: Dinner | M42: 289 | N42: 15 | O42: =N42*M42 -> 4335
A43: 10 | B43: Roti | C43: 18/12/2025 | D43: Lunch | E43: 1455 | F43: 15 | G43: =F43*E43 -> 21825 | I43: 13 | J43: Chay | K43: 19/12/2025 | L43: Dinner | M43: 40 | N43: 35 | O43: =N43*M43 -> 1400
A44: 11 | B44: Chicken Stew | C44: 18/12/2025 | D44: Lunch | E44: 17 | F44: 200 | G44: =F44*E44 -> 3400 | I44: Cash From Sale for tuck Shop | O44: =140+280+280 -> 700
A45: 12 | B45: Chay | C45: 18/12/2025 | D45: Afternoon | E45: 268.285 | F45: 35 | G45: =F45*E45 -> 9389.975 | I45: TOTAL AMOUNT OF KITCHN | O45: =SUM(O31:O43)-O44 -> 187710
A46: 13 | B46: Dall Chana | C46: 18/12/2025 | D46: Dinner | E46: 104 | F46: 80 | G46: =F46*E46 -> 8320 | I46: JUICE COUNTER
A47: 14 | B47: Chicken Karahi | C47: 18/12/2025 | D47: Dinner | E47: 2 | F47: 200 | G47: =F47*E47 -> 400 | I47: 1 | J47: Fruit Chat | K47: 19/12/2025 | L47: All Day | M47: 27 | N47: 120 | O47: =N47*M47 -> 3240
A48: 15 | B48: Roti | C48: 18/12/2025 | D48: Dinner | E48: 556 | F48: 15 | G48: =F48*E48 -> 8340 | I48: 2 | J48: Fruit | K48: 19/12/2025 | L48: All Day | M48: 1 | N48: 100 | O48: =N48*M48 -> 100
A49: 16 | B49: Chay | C49: 18/12/2025 | D49: Dinner | E49: 58 | F49: 35 | G49: =F49*E49 -> 2030 | I49: 3 | J49: Juice | K49: 19/12/2025 | L49: All Day | M49: 25 | N49: 150 | O49: =N49*M49 -> 3750
A50: 17 | B50: Rice | C50: 18/12/2025 | D50: Dinner | E50: 38 | F50: 100 | G50: =F50*E50 -> 3800 | I50: 4 | J50: Channa Chat | K50: 19/12/2025 | L50: All Day | M50: 40 | N50: 120 | O50: =N50*M50 -> 4800
A51: Cash From Sale for tuck Shop | G51: =350+200 -> 550 | I51: TOTAL AMOUNT OF JUICE COUNTER | O51: =SUM(O47:O50) -> 11890
A52: TOTAL AMOUNT OF KITCHN | G52: =SUM(G34:G50)-G51 -> 131219.92 | I52: Total Cash In Hand Amount | O52: =O45+O51 -> 199600
A53: JUICE COUNTER | I53: CREDIT AMOUNT
A54: 1 | B54: Fruit Chat | C54: 18/12/2025 | D54: All Day | E54: 58 | F54: 120 | G54: =F54*E54 -> 6960 | I54: SR# | J54: Department Name | K54: Date | L54: Time | M54: Amount | O54: G.Total
A55: 2 | B55: Fruit | C55: 18/12/2025 | D55: All Day | E55: 1 | F55: 350 | G55: =F55*E55 -> 350 | I55: 1 | J55: Dying | K55: 19/12/2025 | L55: Lunch, Dinner | M55: 5735 | O55: =M55 -> 5735
A56: 3 | B56: Juice | C56: 18/12/2025 | D56: All Day | E56: 34 | F56: 150 | G56: =F56*E56 -> 5100 | I56: 2 | J56: Steaching Deprt | K56: 19/12/2025 | L56: Breakfast, Lunch, Dinner | M56: 2420 | O56: =M56 -> 2420
A57: 4 | B57: Channa Chat | C57: 18/12/2025 | D57: All Day | E57: 79 | F57: 120 | G57: =F57*E57 -> 9480 | I57: 3 | J57: Admin | K57: 19/12/2025 | L57: Breakfast, Lunch | M57: 245 | O57: =M57 -> 245
A58: TOTAL AMOUNT OF JUICE COUNTER | G58: =SUM(G54:G57) -> 21890 | I58: 5 | J58: Sampl | K58: 19/12/2025 | L58: Lunch | M58: 1920 | O58: =M58 -> 1920
A59: Total Cash In Hand Amount | G59: =G52+G58 -> 153109.92 | I59: TOTAL AMOUNT | O59: =SUM(O55:O58) -> 10320
A60: CREDIT AMOUNT | I60: GRAND TOTAL AMOUNT | O60: =O45+O51+O59 -> 209920
A61: SR# | B61: Department Name | C61: Date | D61: Time | E61: Amount | G61: G.Total
A62: 1 | B62: Dying | C62: 18/12/2025 | D62: Lunch, Dinner | E62: 2480 | G62: =E62 -> 2480 | I62: SR# | J62: Item Name | K62: Date | L62: Time | M62: Total Head Count | N62: Rate | O62: Amount
A63: 2 | B63: Steaching Deprt | C63: 18/12/2025 | D63: Breakfast, Lunch, Dinner | E63: 9075 | G63: =E63 -> 9075 | I63: 1 | J63: Chay | K63: 21/12/2025 | L63: Midnight | M63: 150 | N63: 35 | O63: =N63*M63 -> 5250
A64: 3 | B64: Admin | C64: 18/12/2025 | D64: Breakfast, Lunch | E64: 1660 | G64: =E64 -> 1660 | I64: 2 | J64: Paratha | K64: 21/12/2025 | L64: Breakfast | M64: 379 | N64: 35 | O64: =N64*M64 -> 13265
A65: 4 | B65: Guest House | C65: 18/12/2025 | D65: Breakfast | E65: 250 | G65: =E65 -> 250 | I65: 3 | J65: Aloo Tarkari | K65: 21/12/2025 | L65: Breakfast | M65: 35 | N65: 80 | O65: =N65*M65 -> 2800
A66: 5 | B66: Sampl | C66: 18/12/2025 | D66: Lunch | E66: 1190 | G66: =E66 -> 1190 | I66: 4 | J66: Chay | K66: 21/12/2025 | L66: Breakfast | M66: 315.42857 | N66: 35 | O66: =N66*M66 -> 11040
A67: TOTAL AMOUNT | G67: =SUM(G62:G66) -> 14655 | I67: 5 | J67: Dall | K67: 21/12/2025 | L67: Lunch | M67: 139 | N67: 80 | O67: =N67*M67 -> 11120
A68: GRAND TOTAL AMOUNT | G68: =G52+G58+G67 -> 167764.92 | I68: 6 | J68: Chay | K68: 21/12/2025 | L68: Lunch | M68: 60 | N68: 35 | O68: =N68*M68 -> 2100
I69: 7 | J69: Chawal | K69: 21/12/2025 | L69: Lunch | M69: 76 | N69: 100 | O69: =N69*M69 -> 7600
I70: 8 | J70: Chicken karahi | K70: 21/12/2025 | L70: Lunch | M70: 2 | N70: 200 | O70: =N70*M70 -> 400
A71: SR# | B71: Item Name | C71: Date | D71: Time | E71: Total Head Count | F71: Rate | G71: Amount | I71: 9 | J71: Roti | K71: 21/12/2025 | L71: Lunch | M71: 654 | N71: 15 | O71: =N71*M71 -> 9810
A72: 1 | B72: Chay | C72: 20/12/2025 | D72: Midnight | E72: 158 | F72: 35 | G72: =F72*E72 -> 5530 | I72: 10 | J72: Chay | K72: 21/12/2025 | L72: Afternoon | M72: 219.4285 | N72: 35 | O72: =N72*M72 -> 7679.9975
A73: 2 | B73: Paratha | C73: 20/12/2025 | D73: Breakfast | E73: 582 | F73: 35 | G73: =F73*E73 -> 20370 | I73: 11 | J73: Pulao | K73: 21/12/2025 | L73: Dinner | M73: 23 | N73: 120 | O73: =N73*M73 -> 2760
A74: 3 | B74: Chana | C74: 20/12/2025 | D74: Breakfast | E74: 38 | F74: 80 | G74: =F74*E74 -> 3040 | I74: 12 | J74: Chicken Aloo Curry | K74: 21/12/2025 | L74: Dinner | M74: 34 | N74: 110 | O74: =N74*M74 -> 3740
A75: 4 | B75: Chay | C75: 20/12/2025 | D75: Breakfast | E75: 468 | F75: 30 | G75: =F75*E75 -> 14040 | I75: 13 | J75: Roti | K75: 21/12/2025 | L75: Dinner | M75: 286 | N75: 15 | O75: =N75*M75 -> 4290
A76: 5 | B76: Sabzi | C76: 20/12/2025 | D76: Lunch | E76: 200 | F76: 80 | G76: =F76*E76 -> 16000 | I76: 14 | J76: Chay | K76: 21/12/2025 | L76: Dinner | M76: 26 | N76: 30 | O76: =N76*M76 -> 780
A77: 6 | B77: Chay | C77: 20/12/2025 | D77: Lunch | E77: 103.71429 | F77: 35 | G77: =F77*E77 -> 3630 | I77: Cash From Sale for tuck Shop | O77: =400+350+120+140 -> 1010
A78: 7 | B78: Aloo Chawal | C78: 20/12/2025 | D78: Lunch | E78: 12 | F78: 120 | G78: =F78*E78 -> 1440 | I78: TOTAL AMOUNT OF KITCHN | O78: =SUM(O63:O76)-O77 -> 81624.997
A79: 8 | B79: Chicken Rajistani karahi | C79: 20/12/2025 | D79: Lunch | E79: 18 | F79: 200 | G79: =F79*E79 -> 3600 | I79: JUICE COUNTER
A80: 9 | B80: Roti | C80: 20/12/2025 | D80: Lunch | E80: 1426 | F80: 15 | G80: =F80*E80 -> 21390 | I80: 1 | J80: Mix Fruit | K80: 21/12/2025 | L80: All Day | M80: 1 | N80: 950 | O80: =N80*M80 -> 950
A81: 10 | B81: Chay | C81: 20/12/2025 | D81: Afternoon | E81: 343.71428 | F81: 35 | G81: =F81*E81 -> 12030 | I81: 2 | J81: Channa Chat | K81: 21/12/2025 | L81: All Day | M81: 53 | N81: 120 | O81: =N81*M81 -> 6360
A82: 11 | B82: Dall | C82: 20/12/2025 | D82: Dinner | E82: 31 | F82: 80 | G82: =F82*E82 -> 2480 | I82: TOTAL AMOUNT OF JUICE COUNTER | O82: =SUM(O80:O81) -> 7310
A83: 12 | B83: Chicken Aloo Curry | C83: 20/12/2025 | D83: Dinner | E83: 31 | F83: 110 | G83: =F83*E83 -> 3410 | I83: Total Cash In Hand Amount | O83: =O78+O82 -> 88934.997
A84: 13 | B84: Roti | C84: 20/12/2025 | D84: Dinner | E84: 405 | F84: 15 | G84: =F84*E84 -> 6075 | I84: CREDIT AMOUNT
A85: 14 | B85: Chay | C85: 20/12/2025 | D85: Dinner | E85: 34.585714 | F85: 35 | G85: =F85*E85 -> 1210.5 | I85: SR# | J85: Department Name | K85: Date | L85: Time | M85: Amount | O85: G.Total
A86: Cash From Sale for tuck Shop | G86: 2250 | I86: 1 | J86: Dying | K86: 21/12/2025 | L86: Lunch, Dinner | M86: 790 | O86: =M86 -> 790
A87: TOTAL AMOUNT OF KITCHN | G87: =SUM(G72:G85)-G86 -> 111995.5 | I87: 2 | J87: Steaching Deprt | K87: 21/12/2025 | L87: Breakfast, Lunch, Dinner | M87: 3980 | O87: =M87 -> 3980
A88: JUICE COUNTER | I88: TOTAL AMOUNT | O88: =SUM(O86:O87) -> 4770
A89: 1 | B89: Fruit Chat | C89: 20/12/2025 | D89: All Day | E89: 9 | F89: 120 | G89: =F89*E89 -> 1080 | I89: GRAND TOTAL AMOUNT | O89: =O78+O82+O88 -> 93704.997
A90: 2 | B90: Mix Fruit | C90: 20/12/2025 | D90: All Day | E90: 1 | F90: 550 | G90: 550
A91: 3 | B91: Juice | C91: 20/12/2025 | D91: All Day | E91: 23 | F91: 150 | G91: =F91*E91 -> 3450 | I91: SR# | J91: Item Name | K91: Date | L91: Time | M91: Total Head Count | N91: Rate | O91: Amount
A92: 4 | B92: Channa Chat | C92: 20/12/2025 | D92: All Day | E92: 54 | F92: 120 | G92: =F92*E92 -> 6480 | I92: 1 | J92: Chay | K92: 23/12/2025 | L92: Midnight | M92: 138.8571 | N92: 35 | O92: =N92*M92 -> 4859.9985
A93: 5 | B93: Dahi | C93: 20/12/2025 | D93: All Day | E93: 13 | F93: 100 | G93: =F93*E93 -> 1300 | I93: 2 | J93: Paratha | K93: 23/12/2025 | L93: Breakfast | M93: 472 | N93: 35 | O93: =N93*M93 -> 16520
A94: TOTAL AMOUNT OF JUICE COUNTER | G94: =SUM(G89:G93) -> 12860 | I94: 3 | J94: Channa | K94: 23/12/2025 | L94: Breakfast | M94: 37 | N94: 80 | O94: =N94*M94 -> 2960
A95: Total Cash In Hand Amount | G95: =G87+G94 -> 124855.5 | I95: 4 | J95: Chay | K95: 23/12/2025 | L95: Breakfast | M95: 369.4285 | N95: 35 | O95: =N95*M95 -> 12929.997
A96: CREDIT AMOUNT | I96: 5 | J96: Biryani White | K96: 23/12/2025 | L96: Lunch | M96: 25 | N96: 180 | O96: =N96*M96 -> 4500
A97: SR# | B97: Department Name | C97: Date | D97: Time | E97: Amount | G97: G.Total | I97: 6 | J97: Chay | K97: 23/12/2025 | L97: Lunch | M97: 135 | N97: 35 | O97: =N97*M97 -> 4725
A98: 1 | B98: Dying | C98: 20/12/2025 | D98: Lunch, Dinner | E98: 3120 | G98: =E98 -> 3120 | I98: 7 | J98: Dall | K98: 23/12/2025 | L98: Lunch | M98: 149 | N98: 80 | O98: =N98*M98 -> 11920
A99: 2 | B99: Steaching Deprt | C99: 20/12/2025 | D99: Breakfast, Lunch, Dinner | E99: 9285 | G99: =E99 -> 9285 | I99: 8 | J99: Chicken karahi | K99: 23/12/2025 | L99: Lunch | M99: 16 | N99: 200 | O99: =N99*M99 -> 3200
A100: 3 | B100: Maintenances | C100: 20/12/2025 | D100: Lunch | E100: 440 | G100: =E100 -> 440 | I100: 9 | J100: Roti | K100: 23/12/2025 | L100: Lunch | M100: 1022 | N100: 15 | O100: =N100*M100 -> 15330
A101: 5 | B101: Sampl | C101: 20/12/2025 | D101: Lunch | E101: 9640 | G101: =E101 -> 9640 | I101: 10 | J101: Channa | K101: 23/12/2025 | L101: Lunch | M101: 22 | N101: 80 | O101: =N101*M101 -> 1760
...

Sheet Cash Out From Sale
A1: Cash From Sale
A2: SR# | B2: Name | C2: Amount
A3: 1 | B3: Sadi Bhai For Purcahse | C3: 100000
A4: 2 | B4: Vijay Room Boy | C4: 3500
A5: 3 | B5: Youget | C5: 2560
A6: 4 | B6: Darshan Pay 1000+500 | C6: 1500
A7: 5 | B7: Milk Payment | C7: 14300
A8: 6 | B8: Cook Satalment | C8: 25666
A9: 7 | B9: Sadi Bhai For Purcahse | C9: 8050
A10: 8 | B10: Sadi Bhai For Purcahse | C10: 5000
A11: 9 | B11: Ashiq Hussain Advance | C11: 3000
A12: 10 | B12: Sadi Bhai For Purcahse | C12: 42720
A13: 11 | B13: Shahid Sb For Purchase | C13: 42000
A14: 12 | B14: Sadi Bhai For Purcahse 26-Dec-2025 | C14: 35000
... A64: 62 | B64: Bartan Jali | C64: 60
A65: 63 | B65: Sadi Bhai For Purchase 14-Jan-2026 | C65: =60000-1750-1250 -> 57000
A66: 64 | B66: Ali Passand salary of dec 2025 | C66: 26067
A67: 65 | B67: Ayaz Dishwasheer Advance 14-Jan-2026 | C67: 5000
A68: 66 | B68: Ramzan Waiter advance 17-Jan-2026 | C68: 10000
A69: 67 | B69: Sadi Bhai for purchase 17-Jan-2026 | C69: 25000
A70: 68 | B70: Poran Salry finel setlemnet 17-Jan-2026 | C70: 18133
A71: 68 | B71: Asif Samosa Maker 17-Jan-2026 | C71: 9000
A72: 69 | B72: Spunge 3 nos 17-Jan-2026 | C72: 180
A73: 70 | B73: For Tomato Purchase 18-Jan-2026 | C73: 720
A74: 71 | B74: Dahi,Tomato, Shoping Bag, Rice 19-Jan-2026 | C74: 1970
A75: 72 | B75: Sadi Bhai for Purchase 19-Jan-2026 | C75: =25000-6634 -> 18366
A76: 73 | B76: Sadi Bhai Purchase Sabzi Fruit | C76: 26040
A77: 74 | B77: Cash Handover to Javed sb for deposit | C77: 900000
A78: 75 | B78: Cash Handover to shahid sb for Change | C78: 100000
A79: 76 | B79: Sadi Bhai for Aalo And Tomato Purchase | C79: 15000
A80: 77 | B80: Milk Payment 20-Jan-2026 | C80: 20900
A81: 78 | B81: Shoping Bag 3 Sizes 20-Jan-2026 | C81: 1800
B82: Manzoor Cook Advance 20-Jan-2026 | C82: 10000
A83: Total Advance amount from cash | C83: =SUM(C3:C82) -> 4371561

Sheet Daily material use, price sheet
I1: Working on 18-Jan-26
A2: Date | B2: Day | C2: Meal Type | D2: Material | E2: Qty | F2: Unit | G2: Price | H2: Amount | I2: Total Material Cost
A3: 16-21 Dec-25 | B3: Tue - Sun | C3: Refreshment | D3: Milk Powder | E3: 54.5 | F3: Kg | G3: 1400 | H3: =Table3[[#This Row],[Qty]]*Table3[[#This Row],[Price]] -> 76300
A4: 16-21 Dec-25 | B4: Tue - Sun | C4: Refreshment | D4: Sugar | E4: 159.5 | F4: Kg | G4: 170 | H4: =Table3[[#This Row],[Qty]]*Table3[[#This Row],[Price]] -> 27115
A5: 16-21 Dec-25 | B5: Tue - Sun | C5: All Meals | D5: Red Chilli Powder | E5: 7 | F5: Kg | G5: 650 | H5: =Table3[[#This Row],[Qty]]*Table3[[#This Row],[Price]] -> 4550
A6: 16-21 Dec-25 | B6: Tue - Sun | C6: All Meals | D6: Red Chilli Whole | E6: 1 | F6: Kg | G6: 650 | H6: =Table3[[#This Row],[Qty]]*Table3[[#This Row],[Price]] -> 650
A7: 16-21 Dec-25 | B7: Tue - Sun | C7: All Meals | D7: Rice | E7: 211 | F7: Kg | G7: 300 | H7: =Table3[[#This Row],[Qty]]*Table3[[#This Row],[Price]] -> 63300
A8: 16-21 Dec-25 | B8: Tue - Sun | C8: All Meals | D8: Cooking Oil | E8: 140 | F8: Ltr | G8: 443.33 | H8: =Table3[[#This Row],[Qty]]*Table3[[#This Row],[Price]] -> 62066.2
A9: 16-21 Dec-25 | B9: Tue - Sun | C9: All Meals | D9: Atta Fine | E9: 600 | F9: Kg | G9: 119 | H9: =Table3[[#This Row],[Qty]]*Table3[[#This Row],[Price]] -> 71400
A10: 16-21 Dec-25 | B10: Tue - Sun | C10: All Meals | D10: Atta Chakki | E10: 950 | F10: Kg | G10: 113 | H10: =Table3[[#This Row],[Qty]]*Table3[[#This Row],[Price]] -> 107350
A11: 16-21 Dec-25 | B11: Tue - Sun | C11: Lunch | D11: Coriender Powder | E11: 6 | F11: Kg | G11: 580 | H11: =Table3[[#This Row],[Qty]]*Table3[[#This Row],[Price]] -> 3480
A12: 16-21 Dec-25 | B12: Tue - Sun | C12: Lunch | D12: Zeera | E12: 3.5 | F12: Kg | G12: 1150 | H12: =Table3[[#This Row],[Qty]]*Table3[[#This Row],[Price]] -> 4025
A13: 16-21 Dec-25 | B13: Tue - Sun | C13: All Meals | D13: Brown Piyaz Fried | E13: 23 | F13: Kg | G13: 560 | H13: =Table3[[#This Row],[Qty]]*Table3[[#This Row],[Price]] -> 12880
A14: 16-21 Dec-25 | B14: Tue - Sun | C14: Lunch | D14: Daal Channa | E14: 13 | F14: Kg | G14: 210 | H14: =Table3[[#This Row],[Qty]]*Table3[[#This Row],[Price]] -> 2730
... A53: 16-21 Dec-25 | B53: Tue - Sun | C53: Refreshment | D53: Yogurt | E53: 8 | F53: Kg | G53: 320 | H53: =Table3[[#This Row],[Qty]]*Table3[[#This Row],[Price]] -> 2560
A54: 46013 | B54: Monday | C54: Refreshment | D54: Fresh Milk | E54: 10 | F54: Ltr | G54: 220 | H54: =Table3[[#This Row],[Qty]]*Table3[[#This Row],[Price]] -> 2200
A55: 46013 | B55: Monday | C55: Refreshment | D55: Milk Powder | E55: 11 | F55: Kg | G55: 1400 | H55: =Table3[[#This Row],[Qty]]*Table3[[#This Row],[Price]] -> 15400
A56: 46013 | B56: Monday | C56: Refreshment | D56: Sugar | E56: 22.85 | F56: Kg | G56: 170 | H56: =Table3[[#This Row],[Qty]]*Table3[[#This Row],[Price]] -> 3884.5
A57: 46013 | B57: Monday | C57: All Meals | D57: Rice | E57: 24 | F57: Kg | G57: 300 | H57: =Table3[[#This Row],[Qty]]*Table3[[#This Row],[Price]] -> 7200
A58: 46013 | B58: Monday | C58: All Meals | D58: Cooking Oil | E58: 39 | F58: Ltr | G58: 443.33 | H58: =Table3[[#This Row],[Qty]]*Table3[[#This Row],[Price]] -> 17289.87
A59: 46013 | B59: Monday | C59: All Meals | D59: Atta Fine | E59: 100 | F59: Kg | G59: 119 | H59: =Table3[[#This Row],[Qty]]*Table3[[#This Row],[Price]] -> 11900
A60: 46013 | B60: Monday | C60: All Meals | D60: Atta Chakki | E60: 125 | F60: Kg | G60: 113 | H60: =Table3[[#This Row],[Qty]]*Table3[[#This Row],[Price]] -> 14125
A61: 46013 | B61: Monday | C61: All Meals | D61: Brown Piyaz Fried | E61: 2.5 | F61: Kg | G61: 560 | H61: =Table3[[#This Row],[Qty]]*Table3[[#This Row],[Price]] -> 1400
A62: 46013 | B62: Monday | C62: Lunch | D62: Daal Channa | E62: 3 | F62: Kg | G62: 210 | H62: =Table3[[#This Row],[Qty]]*Table3[[#This Row],[Price]] -> 630
A63: 46013 | B63: Monday | C63: All Meals | D63: Achar Gosht Masala | E63: 0.5 | F63: Kg | G63: 580 | H63: =Table3[[#This Row],[Qty]]*Table3[[#This Row],[Price]] -> 290
A64: 46013 | B64: Monday | C64: All Meals | D64: Pulao Masala | E64: 0.5 | F64: Kg | G64: 580 | H64: =Table3[[#This Row],[Qty]]*Table3[[#This Row],[Price]] -> 290
A65: 46013 | B65: Monday | C65: All Meals | D65: Papri | E65: 10 | F65: Kg | G65: 490 | H65: =Table3[[#This Row],[Qty]]*Table3[[#This Row],[Price]] -> 4900
... A315: 46022 | B315: Wednesday | C315: Lunch | D315: Coriender Powder | E315: 1.5 | F315: Kg | G315: 580 | H315: =Table3[[#This Row],[Qty]]*Table3[[#This Row],[Price]] -> 870
A316: 46022 | B316: Wednesday | C316: Lunch | D316: Match Box | E316: 50 | F316: Box | H316: =Table3[[#This Row],[Qty]]*Table3[[#This Row],[Price]] -> 0
A317: 46022 | B317: Wednesday | C317: Lunch | D317: Coriender Dry Whole | E317: 1 | F317: Kg | G317: 530 | H317: =Table3[[#This Row],[Qty]]*Table3[[#This Row],[Price]] -> 530
A318: 46022 | B318: Wednesday | C318: Lunch | D318: Maida | E318: 12 | F318: Kg | G318: 120 | H318: =Table3[[#This Row],[Qty]]*Table3[[#This Row],[Price]] -> 1440
A319: 46022 | B319: Wednesday | C319: Lunch | D319: Cucumber | E319: 0.5 | F319: Kg | G319: 95 | H319: =Table3[[#This Row],[Qty]]*Table3[[#This Row],[Price]] -> 47.5
A320: 46022 | B320: Wednesday | C320: Lunch | D320: Carrot | E320: 1.25 | F320: Kg | G320: 90 | H320: =Table3[[#This Row],[Qty]]*Table3[[#This Row],[Price]] -> 112.5
A321: 46022 | B321: Wednesday | C321: Lunch | D321: Chukandar | E321: 0.3 | F321: Kg | G321: 50 | H321: =Table3[[#This Row],[Qty]]*Table3[[#This Row],[Price]] -> 15
A322: 46022 | B322: Wednesday | C322: Lunch | D322: Karahi Masala | E322: 0.3 | F322: Kg | G322: 580 | H322: =Table3[[#This Row],[Qty]]*Table3[[#This Row],[Price]] -> 174
A323: 46022 | B323: Wednesday | C323: Lunch | D323: Brown Piyaz Fried | E323: 2 | F323: Kg | G323: 560 | H323: =Table3[[#This Row],[Qty]]*Table3[[#This Row],[Price]] -> 1120
A324: 46022 | B324: Wednesday | C324: Breakfast | D324: Channa | E324: 2 | F324: Kg | G324: 183 | H324: =Table3[[#This Row],[Qty]]*Table3[[#This Row],[Price]] -> 366
A325: 46022 | B325: Wednesday | C325: Lunch | D325: Shopping Bags 12 x16 | E325: 3.5 | F325: Kg | G325: 500 | H325: =Table3[[#This Row],[Qty]]*Table3[[#This Row],[Price]] -> 1750
A326: 46022 | B326: Wednesday | C326: Lunch | D326: Ginger / Adrak | E326: 0.005 | F326: Kg | G326: 350 | H326: =Table3[[#This Row],[Qty]]*Table3[[#This Row],[Price]] -> 1.75
A327: 46022 | B327: Wednesday | C327: Lunch | D327: Salt | E327: 3 | F327: Kg | G327: 12 | H327: =Table3[[#This Row],[Qty]]*Table3[[#This Row],[Price]] -> 36
A328: 46022 | B328: Wednesday | C328: Refreshment | D328: Comelle - Condensed Milk | E328: 1 | F328: Tin | G328: 896 | H328: =Table3[[#This Row],[Qty]]*Table3[[#This Row],[Price]] -> 896
... A411: 46024 | B411: Friday | C411: Lunch | D411: Kewra Water | E411: 1 | F411: Botel | G411: 65 | H411: =Table3[[#This Row],[Qty]]*Table3[[#This Row],[Price]] -> 65
A412: 46024 | B412: Friday | C412: Lunch | D412: Chinese Salt | E412: 0.35 | F412: Kg | H412: =Table3[[#This Row],[Qty]]*Table3[[#This Row],[Price]] -> 0
A413: 46024 | B413: Friday | C413: Lunch | D413: Zeera | E413: 1 | F413: Kg | G413: 1150 | H413: =Table3[[#This Row],[Qty]]*Table3[[#This Row],[Price]] -> 1150
A414: 46024 | B414: Friday | C414: Refreshment | D414: Sugar | E414: 6.5 | F414: Kg | G414: 170 | H414: =Table3[[#This Row],[Qty]]*Table3[[#This Row],[Price]] -> 1105
A415: 46024 | B415: Friday | C415: Refreshment | D415: Milk Powder | E415: 2 | F415: Kg | G415: 1400 | H415: =Table3[[#This Row],[Qty]]*Table3[[#This Row],[Price]] -> 2800
A416: 46024 | B416: Friday | C416: Lunch | D416: Green Chilli | E416: 0.65 | F416: Kg | G416: 150 | H416: =Table3[[#This Row],[Qty]]*Table3[[#This Row],[Price]] -> 97.5
A417: 46024 | B417: Friday | C417: Lunch | D417: Haldi | E417: 2 | F417: Kg | G417: 700 | H417: =Table3[[#This Row],[Qty]]*Table3[[#This Row],[Price]] -> 1400
A418: 46024 | B418: Friday | C418: Lunch | D418: Red chilli Powder | E418: 2 | F418: Kg | G418: 650 | H418: =Table3[[#This Row],[Qty]]*Table3[[#This Row],[Price]] -> 1300
A419: 46024 | B419: Friday | C419: Lunch | D419: Red Chilli Crushed | E419: 2 | F419: Kg | G419: 700 | H419: =Table3[[#This Row],[Qty]]*Table3[[#This Row],[Price]] -> 1400
A420: 46024 | B420: Friday | C420: Lunch | D420: Onion | E420: 4 | F420: Kg | G420: 75 | H420: =Table3[[#This Row],[Qty]]*Table3[[#This Row],[Price]] -> 300
A421: 46024 | B421: Friday | C421: Lunch | D421: Cucumber | E421: 0.5 | F421: Kg | G421: 95 | H421: =Table3[[#This Row],[Qty]]*Table3[[#This Row],[Price]] -> 47.5
A422: 46024 | B422: Friday | C422: Lunch | D422: Carrot | E422: 0.5 | F422: Kg | G422: 90 | H422: =Table3[[#This Row],[Qty]]*Table3[[#This Row],[Price]] -> 45
A423: 46024 | B423: Friday | C423: Lunch | D423: Chukandar | E423: 0.4 | F423: Kg | G423: 50 | H423: =Table3[[#This Row],[Qty]]*Table3[[#This Row],[Price]] -> 20
A424: 46024 | B424: Friday | C424: Lunch | D424: Egg | E424: 2 | F424: Nos | G424: 30 | H424: =Table3[[#This Row],[Qty]]*Table3[[#This Row],[Price]] -> 60
... A474: 46025 | B474: Saturday | C474: Dinner | D474: Beef Mince | E474: 1.2 | F474: Kg | G474: 1600 | H474: =Table3[[#This Row],[Qty]]*Table3[[#This Row],[Price]] -> 1920
A475: 46025 | B475: Saturday | C475: Dinner | D475: Shimla Mirch | E475: 3 | F475: Kg | H475: =Table3[[#This Row],[Qty]]*Table3[[#This Row],[Price]] -> 0
A476: 46025 | B476: Saturday | C476: Dinner | D476: Potato | E476: 2 | F476: Kg | G476: 50 | H476: =Table3[[#This Row],[Qty]]*Table3[[#This Row],[Price]] -> 100
A477: 46025 | B477: Saturday | C477: Refreshment | D477: Fresh Milk | E477: 14 | F477: Ltr | G477: 220 | H477: =Table3[[#This Row],[Qty]]*Table3[[#This Row],[Price]] -> 3080
A478: 46025 | B478: Saturday | C478: Breakfast | D478: Channa | E478: 2 | F478: Kg | G478: 183 | H478: =Table3[[#This Row],[Qty]]*Table3[[#This Row],[Price]] -> 366
A479: 46025 | B479: Saturday | C479: Dinner | D479: Cucumber | E479: 0.1 | F479: Kg | G479: 95 | H479: =Table3[[#This Row],[Qty]]*Table3[[#This Row],[Price]] -> 9.5
A480: 46025 | B480: Saturday | C480: Dinner | D480: Green Chilli | E480: 0.25 | F480: Kg | G480: 150 | H480: =Table3[[#This Row],[Qty]]*Table3[[#This Row],[Price]] -> 37.5
A481: 46025 | B481: Saturday | C481: Dinner | D481: Coriender Green | E481: 0.1 | F481: Kg | G481: 230 | H481: =Table3[[#This Row],[Qty]]*Table3[[#This Row],[Price]] -> 23
A482: 46025 | B482: Saturday | C482: Refreshment | D482: Sugar | E482: 4.5 | F482: Kg | G482: 170 | H482: =Table3[[#This Row],[Qty]]*Table3[[#This Row],[Price]] -> 765
A483: 46025 | B483: Saturday | C483: Refreshment | D483: Apple | E483: 15 | F483: Kg | G483: 220 | H483: =Table3[[#This Row],[Qty]]*Table3[[#This Row],[Price]] -> 3300
A484: 46025 | B484: Saturday | C484: Refreshment | D484: Melon | E484: 15 | F484: Kg | G484: 110 | H484: =Table3[[#This Row],[Qty]]*Table3[[#This Row],[Price]] -> 1650
A485: 46025 | B485: Saturday | C485: Refreshment | D485: Milk Powder | E485: 1.75 | F485: Kg | G485: 1400 | H485: =Table3[[#This Row],[Qty]]*Table3[[#This Row],[Price]] -> 2450
A486: 46025 | B486: Saturday | C486: Dinner | D486: Salt | E486: 2 | F486: Kg | G486: 12 | H486: =Table3[[#This Row],[Qty]]*Table3[[#This Row],[Price]] -> 24
A487: 46025 | B487: Saturday | C487: Dinner | D487: Cooking Oil | E487: 5 | F487: Ltr | G487: 443.33 | H487: =Table3[[#This Row],[Qty]]*Table3[[#This Row],[Price]] -> 2216.65
... A612: 46029 | B612: Wednesday | C612: Lunch | D612: Beef | E612: 8 | F612: Kg | G612: 1600 | H612: =Table3[[#This Row],[Qty]]*Table3[[#This Row],[Price]] -> 12800
A613: 46029 | B613: Wednesday | C613: Lunch | D613: Beef Hadi Gudi | E613: 2.2 | F613: Kg | H613: =Table3[[#This Row],[Qty]]*Table3[[#This Row],[Price]] -> 0
A614: 46029 | B614: Wednesday | C614: Lunch | D614: Tomato | E614: 11 | F614: Kg | G614: 40 | H614: =Table3[[#This Row],[Qty]]*Table3[[#This Row],[Price]] -> 440
A615: 46029 | B615: Wednesday | C615: Lunch | D615: Potato | E615: 16 | F615: Kg | G615: 50 | H615: =Table3[[#This Row],[Qty]]*Table3[[#This Row],[Price]] -> 800
A616: 46029 | B616: Wednesday | C616: Lunch | D616: Onion | E616: 3 | F616: Kg | G616: 75 | H616: =Table3[[#This Row],[Qty]]*Table3[[#This Row],[Price]] -> 225
A617: 46029 | B617: Wednesday | C617: Lunch | D617: Cucumber | E617: 0.5 | F617: Kg | G617: 95 | H617: =Table3[[#This Row],[Qty]]*Table3[[#This Row],[Price]] -> 47.5
A618: 46029 | B618: Wednesday | C618: Lunch | D618: Carrot | E618: 0.5 | F618: Kg | G618: 90 | H618: =Table3[[#This Row],[Qty]]*Table3[[#This Row],[Price]] -> 45
A619: 46029 | B619: Wednesday | C619: Lunch | D619: Gobhi | E619: 0.5 | F619: Kg | G619: 80 | H619: =Table3[[#This Row],[Qty]]*Table3[[#This Row],[Price]] -> 40
A620: 46029 | B620: Wednesday | C620: Lunch | D620: Kewra Water | E620: 1 | F620: Botel | G620: 65 | H620: =Table3[[#This Row],[Qty]]*Table3[[#This Row],[Price]] -> 65
A621: 46029 | B621: Wednesday | C621: Lunch | D621: Chinese Salt | E621: 0.1 | F621: Kg | H621: =Table3[[#This Row],[Qty]]*Table3[[#This Row],[Price]] -> 0
A622: 46029 | B622: Wednesday | C622: Lunch | D622: Pulao Masala | E622: 1 | F622: Kg | G622: 580 | H622: =Table3[[#This Row],[Qty]]*Table3[[#This Row],[Price]] -> 580
A623: 46029 | B623: Wednesday | C623: Refreshment | D623: Cooking Ghee | E623: 2 | F623: Kg | G623: 500 | H623: =Table3[[#This Row],[Qty]]*Table3[[#This Row],[Price]] -> 1000
A624: 46029 | B624: Wednesday | C624: Lunch | D624: Maida | E624: 10 | F624: Kg | G624: 120 | H624: =Table3[[#This Row],[Qty]]*Table3[[#This Row],[Price]] -> 1200
A625: 46029 | B625: Wednesday | C625: Lunch | D625: Brown Piyaz Fried | E625: 2 | F625: Kg | G625: 560 | H625: =Table3[[#This Row],[Qty]]*Table3[[#This Row],[Price]] -> 1120
A626: 46029 | B626: Wednesday | C626: Lunch | D626: Green Chilli | E626: 1 | F626: Kg | G626: 150 | H626: =Table3[[#This Row],[Qty]]*Table3[[#This Row],[Price]] -> 150
A627: 46029 | B627: Wednesday | C627: Lunch | D627: Coriender Green | E627: 0.7 | F627: Kg | G627: 230 | H627: =Table3[[#This Row],[Qty]]*Table3[[#This Row],[Price]] -> 161
A628: 46029 | B628: Wednesday | C628: Lunch | D628: Salt | E628: 5 | F628: Kg | G628: 60 | H628: =Table3[[#This Row],[Qty]]*Table3[[#This Row],[Price]] -> 300
A629: 46029 | B629: Wednesday | C629: Refreshment | D629: Sugar | E629: 6.35 | F629: Kg | G629: 170 | H629: =Table3[[#This Row],[Qty]]*Table3[[#This Row],[Price]] -> 1079.5
A630: 46029 | B630: Wednesday | C630: Refreshment | D630: Milk Powder | E630: 4.27 | F630: Kg | G630: 1400 | H630: =Table3[[#This Row],[Qty]]*Table3[[#This Row],[Price]] -> 5978
A631: 46029 | B631: Wednesday | C631: Refreshment | D631: Fresh Milk | E631: 10 | F631: Ltr | G631: 220 | H631: =Table3[[#This Row],[Qty]]*Table3[[#This Row],[Price]] -> 2200
A632: 46029 | B632: Wednesday | C632: Refreshment | D632: Tea Patti | E632: 1 | F632: Kg | G632: 1600 | H632: =Table3[[#This Row],[Qty]]*Table3[[#This Row],[Price]] -> 1600
A633: 46029 | B633: Wednesday | C633: Dinner | D633: Cooking Oil | E633: 2 | F633: Ltr | G633: 443.33 | H633: =Table3[[#This Row],[Qty]]*Table3[[#This Row],[Price]] -> 886.66
... A653: 46030 | B653: Thursday | C653: Lunch | D653: Cooking Oil | E653: 8 | F653: Ltr | G653: 443.33 | H653: =Table3[[#This Row],[Qty]]*Table3[[#This Row],[Price]] -> 3546.64
A654: 46030 | B654: Thursday | C654: Lunch | D654: Chicken | E654: 10 | F654: Kg | H654: =Table3[[#This Row],[Qty]]*Table3[[#This Row],[Price]] -> 0
A655: 46030 | B655: Thursday | C655: Lunch | D655: Lobia | E655: 2.5 | F655: Kg | H655: =Table3[[#This Row],[Qty]]*Table3[[#This Row],[Price]] -> 0
A656: 46030 | B656: Thursday | C656: Lunch | D656: Daal Channa | E656: 5 | F656: Kg | G656: 210 | H656: =Table3[[#This Row],[Qty]]*Table3[[#This Row],[Price]] -> 1050
A657: 46030 | B657: Thursday | C657: Lunch | D657: Onion | E657: 3 | F657: Kg | G657: 75 | H657: =Table3[[#This Row],[Qty]]*Table3[[#This Row],[Price]] -> 225
A658: 46030 | B658: Thursday | C658: Lunch | D658: Cucumber | E658: 0.9 | F658: Kg | G658: 95 | H658: =Table3[[#This Row],[Qty]]*Table3[[#This Row],[Price]] -> 85.5
A659: 46030 | B659: Thursday | C659: Lunch | D659: Carrot | E659: 0.8 | F659: Kg | G659: 80 | H659: =Table3[[#This Row],[Qty]]*Table3[[#This Row],[Price]] -> 64
A660: 46030 | B660: Thursday | C660: Lunch | D660: Coriender Dry Whole | E660: 1.5 | F660: Kg | G660: 530 | H660: =Table3[[#This Row],[Qty]]*Table3[[#This Row],[Price]] -> 795
A661: 46030 | B661: Thursday | C661: Lunch | D661: Brown Piyaz Fried | E661: 1 | F661: Kg | G661: 560 | H661: =Table3[[#This Row],[Qty]]*Table3[[#This Row],[Price]] -> 560
...

Sheet Voucher
A2: Mujtaba And Borthers
A3: SR# | B3: Date | C3: Name | D3: Amount
A4: 1 | B4: 46023 | C4: Riaz Ali Advance Payment | D4: 11000
A6: Total Pay Amount | D6: 11000
A8: Prepared By | C8: Approved By | D8: Received By
A10: Mujtaba And Borthers
A11: SR# | B11: Date | C11: Name | D11: Amount
A12: 1 | B12: 46023 | C12: Rent For Dags And Fridge | D12: 8000
C13: Tool Tex | D13: 400
A14: Total Pay Amount | D14: =SUM(D12:D13) -> 8400
A16: Prepared By | C16: Approved By | D16: Received By
A18: Mujtaba And Borthers
A19: SR# | B19: Date | C19: Name | D19: Amount
A20: 1 | B20: 46024 | C20: Muhammad Ali Advance Payment | D20: 1000
A22: Total Pay Amount | D22: =SUM(D20:D21) -> 1000
A23: Prepared By | C23: Approved By | D23: Received By
A25: Mujtaba And Borthers
A26: SR# | B26: Date | C26: Name | D26: Amount
A27: 1 | B27: 46024 | C27: Dost Ali Advance Payment | D27: 10000
A29: Total Pay Amount | D29: =SUM(D27:D28) -> 10000
A30: Prepared By | C30: Approved By | D30: Received By
A32: Mujtaba And Borthers
A33: SR# | B33: Date | C33: Name | D33: Amount
A34: 1 | B34: 46024 | C34: Suhrab Advance Payment | D34: 1000
A36: Total Pay Amount | D36: =SUM(D34:D35) -> 1000
A37: Prepared By | C37: Approved By | D37: Received By
A39: Mujtaba And Borthers
A40: SR# | B40: Date | C40: Name | D40: Amount
A41: 1 | B41: 46025 | C41: Hussain Advance Payment | D41: 20000
A43: Total Pay Amount | D43: =SUM(D41:D42) -> 20000
A44: Prepared By | C44: Approved By | D44: Received By
A46: Mujtaba And Borthers
A47: SR# | B47: Date | C47: Name | D47: Amount
A48: 1 | B48: 46025 | C48: Amir Ali Cook Salary for 10 Days(25-Dec to 03Jan 2026) | D48: 16666
A50: Total Pay Amount | D50: =SUM(D48:D49) -> 16666
A51: Prepared By | C51: Approved By | D51: Received By
A53: Mujtaba And Borthers
A54: SR# | B54: Date | C54: Name | D54: Amount
A55: 1 | B55: 46025 | C55: Ashiq hussain Salary for 27 Days(09-Dec to 04Jan 2026) | D55: =1400*27 -> 37800
A57: Total Pay Amount | D57: =SUM(D55:D56) -> 37800
A58: Prepared By | C58: Approved By | D58: Received By
A60: Mujtaba And Borthers
A61: SR# | B61: Date | C61: Name | D61: Amount
A62: 1 | B62: 46026 | C62: Asif Samosa Maker 8 Days payment (1500 per day) | D62: =1500*8 -> 12000
A64: Total Pay Amount | D64: =SUM(D62:D63) -> 12000
A65: Prepared By | C65: Approved By
A67: Mujtaba And Borthers
A68: SR# | B68: Date | C68: Name | D68: Amount
A69: 1 | B69: 46027 | C69: Suhrab Ali 22 Days Payment (Dec) | D69: 24933
A71: Total Pay Amount | D71: =SUM(D69:D70) -> 24933
A72: Prepared By | C72: Approved By | D72: Received By
A74: Mujtaba And Borthers
A75: SR# | B75: Date | C75: Name | D75: Amount
A76: 1 | B76: 46032 | C76: Cash Handover to Waqas bhai for deposit | D76: 700000
A78: Total Pay Amount | D78: =SUM(D76:D77) -> 700000
A79: Prepared By | C79: Approved By | D79: Received By
A81: Mujtaba And Borthers
A82: SR# | B82: Date | C82: Name | D82: Amount
A83: 1 | B83: 46034 | C83: Ali Raza 10 Days Payment (Jan) | D83: 13333
A85: Total Pay Amount | D85: =SUM(D83:D84) -> 13333
A86: Prepared By | C86: Approved By | D86: Received By
A88: Mujtaba And Borthers
A89: SR# | B89: Date | C89: Name | D89: Amount
A90: 1 | B90: 46034 | C90: Asif Samosa Maker 6 Days payment (1500 per day) | D90: =1500*6 -> 9000
A92: Total Pay Amount | D92: =SUM(D90:D91) -> 9000
A93: Prepared By | C93: Approved By | D93: Received By
A95: Mujtaba And Borthers
A96: SR# | B96: Date | C96: Name | D96: Amount
A97: 1 | B97: 46036 | C97: Ali Passand Cook Helper salary Dec 2025 | D97: 26067
A99: Total Pay Amount | D99: =SUM(D97:D98) -> 26067
A100: Prepared By | C100: Approved By | D100: Received By
A102: Mujtaba And Borthers
A103: SR# | B103: Date | C103: Name | D103: Amount
A104: 1 | B104: 46039 | C104: Muhammad Ramzan advance payment 17-Dec-2026 | D104: 10000
A106: Total Pay Amount | D106: =SUM(D104:D105) -> 10000
A107: Prepared By | C107: Approved By | D107: Received By
A109: Mujtaba And Borthers
A110: SR# | B110: Date | C110: Name | D110: Amount
A111: 1 | B111: 46039 | C111: Asif Samosa Maker 6 Days payment 17-Dec-2026 | D111: =1500*6 -> 9000
A113: Total Pay Amount | D113: =SUM(D111:D112) -> 9000
A114: Prepared By | C114: Approved By | D114: Received By
A116: Mujtaba And Borthers
A117: SR# | B117: Date | C117: Name | D117: Amount
A118: 1 | B118: 46039 | C118: Poran Salary Finel Setelment 17-Dec-2026 | D118: 18133
A120: Total Pay Amount | D120: =SUM(D118:D119) -> 18133
A121: Prepared By | C121: Approved By | D121: Received By
A123: Mujtaba And Borthers
A124: Depoist Amount Summary
A125: SR# | B125: Date | C125: Name | D125: Amount
A126: 1 | B126: 46021 | C126: Cash Handover to Javed sb for Diposit | D126: 500000
A127: 2 | B127: 46026 | C127: Cash Handover to Ehtesham sb for Diposit | D127: 400000
A128: 3 | B128: 46032 | C128: Cash Handover to Waqas usmani for Diposit | D128: 700000
A129: 4 | B129: 46042 | C129: Cash Handover to Javed sb for Diposit | D129: 900000
A130: Total Amount | D130: =SUM(D126:D129) -> 2500000
A131: Prepared By | C131: Checked By | D131: Received By
A133: Mujtaba And Borthers
A134: SR# | B134: Date | C134: Name | D134: Amount
A135: 1 | B135: 46042 | C135: Cash Handover to Javed sb for Diposit | D135: 900000
A136: Total Amount | D136: =SUM(D135:D135) -> 900000
A137: Prepared By | C137: Checked By | D137: Received By
...

Sheet Menu For Executive
A1: Senior Mess Menu
A2: Lunch
A3: SR# | B3: Day | C3: Item Name | D3: Price | E3: GRM
A4: 1 | B4: Monday | C4: Chicken Hara Masala | D4: 225 | E4: 200
A5: 2 | B5: Tuesday | C5: Allo Mattar Pulao | D5: 180 | E5: 600
A6: 3 | B6: Wednesday | C6: Dall Chana Fry/ Dall Mash | D6: 180 | E6: 200
A7: 4 | B7: Thursday | C7: Seasonal Vegetable | D7: 180 | E7: 200
A8: 5 | B8: Friday | C8: Chicken Biryani (2 Pieces) | D8: 320 | E8: 600
A9: 6 | B9: Saturday | C9: Chicken Aalo Curry | D9: 220 | E9: 200
A10: 7 | B10: Sunday
A12: Senior Mess Menu
A13: Dinner
A14: SR# | B14: Day | C14: Item Name | D14: Price | E14: GRM
A15: 1 | B15: Monday | C15: Red Been (Lobia) | D15: 180 | E15: 200
A16: 2 | B16: Tuesday | C16: Beef Aloo Qeema | D16: 270 | E16: 200
A17: 3 | B17: Wednesday | C17: Dall Chawal (450/150) | D17: 200 | E17: 600
A18: 4 | B18: Thursday | C18: Achari Chicken | D18: 225 | E18: 200
A19: 5 | B19: Friday | C19: Seasonal Vegetable | D19: 180 | E19: 200
A20: 6 | B20: Saturday | C20: Vegetable Rice with Chicken Manchorian (450/150) | D20: 350 | E20: 600
A21: 7 | B21: Sunday

Sheet Labor Menu 
A1: Junior Menu
A2: Breakfast
A3: SR# | B3: Day | C3: Item Name | D3: Price | E3: GRM
A4: 1 | B4: Monday | C4: Paratha, Channa, Chay | D4: 30,50,30 | E4: 100
A5: 2 | B5: Tuesday | C5: Paratha, Aloo Bhujia, Chay | D5: 30,50,30 | E5: 100
A6: 3 | B6: Wednesday | C6: Paratha, Anda Aloo/ Anda Omlete, Chay | D6: 30,50,30 | E6: 100
A7: 4 | B7: Thursday | C7: Paratha, Channa, Chay | D7: 30,50,30 | E7: 100
A8: 5 | B8: Friday | C8: Paratha, Aloo Bhujia, Chay | D8: 30,50,30 | E8: 100
A9: 6 | B9: Saturday | C9: Paratha, Anda Aloo, Chay | D9: 30,50,30 | E9: 100
A10: 7 | B10: Sunday | C10: Paratha, Channa, Chay | D10: 30,50,30 | E10: 100
A12: Lunch
A13: SR# | B13: Day | C13: Item Name | D13: Price | E13: GRM
A14: 1 | B14: Monday | C14: Chicken Aloo | D14: 110 | E14: 250
A15: 2 | B15: Tuesday | C15: Dall Mong | D15: 80 | E15: 250
A16: 3 | B16: Wednesday | C16: Chicken Pulao | D16: 180 | E16: 450
A17: 4 | B17: Thursday | C17: Sabzi | D17: 80 | E17: 250
A18: 5 | B18: Friday | C18: Chicken Biryani (1 Piece) | D18: 180 | E18: 450
A19: 6 | B19: Saturday | C19: Sabzi | D19: 80 | E19: 250
A20: 7 | B20: Sunday | C20: Dall Channa palak | D20: 80 | E20: 250
A22: Dinner
A23: SR# | B23: Day | C23: Item Name | D23: Price | E23: GRM
A24: 1 | B24: Monday | C24: Dall Channa | D24: 80 | E24: 250
A25: 2 | B25: Tuesday | C25: Sabzi | D25: 80 | E25: 250
A26: 3 | B26: Wednesday | C26: Curry Pakora/ White Zeera Rice | D26: 80100 | E26: 150/300
A27: 4 | B27: Thursday | C27: Murg Salan | D27: 110 | E27: 250
A28: 5 | B28: Friday | C28: Sabzi | D28: 80 | E28: 250
A29: 6 | B29: Saturday | C29: Dall Masoor | D29: 80 | E29: 250
A30: 7 | B30: Sunday | C30: Dall Chawal | D30: 120 | E30: 150/300

Sheet Steaching Dep
A1: SR# | B1: Date | C1: Item Name | D1: QTY | E1: Price | F1: Department
A2: 1 | B2: 16/12/2025 | C2: Karahi | D2: 1.5Kg | E2: 2100 | F2: Steaching
A3: 2 | B3: 16/12/2025 | C3: Biryani | D3: 1.5Kg | E3: 2400 | F3: Steaching
A4: 3 | B4: 16/12/2025 | C4: Salad | D4: 2 Plate | E4: 100 | F4: Steaching
A5: 4 | B5: 16/12/2025 | C5: Roti | D5: 6 | E5: 90 | F5: Steaching
A6: 5 | B6: 16/12/2025 | C6: Boild Egg | D6: 4 | E6: 200 | F6: Steaching
A7: 6 | B7: 16/12/2025 | C7: Fry Egg | D7: 3 | E7: 150 | F7: Steaching
A8: 7 | B8: 16/12/2025 | C8: Paratha | D8: 8 | E8: 280 | F8: Steaching
A9: 8 | B9: 16/12/2025 | C9: Tea | D9: 4 | E9: 140 | F9: Steaching
A10: 9 | B10: 16/12/2025 | C10: Lemaon | D10: 2 | E10: 20 | F10: Steaching
A11: Grand Total Amount | E11: =SUM(E2:E10) -> 5480
A12: Preapred By | F12: Clint Signature
A13: SR# | B13: Date | C13: Item Name | D13: QTY | E13: Price | F13: Department
A14: Breakfast
A15: 1 | B15: 17/12/2025 | C15: Night Tea | D15: 5 | E15: 150 | F15: Steaching
A16: 2 | B16: 17/12/2025 | C16: Parathy | D16: 10 | E16: 350 | F16: Steaching
A17: 3 | B17: 17/12/2025 | C17: Anday | D17: 5 | E17: 250 | F17: Steaching
A18: Lunch
A19: 1 | B19: 17/12/2025 | C19: Anday | D19: 4 | E19: 200 | F19: Steaching
A20: 2 | B20: 17/12/2025 | C20: Salad | D20: 2 | E20: 40 | F20: Steaching
A21: 3 | B21: 17/12/2025 | C21: Chicken Qorma | D21: 3 | E21: 600 | F21: Steaching
A22: 4 | B22: 17/12/2025 | C22: Roti | D22: 8 | E22: 120 | F22: Steaching
A23: 5 | B23: 17/12/2025 | C23: Chicken Qorma | D23: 3 | E23: 600 | F23: Steaching
A24: 6 | B24: 17/12/2025 | C24: Roti | D24: 8 | E24: 120 | F24: Steaching
A25: 7 | B25: 17/12/2025 | C25: Salad | D25: 2 | E25: 40 | F25: Steaching
A26: 8 | B26: 17/12/2025 | C26: Raita | D26: 1 | E26: 120 | F26: Steaching
A27: 9 | B27: 17/12/2025 | C27: Tea | D27: 10 | E27: 350 | F27: Steaching
A28: Dinner
A29: 1 | B29: 17/12/2025 | C29: Biryani | D29: 2 Kg | E29: 3200 | F29: Steaching
A30: 2 | B30: 17/12/2025 | C30: Karahi | D30: 1kg | E30: 1600 | F30: Steaching
A31: 3 | B31: 17/12/2025 | C31: Salad | D31: 2 | E31: 40 | F31: Steaching
A32: 4 | B32: 17/12/2025 | C32: Raita | D32: 1 | E32: 120 | F32: Steaching
A33: 5 | B33: 17/12/2025 | C33: Roti | D33: 15 | E33: 225 | F33: Steaching
A34: Grand Total Amount | E34: =E15+E16+E17+E19+E20+E21+E22+E23+E24+E25+E26+E27+E29+E30+E31+E32+E33 -> 8125
A35: Preapred By | F35: Clint Signature
A36: SR# | B36: Date | C36: Item Name | D36: QTY | E36: Price | F36: Department
A37: 1 | B37: 18/12/2025 | C37: Partahy | D37: 7 | E37: 245 | F37: Steaching
A38: 2 | B38: 18/12/2025 | C38: Half Fry Egg | D38: 5 | E38: 250 | F38: Steaching
A39: 3 | B39: 18/12/2025 | C39: White Rice | D39: 1Kg | E39: 1000 | F39: Steaching
A40: 4 | B40: 18/12/2025 | C40: Biryani | D40: 1Kg | E40: 1600 | F40: Steaching
A41: 5 | B41: 18/12/2025 | C41: Chicken Karahi | D41: 1Kg | E41: 1600 | F41: Steaching
A42: 6 | B42: 18/12/2025 | C42: Chicken Stew | D42: 3 Plate | E42: 600 | F42: Steaching
A43: 7 | B43: 18/12/2025 | C43: Salad | D43: 1 | E43: 20 | F43: Steaching
A44: 8 | B44: 18/12/2025 | C44: Veg Pulao | D44: 2 Plate | E44: 220 | F44: Steaching
A45: 9 | B45: 18/12/2025 | C45: Rice | D45: 4 Plate | E45: 400 | F45: Steaching
A46: 10 | B46: 18/12/2025 | C46: Dall | D46: 4 | E46: 260 | F46: Steaching
A47: Grand Total Amount | E47: =SUM(E37:E46) -> 6195
A48: Preapred By | F48: Clint Signature
A49: SR# | B49: Date | C49: Item Name | D49: QTY | E49: Price | F49: Department
A50: 1 | B50: 19/12/2025 | C50: Dahi | D50: 1Kg | E50: 500 | F50: Steaching
A51: 2 | B51: 19/12/2025 | C51: Chicken Biryani | D51: 1Kg | E51: 1600 | F51: Steaching
A52: 3 | B52: 19/12/2025 | C52: Salad | D52: 2 | E52: 40 | F52: Steaching
A53: 4 | B53: 19/12/2025 | C53: Cold drink | E53: 280 | F53: Steaching
A54: Grand Total Amount | E54: =SUM(E50:E53) -> 2420
A55: Preapred By | F55: Clint Signature
A56: SR# | B56: Date | C56: Item Name | D56: QTY | E56: Price | F56: Department
A57: 1 | B57: 20/12/2025 | C57: Paratha | D57: 10 | E57: 350 | F57: Steaching
A58: 2 | B58: 20/12/2025 | C58: Egg Fry | D58: 5 | E58: 250 | F58: Steaching
A59: 3 | B59: 20/12/2025 | C59: Karahi | D59: 1Kg | E59: 1600 | F59: Steaching
A60: 4 | B60: 20/12/2025 | C60: Sabzi | D60: 3 | E60: 240 | F60: Steaching
A61: 5 | B61: 20/12/2025 | C61: Roti | D61: 31 | E61: 465 | F61: Steaching
A62: 6 | B62: 20/12/2025 | C62: Salad | D62: 2 | E62: 40 | F62: Steaching
A63: 7 | B63: 20/12/2025 | C63: Cold drink | D63: 13 | E63: 910 | F63: Steaching
A64: 8 | B64: 20/12/2025 | C64: Biscut | D64: 11 | E64: 440 | F64: Steaching
A65: 9 | B65: 20/12/2025 | C65: Lays | D65: 6 | E65: 420 | F65: Steaching
A66: 10 | B66: 20/12/2025 | C66: Juice Mango | E66: 480 | F66: Steaching
A67: 11 | B67: 20/12/2025 | C67: Chicken Pulao | D67: 2Kg | E67: 3200 | F67: Steaching
A68: 12 | B68: 20/12/2025 | C68: Chicken Salan | D68: 2 | E68: 240 | F68: Steaching
A69: 13 | B69: 20/12/2025 | C69: Dahi | D69: 0.5 | E69: 100 | F69: Steaching
A70: 14 | B70: 20/12/2025 | C70: Karahi | D70: 2 | E70: 400 | F70: Steaching
A71: 15 | B71: 20/12/2025 | C71: Chay | D71: 5 | E71: 150 | F71: Steaching
A72: Grand Total Amount | E72: =SUM(E57:E71) -> 9285
A73: Preapred By | F73: Clint Signature
A74: SR# | B74: Date | C74: Item Name | D74: QTY | E74: Price | F74: Department
A75: 1 | B75: 21/12/2025 | C75: Paratha | D75: 5 | E75: 175 | F75: Steaching
A76: 2 | B76: 21/12/2025 | C76: Egg Fry | D76: 4 | E76: 200 | F76: Steaching
A77: 3 | B77: 21/12/2025 | C77: Biscut | D77: 10 | E77: 400 | F77: Steaching
A78: 4 | B78: 21/12/2025 | C78: White Karahi | D78: 1 Kg | E78: 1600 | F78: Steaching
A79: 5 | B79: 21/12/2025 | C79: Dall | D79: 4 | E79: 320 | F79: Steaching
A80: 6 | B80: 21/12/2025 | C80: Rice | D80: 4 | E80: 400 | F80: Steaching
A81: 7 | B81: 21/12/2025 | C81: Roti | D81: 15 | E81: 225 | F81: Steaching
A82: 8 | B82: 21/12/2025 | C82: Cold Drink | D82: 5 | E82: 350 | F82: Steaching
A83: 9 | B83: 21/12/2025 | C83: Salad | D83: 2 | E83: 50 | F83: Steaching
A84: 10 | B84: 21/12/2025 | C84: Nimko | D84: 6 | E84: 120 | F84: Steaching
A85: 11 | B85: 21/12/2025 | C85: Lays | D85: 2 | E85: 140 | F85: Steaching
A86: Grand Total Amount | E86: =SUM(E75:E85) -> 3980
A87: Preapred By | F87: Clint Signature
A88: SR# | B88: Date | C88: Item Name | D88: QTY | E88: Price | F88: Department
A89: 1 | B89: 22/12/2025 | C89: Paratha | D89: 10 | E89: 350 | F89: Steaching
A90: 2 | B90: 22/12/2025 | C90: Egg Fry | D90: 3 | E90: 150 | F90: Steaching
A91: 3 | B91: 22/12/2025 | C91: Lays | D91: 5 | E91: 350 | F91: Steaching
A92: 4 | B92: 22/12/2025 | C92: Biscut | D92: 7 | E92: 280 | F92: Steaching
A93: 5 | B93: 22/12/2025 | C93: Chicken Karahi | D93: 2 | E93: 400 | F93: Steaching
A94: 6 | B94: 22/12/2025 | C94: Egg Channa | D94: 2 | E94: 220 | F94: Steaching
A95: 7 | B95: 22/12/2025 | C95: Roti | D95: 20 | E95: 300 | F95: Steaching
A96: 8 | B96: 22/12/2025 | C96: Salad | D96: 2 | E96: 40 | F96: Steaching
A97: 9 | B97: 22/12/2025 | C97: Cold Drink | D97: 5 | E97: 350 | F97: Steaching
A98: 10 | B98: 22/12/2025 | C98: Chai | D98: 3 | E98: 45 | F98: Steaching
A99: Grand Total Amount | E99: =SUM(E89:E98) -> 2485
A100: Preapred By | F100: Clint Signature
...

Sheet Steaching Deprt Summary 
A1: Mujtaba and Brothers (Bill)
A2: SR# | B2: Date | C2: Name | D2: Depart | E2: Amount | F2: Signature | G2: Received Amount Date
A3: 1 | B3: 16 Dec to 09 Jan 2026 | C3: Talha | D3: Steaching | E3: 181270
A4: 2 | B4: 16 Dec to 09 Jan 2026
A5: 3 | B5: 16 Dec to 09 Jan 2026
A6: 4 | B6: 16 Dec to 09 Jan 2026
A7: Total Amount
A8: Preapred BY | G8: Clint Signature
A10: SUMMARY OF STEACHING OVERTIME DEPART
A11: SR# | B11: Date | C11: Name | D11: Amount | E11: Depart
A12: 1 | B12: 46032 | C12: Atar Sb | D12: ='Steaching Dep'!E455 -> 8680 | E12: Steaching
A13: 2 | B13: 46033 | C13: Atar Sb | D13: ='Steaching Dep'!E467 -> 3915 | E13: Steaching
A14: 3 | B14: 46034 | C14: Atar Sb | D14: ='Steaching Dep'!E486 -> 5520 | E14: Steaching
A15: 4 | B15: 46035 | C15: Atar Sb | D15: ='Steaching Dep'!E504 -> 7205 | E15: Steaching
A16: 5 | B16: 46036 | C16: Atar Sb | D16: ='Steaching Dep'!E526 -> 6095 | E16: Steaching
A17: 6 | B17: 46037 | C17: Atar Sb | D17: ='Steaching Dep'!E551 -> 13345 | E17: Steaching
A18: TOTAL AMOUNT | D18: =SUM(D12:D17) -> 44760
A19: Preapred By | E19: Clint Signature
A22: Admin Sig

Sheet Steaching Thakydar overtime
A1: SR# | B1: Date | C1: Item Name | D1: QTY | E1: Price | F1: Department
A2: 1 | B2: 17/12/2025 | C2: Sabzi | D2: 23 | E2: 1840 | F2: Steaching
A3: 2 | B3: 17/12/2025 | C3: Roti | D3: 69 | E3: 1035 | F3: Steaching
A4: 3 | B4: 17/12/2025 | C4: Tea | D4: 23 | E4: 805 | F4: Steaching
A5: Grand Total Amount | E5: =SUM(E2:E4) -> 3680
A6: Preapred By | F6: Clint Signature
A7: SR# | B7: Date | C7: Item Name | D7: QTY | E7: Price | F7: Department
A8: 1 | B8: 18/12/2025 | C8: Chay | D8: 18 | E8: =D8*35 -> 630 | F8: Steaching
A9: 2 | B9: 18/12/2025 | C9: Dall | D9: 18 | E9: =D9*80 -> 1440 | F9: Steaching
A10: 3 | B10: 18/12/2025 | C10: Roti | D10: 54 | E10: =D10*15 -> 810 | F10: Steaching
A11: Grand Total Amount | E11: =SUM(E8:E10) -> 2880
A12: Preapred By | F12: Clint Signature
A13: SR# | B13: Date | C13: Item Name | D13: QTY | E13: Price | F13: Department
A14: 1 | B14: 25/12/2025 | C14: Chai | D14: 1 | E14: 35 | F14: Steaching
A15: 2 | B15: 25/12/2025 | C15: Roti | D15: 38 | E15: 570 | F15: Steaching
A16: 3 | B16: 25/12/2025 | C16: Ch- Aalo Ghost | D16: 18 | E16: 1980 | F16: Steaching
A17: Grand Total Amount | E17: =SUM(E14:E16) -> 2585
A18: Preapred By | F18: Clint Signature
A19: SR# | B19: Date | C19: Item Name | D19: QTY | E19: Price | F19: Department
A20: 1 | B20: 26/12/2025 | C20: Aalo Biryani | D20: 15 | E20: =D20*120 -> 1800 | F20: Steaching
A21: Grand Total Amount | E21: =SUM(E20:E20) -> 1800
A22: Preapred By | F22: Clint Signature
A23: SR# | B23: Date | C23: Item Name | D23: QTY | E23: Price | F23: Department
A24: 1 | B24: 27/12/2025 | C24: Sabzi | D24: 17 | E24: =D24*80 -> 1360 | F24: Steaching
A25: 2 | B25: 27/12/2025 | C25: Roti | D25: 51 | E25: =D25*15 -> 765 | F25: Steaching
A26: 3 | B26: 27/12/2025 | C26: Chai | D26: 11 | E26: =D26*35 -> 385 | F26: Steaching
A27: Grand Total Amount | E27: =SUM(E24:E24) -> 1360
A28: Preapred By | F28: Clint Signature
A29: SR# | B29: Date | C29: Item Name | D29: QTY | E29: Price | F29: Department
A30: 1 | B30: 29/12/2025 | C30: Channa Dal | D30: 17 | E30: =D30*80 -> 1360 | F30: Steaching
A31: 2 | B31: 29/12/2025 | C31: Roti | D31: 51 | E31: =D31*15 -> 765 | F31: Steaching
A32: Grand Total Amount | E32: =SUM(E30:E31) -> 2125
A33: Preapred By | F33: Clint Signature
A34: SR# | B34: Date | C34: Item Name | D34: QTY | E34: Price | F34: Department
A35: 1 | B35: 30/12/2025 | C35: Sabzi | D35: 10 | E35: =D35*80 -> 800 | F35: Steaching
A36: 2 | B36: 30/12/2025 | C36: Roti | D36: 30 | E36: =D36*15 -> 450 | F36: Steaching
A37: Grand Total Amount | E37: =SUM(E35:E36) -> 1250
A38: Preapred By | F38: Clint Signature
A39: SR# | B39: Date | C39: Item Name | D39: QTY | E39: Price | F39: Department
A40: 1 | B40: 46022 | C40: Sabzi | D40: 8 | E40: =D40*80 -> 640 | F40: Steaching
A41: 2 | B41: 46022 | C41: Roti | D41: 24 | E41: =D41*15 -> 360 | F41: Steaching
A42: 3 | B42: 46022 | C42: Chai | D42: 8 | E42: =D42*35 -> 280
A43: Grand Total Amount | E43: =SUM(E40:E42) -> 1280
A44: Preapred By | F44: Clint Signature
A45: SR# | B45: Date | C45: Item Name | D45: QTY | E45: Price | F45: Department
A46: 1 | B46: 46023 | C46: Ch- Curry | D46: 42 | E46: =D46*110 -> 4620 | F46: Steaching
A47: 2 | B47: 46023 | C47: Roti | D47: =42*3 -> 126 | E47: =D47*15 -> 1890 | F47: Steaching
A48: 3 | B48: 46023 | C48: Chai | D48: 38 | E48: =D48*35 -> 1330 | F48: Steaching
A49: Grand Total Amount | E49: =SUM(E46:E48) -> 7840
A50: Preapred By | F50: Clint Signature
A51: SR# | B51: Date | C51: Item Name | D51: QTY | E51: Price | F51: Department
A52: 1 | B52: 46024 | C52: Aalo Biryani | D52: 22 | E52: =D52*110 -> 2420 | F52: Steaching
A53: 2 | B53: 46024 | C53: Chai | D53: 22 | E53: =D53*15 -> 330 | F53: Steaching
A54: Grand Total Amount | E54: =SUM(E52:E53) -> 2750
A55: Preapred By | F55: Clint Signature
A56: SR# | B56: Date | C56: Item Name | D56: QTY | E56: Price | F56: Department
A57: 1 | B57: 46028 | C57: Sabzi | D57: 5 | E57: =D57*80 -> 400 | F57: Steaching
A58: 2 | B58: 46028 | C58: Roti | D58: 15 | E58: =D58*15 -> 225 | F58: Steaching
A59: 3 | B59: 46028 | C59: Tea | D59: 5 | E59: =D59*30 -> 150 | F59: Steaching
A60: Grand Total Amount | E60: =SUM(E57:E59) -> 775
A61: Preapred By | F61: Clint Signature
A62: SR# | B62: Date | C62: Item Name | D62: QTY | E62: Price | F62: Department
A63: 1 | B63: 46030 | C63: Aalo Pulao | D63: 21 | E63: =D63*110 -> 2310 | F63: Steaching
A64: Grand Total Amount | E64: =SUM(E63:E63) -> 2310
A65: Preapred By | F65: Clint Signature
A66: SR# | B66: Date | C66: Item Name | D66: QTY | E66: Price | F66: Department
A67: 1 | B67: 46030 | C67: Sp- Ch- Qorma | D67: 6 | E67: =D67*220 -> 1320 | F67: Steaching
A68: 2 | B68: 46030 | C68: Roti | D68: 18 | E68: =D68*15 -> 270 | F68: Steaching
A69: 3 | B69: 46030 | C69: Tea | D69: 6 | E69: =D69*35 -> 210 | F69: Steaching
A70: Grand Total Amount | E70: =SUM(E67:E69) -> 1800
A71: Preapred By | F71: Clint Signature
A72: SR# | B72: Date | C72: Item Name | D72: QTY | E72: Price | F72: Department
A73: 1 | B73: 46031 | C73: Sabzi | D73: 21 | E73: =D73*80 -> 1680 | F73: Steaching
A74: 2 | B74: 46031 | C74: Roti | D74: =D73*3 -> 63 | E74: =D74*15 -> 945 | F74: Steaching
A75: Grand Total Amount | E75: =SUM(E73:E74) -> 2625
A76: Preapred By | F76: Clint Signature
A77: SR# | B77: Date | C77: Item Name | D77: QTY | E77: Price | F77: Department
A78: 1 | B78: 46031 | C78: Sabzi | D78: 18 | E78: =D78*80 -> 1440 | F78: Steaching
A79: 2 | B79: 46031 | C79: Roti | D79: =D78*3 -> 54 | E79: =D79*15 -> 810 | F79: Steaching
A80: 3 | B80: 46031 | C80: Tea | D80: 21 | E80: =D80*30 -> 630 | F80: Steaching
A81: Grand Total Amount | E81: =SUM(E78:E80) -> 2880
A82: Preapred By | F82: Clint Signature
A83: SR# | B83: Date | C83: Item Name | D83: QTY | E83: Price | F83: Department
A84: 1 | B84: 46032 | C84: Dall | D84: 14 | E84: =D84*80 -> 1120 | F84: Steaching
A85: 2 | B85: 46032 | C85: Roti | D85: =D84*3 -> 42 | E85: =D85*15 -> 630 | F85: Steaching
A86: Grand Total Amount | E86: =SUM(E84:E85) -> 1750
A87: Preapred By | F87: Clint Signature
A88: SR# | B88: Date | C88: Item Name | D88: QTY | E88: Price | F88: Department
A89: 1 | B89: 46036 | C89: Ch- Biryani | D89: 22 | E89: =D89*120 -> 2640 | F89: Steaching
A90: Grand Total Amount | E90: =SUM(E89:E89) -> 2640
A91: Preapred By | F91: Clint Signature
A92: SR# | B92: Date | C92: Item Name | D92: QTY | E92: Price | F92: Department
A93: 1 | B93: 46037 | C93: Chicken Curry | D93: 13 | E93: =D93*110 -> 1430 | F93: Steaching
A94: 2 | B94: 46037 | C94: Roti | D94: =13*3 -> 39 | E94: =D94*15 -> 585 | F94: Steaching
A95: 3 | B95: 46037 | C95: Tea | D95: 13 | E95: =D95*30 -> 390 | F95: Steaching
A96: Grand Total Amount | E96: =SUM(E93:E95) -> 2405
A97: Preapred By | F97: Clint Signature
A98: SR# | B98: Date | C98: Item Name | D98: QTY | E98: Price | F98: Department
A99: 1 | B99: 46037 | C99: Chicken Curry | D99: 25 | E99: =D99*110 -> 2750 | F99: Steaching
A100: 2 | B100: 46037 | C100: Roti | D100: =25*3 -> 75 | E100: =D100*15 -> 1125 | F100: Steaching
...

Sheet Summary Amanat Sb 
A1: SUMMARY OF STEACHING OVERTIME DEPART
A2: SR# | B2: Date | C2: Name | D2: Amount | E2: Depart
A3: 1 | B3: 46023 | C3: Amant Sb | D3: 7840 | E3: Steaching
A4: 2 | B4: 46024 | C4: Amant Sb | D4: 2750 | E4: Steaching
A5: 3 | B5: 46028 | C5: Amant Sb | D5: 775 | E5: Steaching
A6: 4 | B6: 46030 | C6: Amant Sb | D6: 2310 | E6: Steaching
A7: 5 | B7: 46030 | C7: Amant Sb | D7: 1800 | E7: Steaching
A8: 6 | B8: 46031 | C8: Amant Sb | D8: 2880 | E8: Steaching
A9: 7 | B9: 46031 | C9: Amant Sb | D9: 2625 | E9: Steaching
A10: 8 | B10: 46032 | C10: Amant Sb | D10: 1750 | E10: Steaching
A11: 9 | B11: 46036 | C11: Amant Sb | D11: 2640 | E11: Steaching
A12: 10 | B12: 46037 | C12: Amant Sb | D12: 3875 | E12: Steaching
A13: 11 | B13: 46037 | C13: Amant Sb | D13: 2405 | E13: Steaching
A14: TOTAL AMOUNT | D14: =SUM(D3:D13) -> 31650
A15: Preapred By | E15: Clint Signature
A18: Admin Sig

Sheet Dying
A1: SR# | B1: Date | C1: Item Name | D1: QTY | E1: Price | F1: Department
A2: 1 | B2: 16/12/2025 | C2: Chicken Karahi | D2: 1 Plate | E2: 200 | F2: Dying
A3: 2 | B3: 16/12/2025 | C3: Dall | D3: 1 Plate | E3: 80 | F3: Dying
A4: 3 | B4: 16/12/2025 | C4: Roti | D4: 5 | E4: 90 | F4: Dying
A5: 4 | B5: 16/12/2025 | C5: Salad | F5: Dying
A6: Grand Total Amount | E6: =SUM(E2:E5) -> 370
A8: Preapred By | F8: Clint Signature
A11: SR# | B11: Date | C11: Item Name | D11: QTY | E11: Price | F11: Department
A12: 1 | B12: 17/12/2025 | C12: Chicken Karahi | D12: 2 Plate | E12: 400 | F12: Dying
A13: 2 | B13: 17/12/2025 | C13: Cold Drink | D13: 1 | E13: 70 | F13: Dying
A14: 3 | B14: 17/12/2025 | C14: Roti | D14: 6 | E14: 90 | F14: Dying
A15: 4 | B15: 17/12/2025 | C15: Salad | D15: 1 | E15: 20 | F15: Dying
A16: Grand Total Amount | E16: =SUM(E12:E15) -> 580
A18: Preapred By | F18: Clint Signature
A21: SR# | B21: Date | C21: Item Name | D21: QTY | E21: Price | F21: Department
A22: 1 | B22: 18/12/2025 | C22: Chicken Stew | D22: 1 Plate | E22: 200 | F22: Dying
A23: 2 | B23: 18/12/2025 | C23: Roti | D23: 3 | E23: 45 | F23: Dying
A24: 3 | B24: 18/12/2025 | C24: Salad | D24: 1 | E24: 20 | F24: Dying
A26: Grand Total Amount | E26: =SUM(E22:E25) -> 265
A28: Preapred By | F28: Clint Signature
A30: SR# | B30: Date | C30: Item Name | D30: QTY | E30: Price | F30: Department
A31: 1 | B31: 19/12/2025 | C31: Biryani | D31: 5 | E31: 900 | F31: Dying
A32: 2 | B32: 19/12/2025 | C32: Salad | D32: 2 | E32: 50 | F32: Dying
A33: 3 | B33: 19/12/2025 | C33: Raita | D33: 1 | E33: 50 | F33: Dying
A34: 4 | B34: 19/12/2025 | C34: ColdDrink | D34: 2 | E34: 140 | F34: Dying
A35: 5 | B35: 19/12/2025 | C35: Fruit Chat | D35: 2 | E35: 240 | F35: Dying
A36: Grand Total Amount | E36: =SUM(E31:E35) -> 1380
A38: Preapred By | F38: Clint Signature
A41: SR# | B41: Date | C41: Item Name | D41: QTY | E41: Price | F41: Department
A42: 1 | B42: 20/12/2025 | C42: Fruit Chat | D42: 1 | E42: 120 | F42: Dying
A43: 2 | B43: 20/12/2025 | C43: Biscut | D43: 3 | E43: 120 | F43: Dying
A44: 3
A45: 4
A46: 5
A47: Grand Total Amount | E47: =SUM(E42:E46) -> 240
A49: Preapred By | F49: Clint Signature
A52: SR# | B52: Date | C52: Item Name | D52: QTY | E52: Price | F52: Department
A53: 1 | B53: 22/12/2025 | C53: Ch Karahi | D53: 1 | E53: 200 | F53: Dying
A54: 2 | B54: 22/12/2025 | C54: Anda channa | D54: 1 | E54: 110 | F54: Dying
A55: 3 | B55: 22/12/2025 | C55: Roti | D55: 5 | E55: =D55*15 -> 75 | F55: Dying
A56: 4 | B56: 22/12/2025 | C56: Cold drink | D56: 1 | E56: 70 | F56: Dying
A57: Grand Total Amount | E57: =SUM(E53:E56) -> 455
A59: Preapred By | F59: Clint Signature
A61: SR# | B61: Date | C61: Item Name | D61: QTY | E61: Price | F61: Department
A62: 1 | B62: 23/12/2025 | C62: Ch- Pulao | D62: 1 | E62: 200 | F62: Dying
A63: 2 | B63: 23/12/2025 | C63: Cold drink | D63: 2 | E63: 140 | F63: Dying
A64: Grand Total Amount | E64: =SUM(E62:E63) -> 340
A66: Preapred By | F66: Clint Signature
A69: SR# | B69: Date | C69: Item Name | D69: QTY | E69: Price | F69: Department
A70: 1 | B70: 24/12/2025 | C70: Channa Chat | D70: 2 | E70: 240 | F70: Dying
A71: 2 | B71: 24/12/2025 | C71: Roti | D71: 10 | E71: 150 | F71: Dying
A72: 3 | B72: 24/12/2025 | C72: Chicken Gosht | D72: 3 | E72: 660 | F72: Dying
A73: Grand Total Amount | E73: =SUM(E70:E72) -> 1050
A75: Preapred By | F75: Clint Signature
A77: SR# | B77: Date | C77: Item Name | D77: QTY | E77: Price | F77: Department
A78: 1 | B78: 25/12/2025 | C78: Ch Karahi | D78: 3Kg | E78: 4800 | F78: Dying
A79: 2 | B79: 25/12/2025 | C79: Roti | D79: 37 | E79: 555 | F79: Dying
A80: 3 | B80: 25/12/2025 | C80: Salad Bowl | D80: 1 | E80: 200 | F80: Dying
A81: 4 | B81: 25/12/2025 | C81: Salad Plate | D81: 10 | E81: 400 | F81: Dying
A82: 5 | B82: 25/12/2025 | C82: S. Sabzi | D82: 8 | E82: 1760 | F82: Dying
A83: 6 | B83: 25/12/2025 | C83: Dahi | D83: 0.5Kg | E83: 200 | F83: Dying
A84: 7 | B84: 25/12/2025 | C84: S. Chicken Karahi | D84: 1 | E84: 220 | F84: Dying
A85: Grand Total Amount | E85: =SUM(E78:E84) -> 8135
A87: Preapred By | F87: Clint Signature
A89: SR# | B89: Date | C89: Item Name | D89: QTY | E89: Price | F89: Department
A90: 1 | B90: 26/12/2025 | C90: Sp- Biryani | D90: 5 | E90: =320*5 -> 1600 | F90: Dying
A91: 2 | B91: 26/12/2025 | C91: Salad | D91: 5 | E91: 100 | F91: Dying
A92: Grand Total Amount | E92: =SUM(E90:E91) -> 1700
A94: Preapred By | F94: Clint Signature
A96: SR# | B96: Date | C96: Item Name | D96: QTY | E96: Price | F96: Department
A97: 1 | B97: 27/12/2025 | C97: Sp- Chicken Curry | D97: 5 | E97: =D97*180 -> 900 | F97: Dying
A98: 2 | B98: 27/12/2025 | C98: Roti | D98: 15 | E98: =D98*15 -> 225 | F98: Dying
A99: Grand Total Amount | E99: =SUM(E97:E98) -> 1125
A101: Preapred By | F101: Clint Signature
A103: SR# | B103: Date | C103: Item Name | D103: QTY | E103: Price | F103: Department
A104: 1 | B104: 27/12/2025 | C104: Ch- Curry | D104: 3 | E104: =D104*180 -> 540 | F104: Dying
A105: 2 | B105: 27/12/2025 | C105: Roti | D105: 20 | E105: =D105*15 -> 300 | F105: Dying
A106: 3 | B106: 27/12/2025 | C106: Salad Plate | D106: 2 | E106: =D106*25 -> 50 | F106: Dying
A107: 4 | B107: 27/12/2025 | C107: Cold Drink | D107: 1 | E107: =D107*70 -> 70 | F107: Dying
A108: 5 | B108: 27/12/2025 | C108: Samosa | D108: 4 | E108: =D108*30 -> 120 | F108: Dying
A109: 6 | B109: 27/12/2025 | C109: Sabzi | D109: 3 | E109: =D109*80 -> 240 | F109: Dying
A110: Grand Total Amount | E110: =SUM(E104:E109) -> 1320
A112: Preapred By | F112: Clint Signature
A114: SR# | B114: Date | C114: Item Name | D114: QTY | E114: Price | F114: Department
A115: 1 | B115: 29/12/2025 | C115: Chicken Hara Masala | D115: 4 | E115: =D115*225 -> 900 | F115: Dying
A116: 2 | B116: 29/12/2025 | C116: Salad | D116: 4 | E116: =D116*20 -> 80 | F116: Dying
A117: 3 | B117: 29/12/2025 | C117: Roti | D117: 15 | E117: =D117*15 -> 225 | F117: Dying
A118: 4 | B118: 29/12/2025 | C118: Egg Ghotala | D118: 6 | E118: =D118*50 -> 300 | F118: Dying
A119: 5 | B119: 29/12/2025 | C119: Aalo Pulao | D119: 1 | E119: =D119*110 -> 110 | F119: Dying
A120: 6 | B120: 29/12/2025 | C120: Dahi | D120: 1 | E120: =D120*50 -> 50 | F120: Dying
A121: Grand Total Amount | E121: =SUM(E115:E120) -> 1665
A123: Preapred By | F123: Clint Signature
A125: SR# | B125: Date | C125: Item Name | D125: QTY | E125: Price | F125: Department
A126: 1 | B126: 29/12/2025 | C126: Chicken Hara Masala | D126: 1 | E126: =D126*225 -> 225 | F126: Dying
A127: 2 | B127: 29/12/2025 | C127: Roti | D127: 15 | E127: =D127*15 -> 225 | F127: Dying
A128: 3 | B128: 29/12/2025 | C128: Ch- Curry | D128: 1 | E128: =D128*110 -> 110 | F128: Dying
A129: 4 | B129: 29/12/2025 | C129: Dall | D129: 2 | E129: =D129*80 -> 160 | F129: Dying
A130: Grand Total Amount | E130: =SUM(E126:E129) -> 720
A132: Preapred By | F132: Clint Signature
A134: SR# | B134: Date | C134: Item Name | D134: QTY | E134: Price | F134: Department
...

Sheet Summary Of Dying Depart 
A1: SUMMARY OF DYING DEPART
A2: SR# | B2: Date | C2: Name | D2: Amount | E2: Depart
A3: 1 | B3: 46007 | C3: Waqas SB | D3: 370 | E3: Dying
A4: 2 | B4: 46008 | C4: Waqas SB | D4: 580 | E4: Dying
A5: 3 | B5: 46009 | C5: Waqas SB | D5: 265 | E5: Dying
A6: 4 | B6: 46010 | C6: Waqas SB | D6: 1380 | E6: Dying
A7: 5 | B7: 46011 | C7: Waqas SB | D7: 240 | E7: Dying
A8: 6 | B8: 46012 | C8: Waqas SB | D8: 720 | E8: Dying
A9: 7 | B9: 46014 | C9: Waqas SB | D9: 340 | E9: Dying
A10: 8 | B10: 46015 | C10: Waqas SB | D10: 1050 | E10: Dying
A11: 9 | B11: 46017 | C11: Waqas SB | D11: 1700 | E11: Dying
A12: 10 | B12: 46018 | C12: Waqas SB | D12: 1320 | E12: Dying
A13: 11 | B13: 46020 | C13: Waqas SB | D13: 720 | E13: Dying
A14: 12 | B14: 46021 | C14: Waqas SB | D14: 1770 | E14: Dying
A15: 13 | B15: 46022 | C15: Waqas SB | D15: 1575 | E15: Dying
A16: Grand Total Amount | D16: =SUM(D3:D15) -> 12030
A18: SUMMARY OF DYING DEPART
A19: SR# | B19: Date | C19: Name | D19: Amount | E19: Depart
A20: 1 | B20: 46023 | C20: Waqas SB | D20: 1585 | E20: Dying
A21: 2 | B21: 46024 | C21: Waqas SB | D21: 1160 | E21: Dying
A22: 3 | B22: 46025 | C22: Waqas SB | D22: 1065 | E22: Dying
A23: 4 | B23: 46027 | C23: Waqas SB | D23: 740 | E23: Dying
A24: 5 | B24: 46027 | C24: Waqas SB | D24: 280 | E24: Dying
A25: 6 | B25: 46028 | C25: Waqas SB | D25: 650 | E25: Dying
A26: 7 | B26: 46029 | C26: Waqas SB | D26: 625 | E26: Dying
A27: 8 | B27: 46029 | C27: Waqas SB | D27: 640 | E27: Dying
A28: 9 | B28: 46030 | C28: Waqas SB | D28: 920 | E28: Dying
A29: 10 | B29: 46031 | C29: Waqas SB | D29: 870 | E29: Dying
A30: 11 | B30: 46032 | C30: Waqas SB | D30: 445 | E30: Dying
A31: 12 | B31: 46034 | C31: Waqas SB | D31: 695 | E31: Dying
... A39: 20 | B39: 46037 | C39: Waqas SB | D39: 280 | E39: Dying
A40: Grand Total Amount | D40: =SUM(D20:D39) -> 15510
A41: Preapred By | E41: Clint Signature
A45: Admin Sig

Sheet Admin
A1: SR# | B1: Date | C1: Item Name | D1: QTY | E1: Price | F1: Department
A2: 1 | B2: 16/12/2025 | C2: Chicken Karahi | D2: 4 Plate | E2: 800 | F2: Admin
A3: 2 | B3: 16/12/2025 | C3: Dall | D3: 1 Plate | E3: 80 | F3: Admin
A4: 3 | B4: 16/12/2025 | C4: Roti | D4: 15 | E4: 225 | F4: Admin
A5: 4 | B5: 16/12/2025 | C5: Salad | D5: 1 | E5: 20 | F5: Admin
A6: Grand Total Amount | E6: =SUM(E2:E5) -> 1125
A8: Preapred By | F8: Clint Signature
A11: SR# | B11: Date | C11: Item Name | D11: QTY | E11: Price | F11: Department
A12: 1 | B12: 17/12/2025 | C12: Boil Egg | D12: 1 | E12: 50 | F12: Admin
A13: 2 | B13: 17/12/2025 | C13: Cake Rus | D13: 1 | E13: 120 | F13: Admin
A14: 3 | B14: 17/12/2025 | C14: Cake | D14: 1 | E14: 80 | F14: Admin
A15: 4 | B15: 17/12/2025 | C15: Chicken Karahi | D15: 1 Plate | E15: 200 | F15: Admin
A16: 5 | B16: 17/12/2025 | C16: Roti | D16: 4 | E16: 60 | F16: Admin
A17: 6 | B17: 17/12/2025 | C17: Salad | D17: 1 | E17: 20 | F17: Admin
A18: Grand Total Amount | E18: =SUM(E12:E17) -> 530
A20: Preapred By | F20: Clint Signature
A23: SR# | B23: Date | C23: Item Name | D23: QTY | E23: Price | F23: Department
A24: 1 | B24: 17/12/2025 | C24: Chicken Qorma | D24: 4 | E24: 800 | F24: Admin
A25: 2 | B25: 17/12/2025 | C25: Roti | D25: 10 | E25: 150 | F25: Admin
A26: 3 | B26: 17/12/2025 | C26: Salad | D26: 2 | E26: 40 | F26: Admin
A27: Grand Total Amount | E27: =SUM(E24:E26) -> 990
A29: Preapred By | F29: Clint Signature
A31: SR# | B31: Date | C31: Item Name | D31: QTY | E31: Price | F31: Department
A32: 1 | B32: 18/12/2025 | C32: Chicken Stew | D32: 2 | E32: 400 | F32: Admin
A33: 2 | B33: 18/12/2025 | C33: Salad | D33: 1 | E33: 20 | F33: Admin
A34: 3 | B34: 18/12/2025 | C34: Tea | D34: 1 | E34: 35 | F34: Admin
A35: 4 | B35: 18/12/2025 | C35: Roti | D35: 10 | E35: 150 | F35: Admin
A36: Grand Total Amount | E36: =SUM(E32:E35) -> 605
A38: Preapred By | F38: Clint Signature
A40: SR# | B40: Date | C40: Item Name | D40: QTY | E40: Price | F40: Department
A41: 1 | B41: 18/12/2025 | C41: Dall | D41: 2 | E41: 160 | F41: Admin
A42: 2 | B42: 18/12/2025 | C42: Roti | D42: 6 | E42: 90 | F42: Admin
A43: 3 | B43: 18/12/2025 | C43: Tea | D43: 2 | E43: 70 | F43: Admin
A44: 4 | B44: 18/12/2025 | C44: Biryani | D44: 1 Pltae | E44: 170 | F44: Admin
A45: 5 | B45: 18/12/2025 | C45: Roti | D45: 5 | E45: 75
A47: Grand Total Amount | E47: =SUM(E41:E46) -> 565
A49: Preapred By | F49: Clint Signature
A51: SR# | B51: Date | C51: Item Name | D51: QTY | E51: Price | F51: Department
A52: 1 | B52: 19/12/2025 | C52: Biryani | D52: 1 | E52: 180 | F52: Admin
A53: 2 | B53: 19/12/2025 | C53: Roti | D53: 3 | E53: 45 | F53: Admin
A54: 3 | B54: 19/12/2025 | C54: Salad | D54: 1 | E54: 20 | F54: Admin
A56: Grand Total Amount | E56: =SUM(E52:E55) -> 245
A58: Preapred By | F58: Clint Signature
A60: SR# | B60: Date | C60: Item Name | D60: QTY | E60: Price | F60: Department
A61: 1 | B61: 22/12/2025 | C61: Anda Channa | D61: 1 | E61: 110 | F61: Admin
A62: 2 | B62: 22/12/2025 | C62: Roti | D62: 4 | E62: 60 | F62: Admin
A63: 3 | B63: 22/12/2025 | C63: Salad | D63: 1 | E63: 20 | F63: Admin
A65: Grand Total Amount | E65: =SUM(E61:E64) -> 190
A67: Preapred By | F67: Clint Signature
A69: SR# | B69: Date | C69: Item Name | D69: QTY | E69: Price | F69: Department
A70: 1 | B70: 23/12/2025 | C70: CH- Karahi | D70: 3 | E70: 660 | F70: Admin
A71: 2 | B71: 23/12/2025 | C71: Roti | D71: 7 | E71: 105 | F71: Admin
A72: 3 | B72: 23/12/2025 | C72: Cold Drink | D72: 2 | E72: 140 | F72: Admin
A74: Grand Total Amount | E74: =SUM(E70:E73) -> 905
A76: Preapred By | F76: Clint Signature
A79: SR# | B79: Date | C79: Item Name | D79: QTY | E79: Price | F79: Department
A80: 1 | B80: 23/12/2025 | C80: CH- Karahi | D80: 4 | E80: =D80*220 -> 880 | F80: Admin
A81: 2 | B81: 23/12/2025 | C81: White Biryani | D81: 6 | E81: =D81*320 -> 1920 | F81: Admin
A82: 3 | B82: 23/12/2025 | C82: Salad | D82: 4 | E82: 80 | F82: Admin
A83: 4 | B83: 23/12/2025 | C83: Roti | D83: 12 | E83: 180 | F83: Admin
A84: 5 | B84: 23/12/2025 | C84: Cold Drink | E84: 160 | F84: Admin
A85: Grand Total Amount | E85: =SUM(E80:E84) -> 3220
A87: Preapred By | F87: Clint Signature
A90: SR# | B90: Date | C90: Item Name | D90: QTY | E90: Price | F90: Department
A91: 1 | B91: 23/12/2025 | C91: CH- Karahi | D91: 1 | E91: =D91*220 -> 220 | F91: Admin
A92: 2 | B92: 23/12/2025 | C92: Pulao | D92: 1 | E92: 200 | F92: Admin
A93: 3 | B93: 23/12/2025 | C93: Salad | D93: 1 | E93: 20 | F93: Admin
A94: 4 | B94: 23/12/2025 | C94: Roti | D94: 6 | E94: 90 | F94: Admin
A95: Grand Total Amount | E95: =SUM(E91:E94) -> 530
A97: Preapred By | F97: Clint Signature
A99: SR# | B99: Date | C99: Item Name | D99: QTY | E99: Price | F99: Department
A100: 1 | B100: 24/12/2025 | C100: Ch- Korma | D100: 6 | E100: 1350 | F100: Admin
A101: 2 | B101: 24/12/2025 | C101: Biryani | D101: 6 | E101: 1920 | F101: Admin
A102: 3 | B102: 24/12/2025 | C102: Salad | D102: 6 | E102: 120 | F102: Admin
A103: 4 | B103: 24/12/2025 | C103: Dahi | D103: 1 Kg | E103: 400 | F103: Admin
A104: 5 | B104: 24/12/2025 | C104: Lays | D104: 3 | E104: 210 | F104: Admin
A105: 6 | B105: 24/12/2025 | C105: Roti | D105: 12 | E105: 180 | F105: Admin
A106: Grand Total Amount | E106: =SUM(E100:E105) -> 4180
A108: Preapred By | F108: Clint Signature
A110: SR# | B110: Date | C110: Item Name | D110: QTY | E110: Price | F110: Department
A111: 1 | B111: 24/12/2025 | C111: Chicken Curry | D111: 1 | E111: 110 | F111: Admin
A112: 2 | B112: 24/12/2025 | C112: Roti | D112: 2 | E112: 30 | F112: Admin
A113: 3 | B113: 24/12/2025 | C113: Chay | D113: 1 | E113: 35 | F113: Admin
A114: Grand Total Amount | E114: =SUM(E111:E113) -> 175
A116: Preapred By | F116: Clint Signature
A118: SR# | B118: Date | C118: Item Name | D118: QTY | E118: Price | F118: Department
A119: 1 | B119: 26/12/2025 | C119: Sp- Biryani | D119: 1 | E119: 320 | F119: Admin
A120: 2 | B120: 26/12/2025 | C120: Salad | D120: 1 | E120: 20 | F120: Admin
A121: Grand Total Amount | E121: =SUM(E119:E120) -> 340
A123: Preapred By | F123: Clint Signature
A125: SR# | B125: Date | C125: Item Name | D125: QTY | E125: Price | F125: Department
A126: 1 | B126: 29/12/2025 | C126: Ch- Hara Masala | D126: 4 | E126: =D126*225 -> 900 | F126: Admin
A127: 2 | B127: 29/12/2025 | C127: Roti | D127: 8 | E127: =D127*15 -> 120 | F127: Admin
A128: 3 | B128: 29/12/2025 | C128: Salad | D128: 1 | E128: =D128*20 -> 20 | F128: Admin
A129: 4 | B129: 29/12/2025 | C129: Dahi | D129: 1 | E129: 50 | F129: Admin
A130: 5 | B130: 29/12/2025 | C130: Channa Chat | D130: 1 | E130: 120 | F130: Admin
A131: 6 | B131: 29/12/2025 | C131: Fruit Chat | D131: 1 | E131: 120 | F131: Admin
A132: 7 | B132: 29/12/2025 | C132: Ch- Curry | D132: 1 | E132: 110 | F132: Admin
A133: Grand Total Amount | E133: =SUM(E126:E132) -> 1440
A135: Preapred By | F135: Clint Signature
...

Sheet Summary of Admin 
A1: SUMMARY OF ADMIN DEPART
A2: SR# | B2: Date | C2: Name | D2: Amount | E2: Depart
A3: 1 | B3: 46009 | C3: Malik Riaz Sb | D3: 605 | E3: Admin
A4: 2 | B4: 46010 | C4: Malik Riaz Sb | D4: 200 | E4: Admin
A5: 3 | B5: 46013 | C5: Malik Riaz Sb | D5: 190 | E5: Admin
A6: 4 | B6: 46014 | C6: Malik Riaz Sb | D6: 530 | E6: Admin
A7: 5 | B7: 46014 | C7: Malik Riaz Sb | D7: 3220 | E7: Admin
A8: 6 | B8: 46015 | C8: Malik Riaz Sb | D8: 175 | E8: Admin
A9: 7 | B9: 46020 | C9: Malik Riaz Sb | D9: 1440 | E9: Admin
A10: 8 | B10: 46021 | C10: Malik Riaz Sb | D10: 1755 | E10: Admin
A11: 9 | B11: 46022 | C11: Malik Riaz Sb | D11: 1340 | E11: Admin
A12: Grand Total Amount | D12: =SUM(D3:D11) -> 9455
A14: SUMMARY OF ADMIN DEPART
A15: SR# | B15: Date | C15: Name | D15: Amount | E15: Depart
A16: 1 | B16: 46023 | C16: Malik Riaz Sb | D16: 200 | E16: Admin
A17: 2 | B17: 46024 | C17: Malik Riaz Sb | D17: 840 | E17: Admin
A18: 3 | B18: 46024 | C18: Malik Riaz Sb | D18: 760 | E18: Admin
A19: 4 | B19: 46027 | C19: Malik Riaz Sb | D19: 620 | E19: Admin
A20: 5 | B20: 46027 | C20: Malik Riaz Sb | D20: 560 | E20: Admin
A21: 6 | B21: 46027 | C21: Malik Riaz Sb | D21: 590 | E21: Admin
A22: 7 | B22: 46028 | C22: Malik Riaz Sb | D22: 620 | E22: Admin
A23: 8 | B23: 46028 | C23: Malik Riaz Sb | D23: 1700 | E23: Admin
A24: 9 | B24: 46028 | C24: Malik Riaz Sb | D24: 280 | E24: Admin
A25: 10 | B25: 46028 | C25: Malik Riaz Sb | D25: 340 | E25: Admin
A26: 11 | B26: 46028 | C26: Malik Riaz Sb | D26: 1110 | E26: Admin
A27: 12 | B27: 46029 | C27: Malik Riaz Sb | D27: 240 | E27: Admin
A28: 13 | B28: 46030 | C28: Malik Riaz Sb | D28: 1210 | E28: Admin
A29: Grand Total Amount | D29: =SUM(D16:D28) -> 9070

Sheet Printing
A1: SR# | B1: Date | C1: Item Name | D1: QTY | E1: Price | F1: Department
A2: 1 | B2: 16/12/2025 | C2: Chicken Karahi | D2: 2 Plate | E2: 400 | F2: Printing
A3: 2 | B3: 16/12/2025 | C3: Chawal | D3: 2 | E3: 200 | F3: Printing
A4: 3 | B4: 16/12/2025 | C4: Dall | D4: 2 | E4: 160 | F4: Printing
A5: 4 | B5: 16/12/2025 | C5: Roti | D5: 5 | E5: 75 | F5: Printing
A6: 5 | B6: 16/12/2025 | C6: Salad | D6: 2 | E6: 50 | F6: Printing
A7: Grand Total Amount | E7: =SUM(E2:E6) -> 885
A9: Preapred By | F9: Clint Signature
A11: SR# | B11: Date | C11: Item Name | D11: QTY | E11: Price | F11: Department
A12: 1 | B12: 46036 | C12: Sp-Ch-Pulao | D12: 4 | E12: =D12*320 -> 1280 | F12: Printing
A13: 2 | B13: 46036 | C13: Salad | D13: 4 | E13: =D13*30 -> 120 | F13: Printing
A14: 3 | B14: 46036 | C14: Dahi | D14: 0.5 | E14: =D14*400 -> 200 | F14: Printing
A15: 4 | B15: 46036 | C15: Cold Drink | D15: 4 | E15: =D15*70 -> 280 | F15: Printing
A16: 5 | B16: 46036 | C16: Roti | D16: 4 | E16: =D16*15 -> 60 | F16: Printing
A17: Grand Total Amount | E17: =SUM(E12:E16) -> 1940
A19: Preapred By | F19: Clint Signature
A22: SUMMARY OF SAMPLE DEPART
A23: SR# | B23: Date | C23: Name | D23: Amount | E23: Depart
A24: 1 | B24: 46036 | C24: Waseem Sb | D24: 1940 | E24: Printing
A25: Grand Total Amount | D25: =SUM(D24:D24) -> 1940
A26: Preapred By | E26: Clint Signature
A31: Admin Sig

Sheet Sample
A1: SR# | B1: Date | C1: Item Name | D1: QTY | E1: Price | F1: Department
A2: 1 | B2: 16/12/2025 | C2: Dall | D2: 4 | E2: 320 | F2: Sampl
A3: 2 | B3: 16/12/2025 | C3: Chawal | D3: 4 | E3: 400 | F3: Sampl
A4: 3 | B4: 16/12/2025 | C4: Chicken Karahi | D4: 4 | E4: 800 | F4: Sampl
A5: 4 | B5: 16/12/2025 | C5: Roti | D5: 6 | E5: 90 | F5: Sampl
A6: 5 | B6: 16/12/2025 | C6: Salad | D6: 1 Bowl | E6: 200 | F6: Sampl
A7: 6 | B7: 16/12/2025 | C7: Cold Drink | D7: 4 | E7: 280 | F7: Sampl
A8: Grand Total Amount | E8: =SUM(E2:E7) -> 2090
A10: Preapred By | F10: Clint Signature
A13: SR# | B13: Date | C13: Item Name | D13: QTY | E13: Price | F13: Department
A14: 1 | B14: 18/12/2025 | C14: Chicken Biryani | D14: 5 | E14: 800 | F14: Sampl
A15: 2 | B15: 18/12/2025 | C15: Salad | D15: 2 | E15: 40 | F15: Sampl
A16: 3 | B16: 18/12/2025 | C16: Cold Drink | D16: 5 | E16: 350 | F16: Sampl
A20: Grand Total Amount | E20: =SUM(E14:E19) -> 1190
A22: Preapred By | F22: Clint Signature
A25: SR# | B25: Date | C25: Item Name | D25: QTY | E25: Price | F25: Department
A26: 1 | B26: 19/12/2025 | C26: Chicken Biryani | D26: 1Kg | E26: 1600 | F26: Sampl
A27: 2 | B27: 19/12/2025 | C27: Salad | D27: 2 | E27: 40 | F27: Sampl
A28: 3 | B28: 19/12/2025 | C28: Cold Drink | D28: 4 | E28: 280 | F28: Sampl
A32: Grand Total Amount | E32: =SUM(E26:E31) -> 1920
A34: Preapred By | F34: Clint Signature
A36: SR# | B36: Date | C36: Item Name | D36: QTY | E36: Price | F36: Department
A37: 1 | B37: 20/12/2025 | C37: Biscut | E37: 40 | F37: Sampl
A38: 2 | B38: 20/12/2025 | C38: Salad | D38: 2 | E38: 40 | F38: Sampl
A39: 3 | B39: 20/12/2025 | C39: Cold Drink | E39: 300 | F39: Sampl
A40: 4 | B40: 20/12/2025 | C40: Fruit Chat | D40: 1 | E40: 120 | F40: Sampl
A41: 5 | B41: 20/12/2025 | C41: Tissue Box | D41: 1 | E41: 270 | F41: Sampl
A42: 6 | B42: 20/12/2025 | C42: Karahi | D42: 4 | E42: 800 | F42: Sampl
A43: 7 | B43: 20/12/2025 | C43: Roti | D43: 10 | E43: 150 | F43: Sampl
A44: Grand Total Amount | E44: =SUM(E37:E43) -> 1720
A46: Preapred By | F46: Clint Signature
A48: SR# | B48: Date | C48: Item Name | D48: QTY | E48: Price | F48: Department
A49: 1 | B49: 20/12/2025 | C49: Aloo Biryani | D49: 72 | E49: =D49*110 -> 7920 | F49: Sampl
A50: Grand Total Amount | E50: =SUM(E49:E49) -> 7920
A52: Preapred By | F52: Clint Signature
A55: SR# | B55: Date | C55: Item Name | D55: QTY | E55: Price | F55: Department
A56: 1 | B56: 22/12/2025 | C56: Ch- Karahi | D56: 3 | E56: 600 | F56: Sampl
A57: 2 | B57: 22/12/2025 | C57: Roti | D57: 8 | E57: 120 | F57: Sampl
A58: 3 | B58: 22/12/2025 | C58: Salad | D58: 1 | E58: 20 | F58: Sampl
A59: 4 | B59: 22/12/2025 | C59: Cold Drink | D59: 3 | E59: 210 | F59: Sampl
A60: Grand Total Amount | E60: =SUM(E56:E59) -> 950
A62: Preapred By | F62: Clint Signature
A64: SR# | B64: Date | C64: Item Name | D64: QTY | E64: Price | F64: Department
A65: 1 | B65: 23/12/2025 | C65: Aalo Biryani | D65: 89 | E65: 9790 | F65: Sample
A66: Grand Total Amount | E66: =SUM(E65:E65) -> 9790
A68: Preapred By | F68: Clint Signature
A71: SR# | B71: Date | C71: Item Name | D71: QTY | E71: Price | F71: Department
A72: 1 | B72: 24/12/2025 | C72: Aalo Biryani | D72: 96 | E72: 10560 | F72: Sample
A73: Grand Total Amount | E73: =SUM(E72:E72) -> 10560
A75: Preapred By | F75: Clint Signature
A78: SR# | B78: Date | C78: Item Name | D78: QTY | E78: Price | F78: Department
A79: 1 | B79: 24/12/2025 | C79: Dall Fry | D79: 4 | E79: 720 | F79: Sampl
A80: 2 | B80: 24/12/2025 | C80: Roti | D80: 12 | E80: 180 | F80: Sampl
A81: 3 | B81: 24/12/2025 | C81: Cold Drink | D81: 5 | E81: 350 | F81: Sampl
A82: 4 | B82: 24/12/2025 | C82: Salad | D82: 2 | E82: 50
A83: Grand Total Amount | E83: =SUM(E79:E82) -> 1300
A85: Preapred By | F85: Clint Signature
A87: SR# | B87: Date | C87: Item Name | D87: QTY | E87: Price | F87: Department
A88: 1 | B88: 26/12/2025 | C88: Aalo Biryani | D88: 90 | E88: =D88*110 -> 9900 | F88: Sample
A89: Grand Total Amount | E89: =SUM(E88:E88) -> 9900
A91: Preapred By | F91: Clint Signature
A93: SR# | B93: Date | C93: Item Name | D93: QTY | E93: Price | F93: Department
A94: 1 | B94: 26/12/2025 | C94: Sp- Biryani | D94: 3 | E94: =D94*320 -> 960 | F94: Sample
A95: 2 | B95: 26/12/2025 | C95: Botel | D95: 2 | E95: =D95*70 -> 140 | F95: Sample
A96: 3 | B96: 26/12/2025 | C96: Raita | D96: 2 | E96: 200 | F96: Sample
A97: 4 | B97: 26/12/2025 | C97: Salad | D97: 2 | E97: 40 | F97: Sample
A98: Grand Total Amount | E98: =SUM(E94:E97) -> 1340
A100: Preapred By | F100: Clint Signature
A102: SR# | B102: Date | C102: Item Name | D102: QTY | E102: Price | F102: Department
A103: 1 | B103: 29/12/2025 | C103: Aloo Biryani | D103: 74 | E103: =D103*110 -> 8140 | F103: Sample
A104: Grand Total Amount | E104: =SUM(E103:E103) -> 8140
A106: Preapred By | F106: Clint Signature
A108: SR# | B108: Date | C108: Item Name | D108: QTY | E108: Price | F108: Department
A109: 1 | B109: 31/12/2025 | C109: Dahi | E109: 100 | F109: Sample
A110: 2 | B110: 31/12/2025 | C110: Salad | D110: 1 | E110: 25 | F110: Sample
A111: 3 | B111: 31/12/2025 | C111: Cold Drink | D111: 3 | E111: =D111*70 -> 210 | F111: Sample
A112: 4 | B112: 31/12/2025 | C112: Roti | D112: 6 | E112: =D112*15 -> 90 | F112: Sample
A113: 5 | B113: 31/12/2025 | C113: Sp- Dall Fry | D113: 2 | E113: =D113*180 -> 360 | F113: Sample
A114: 6 | B114: 31/12/2025 | C114: Ch- Curry | D114: 1 | E114: =D114*110 -> 110 | F114: Sample
A115: Grand Total Amount | E115: =SUM(E109:E114) -> 895
A117: Preapred By | F117: Clint Signature
A119: SR# | B119: Date | C119: Item Name | D119: QTY | E119: Price | F119: Department
A120: 1 | B120: 46023 | C120: Aloo Biryani | D120: 80 | E120: =D120*110 -> 8800 | F120: Sample
A121: Grand Total Amount | E121: =SUM(E120:E120) -> 8800
A123: Preapred By | F123: Clint Signature
A125: SR# | B125: Date | C125: Item Name | D125: QTY | E125: Price | F125: Department
A126: 1 | B126: 46023 | C126: Ch- Biryani | D126: 2 | E126: =D126*320 -> 640 | F126: Sample
A127: 2 | B127: 46023 | C127: Cold Drink | D127: 1 | E127: 70 | F127: Sample
A128: Grand Total Amount | E128: =SUM(E126:E127) -> 710
A130: Preapred By | F130: Clint Signature
A132: SR# | B132: Date | C132: Item Name | D132: QTY | E132: Price | F132: Department
A133: 1 | B133: 46024 | C133: Sp- Biryani | D133: 1 | E133: =D133*320 -> 320 | F133: Sample
A134: 2 | B134: 46024 | C134: Salad | D134: 1 | E134: =D134*30 -> 30 | F134: Sample
A135: 3 | B135: 46024 | C135: Cold Drink | D135: 1 | E135: =D135*70 -> 70 | F135: Sample
A136: Grand Total Amount | E136: =SUM(E133:E135) -> 420
A138: Preapred By | F138: Clint Signature
A140: SR# | B140: Date | C140: Item Name | D140: QTY | E140: Price | F140: Department
A141: 1 | B141: 46024 | C141: Aloo Biryani | D141: 94 | E141: =D141*110 -> 10340 | F141: Sample
A142: Grand Total Amount | E142: =SUM(E141:E141) -> 10340
A144: Preapred By | F144: Clint Signature
...

Sheet Summary of Sample Depart
A1: SUMMARY OF SAMPLE DEPART
A2: SR# | B2: Date | C2: Name | D2: Amount | E2: Depart
A3: 1 | B3: 46007 | C3: Saeed Sb | D3: 2090 | E3: Sample
A4: 2 | B4: 46009 | C4: Saeed Sb | D4: 1190 | E4: Sample
A5: 3 | B5: 46010 | C5: Saeed Sb | D5: 1920 | E5: Sample
A6: 4 | B6: 46011 | C6: Saeed Sb | D6: 1720 | E6: Sample
A7: 5 | B7: 46011 | C7: Saeed Sb | D7: 7920 | E7: Sample
A8: 6 | B8: 46013 | C8: Saeed Sb | D8: 950 | E8: Sample
A9: 7 | B9: 46014 | C9: Saeed Sb | D9: 9790 | E9: Sample
A10: 8 | B10: 46014 | C10: Saeed Sb | D10: 1325 | E10: Sample
A11: 10 | B11: 46015 | C11: Saeed Sb | D11: 1300 | E11: Sample
A12: 11 | B12: 46015 | C12: Saeed Sb | D12: 10560 | E12: Sample
A13: 13 | B13: 46017 | C13: Saeed Sb | D13: 9900 | E13: Sample
A14: 14 | B14: 46017 | C14: Saeed Sb | D14: 1340 | E14: Sample
... A16: 16 | B16: 46022 | C16: Sohail Sb | D16: 895 | E16: Sample
A17: Grand Total Amount | D17: =SUM(D3:D16) -> 59040
A19: SUMMARY OF SAMPLE DEPART
A20: SR# | B20: Date | C20: Name | D20: Amount | E20: Depart
A21: 1 | B21: 46023 | C21: Sohail Sb | D21: 710 | E21: Sample
A22: 2 | B22: 46023 | C22: Sohail Sb | D22: 8800 | E22: Sample
A23: 3 | B23: 46024 | C23: Sohail Sb | D23: 420 | E23: Sample
A24: 4 | B24: 46024 | C24: Sohail Sb | D24: 10340 | E24: Sample
A25: 5 | B25: 46025 | C25: Sohail Sb | D25: 1090 | E25: Sample
A26: 6 | B26: 46027 | C26: Sohail Sb | D26: 5350 | E26: Sample
A27: 7 | B27: 46028 | C27: Sohail Sb | D27: 750 | E27: Sample
A28: 8 | B28: 46029 | C28: Sohail Sb | D28: 560 | E28: Sample
A29: 9 | B29: 46030 | C29: Sohail Sb | D29: 915 | E29: Sample
A30: 10 | B30: 46030 | C30: Sohail Sb | D30: 9240 | E30: Sample
A31: 11 | B31: 46031 | C31: Sohail Sb | D31: 1010 | E31: Sample
A32: 12 | B32: 46031 | C32: Sohail Sb | D32: 7805 | E32: Sample
... A38: 18 | B38: 46037 | C38: Sohail Sb | D38: 3405 | E38: Sample
A39: Grand Total Amount | D39: =SUM(D21:D38) -> 70655
A40: Preapred By | E40: Clint Signature
A44: Admin Sig

Sheet Maintences 
A1: SR# | B1: Date | C1: Item Name | D1: QTY | E1: Price | F1: Department
A2: 1 | B2: 20/12/2025 | C2: Rice | D2: 1 | E2: 110 | F2: Maintences
A3: 2 | B3: 20/12/2025 | C3: Karahi | D3: 2 | E3: 240 | F3: Maintences
A4: 3 | B4: 20/12/2025 | C4: Roti | D4: 6 | E4: 90 | F4: Maintences
A6: Grand Total Amount | E6: =SUM(E2:E5) -> 440
A8: Preapred By | F8: Clint Signature
A10: SR# | B10: Date | C10: Item Name | D10: QTY | E10: Price | F10: Department
A11: 1 | B11: 22/12/2025 | C11: Ch- Karahi | D11: 1 | E11: 200 | F11: Maintences
A12: 2 | B12: 22/12/2025 | C12: Sabzi | D12: 1 | E12: 80 | F12: Maintences
A13: 3 | B13: 22/12/2025 | C13: Roti | D13: 6 | E13: 90 | F13: Maintences
A15: Grand Total Amount | E15: =SUM(E11:E14) -> 370
A17: Preapred By | F17: Clint Signature
A19: SR# | B19: Date | C19: Item Name | D19: QTY | E19: Price | F19: Department
A20: 1 | B20: 22/12/2025 | C20: Ch- Karahi | D20: 1 | E20: 200 | F20: Maintences
A21: 2 | B21: 22/12/2025 | C21: Anda Channa | D21: 1 | E21: 110 | F21: Maintences
A22: 3 | B22: 22/12/2025 | C22: Pulao | D22: 1 | E22: 120 | F22: Maintences
A23: 4 | B23: 22/12/2025 | C23: Dall | D23: 1 | E23: 80 | F23: Maintences
A24: 5 | B24: 22/12/2025 | C24: Roti | D24: 6 | E24: 90 | F24: Maintences
A25: 6 | B25: 22/12/2025 | C25: Chai | D25: 2 | E25: 70 | F25: Maintences
A26: Grand Total Amount | E26: =SUM(E20:E25) -> 670
A28: Preapred By | F28: Clint Signature
A30: SR# | B30: Date | C30: Item Name | D30: QTY | E30: Price | F30: Department
A31: 1 | B31: 23/12/2025 | C31: Chai | D31: 6 | E31: 90 | F31: Maintences
A32: 2 | B32: 23/12/2025 | C32: Parathy | D32: 3 | E32: 105 | F32: Maintences
A33: 3 | B33: 23/12/2025 | C33: Channay | D33: 1 | E33: 80 | F33: Maintences
A34: 4 | B34: 23/12/2025 | C34: Roti | D34: 4 | E34: 60 | F34: Maintences
A35: 5 | B35: 23/12/2025 | C35: Dall | D35: 1 | E35: 80 | F35: Maintences
A36: 6 | B36: 23/12/2025 | C36: Ch- White Biryani | D36: 1 | E36: 120 | F36: Maintences
A37: 7 | B37: 23/12/2025 | C37: Zeera White Rice | D37: 1 | E37: 100 | F37: Maintences
A38: 8 | B38: 23/12/2025 | C38: Sabzi | D38: 2 | E38: 160 | F38: Maintences
A39: Grand Total Amount | E39: =SUM(E31:E38) -> 795
A41: Preapred By | F41: Clint Signature
A43: SR# | B43: Date | C43: Item Name | D43: QTY | E43: Price | F43: Department
A44: 1 | B44: 23/12/2025 | C44: Ch- White Biryani | D44: 1 | E44: 200 | F44: Maintences
A45: 2 | B45: 23/12/2025 | C45: Ch- Karahi | D45: 1 | E45: 220 | F45: Maintences
A46: 3 | B46: 23/12/2025 | C46: Roti | D46: 5 | E46: 75 | F46: Maintences
A47: 4 | B47: 23/12/2025 | C47: Salad | D47: 1 | E47: 20 | F47: Maintences
A48: Grand Total Amount | E48: =SUM(E44:E47) -> 515
A50: Preapred By | F50: Clint Signature
A52: SR# | B52: Date | C52: Item Name | D52: QTY | E52: Price | F52: Department
A53: 1 | B53: 24/12/2025 | C53: Dall Fry | D53: 2 | E53: 360 | F53: Maintences
A54: 2 | B54: 24/12/2025 | C54: Roti | D54: 6 | E54: 90 | F54: Maintences
A55: Grand Total Amount | E55: =SUM(E53:E54) -> 450
A57: Preapred By | F57: Clint Signature
A60: SR# | B60: Date | C60: Item Name | D60: QTY | E60: Price | F60: Department
A61: 1 | B61: 24/12/2025 | C61: Parathy | D61: 3 | E61: 105 | F61: Maintences
A62: 2 | B62: 24/12/2025 | C62: Chai | D62: 4 | E62: 140 | F62: Maintences
A63: 3 | B63: 24/12/2025 | C63: Aalo Tari | D63: 1 | E63: 70 | F63: Maintences
A64: 4 | B64: 24/12/2025 | C64: Roti | D64: 6 | E64: 90 | F64: Maintences
A65: 5 | B65: 24/12/2025 | C65: Rzera rice | D65: 1 | E65: 100 | F65: Maintences
A66: 6 | B66: 24/12/2025 | C66: Chicken Allo | D66: 1 | E66: 220 | F66: Maintences
A67: 7 | B67: 24/12/2025 | C67: Anda Dall Ghotala | D67: 1 | E67: 220 | F67: Maintences
A68: Grand Total Amount | E68: =SUM(E61:E67) -> 945
A70: Preapred By | F70: Clint Signature
A72: SR# | B72: Date | C72: Item Name | D72: QTY | E72: Price | F72: Department
A73: 1 | B73: 25/12/2025 | C73: Parathy | D73: 3 | E73: 105 | F73: Maintences
A74: 2 | B74: 25/12/2025 | C74: Channa | D74: 1 | E74: 80 | F74: Maintences
A75: 3 | B75: 25/12/2025 | C75: Chai | D75: 3 | E75: 105 | F75: Maintences
A76: 4 | B76: 25/12/2025 | C76: S. Sabzi | D76: 1 | E76: 180 | F76: Maintences
A77: 5 | B77: 25/12/2025 | C77: Roti | D77: 5 | E77: 75 | F77: Maintences
A78: 6 | B78: 25/12/2025 | C78: Salad | D78: 1 | E78: 20 | F78: Maintences
A79: 7 | B79: 25/12/2025 | C79: S. Chicken | D79: 1 | E79: 220 | F79: Maintences
A80: Grand Total Amount | E80: =SUM(E73:E79) -> 785
A82: Preapred By | F82: Clint Signature
A84: SR# | B84: Date | C84: Item Name | D84: QTY | E84: Price | F84: Department
A85: 1 | B85: 26/12/2025 | C85: Sp- Biryani | D85: 3 | E85: =D85*320 -> 960 | F85: Maintences
A86: 2 | B86: 26/12/2025 | C86: Simple Biryani | D86: 1 | E86: 180 | F86: Maintences
A87: 3 | B87: 26/12/2025 | C87: Salad | D87: 1 | E87: 20 | F87: Maintences
A88: Grand Total Amount | E88: =SUM(E85:E87) -> 1160
A90: Preapred By | F90: Clint Signature
A92: SR# | B92: Date | C92: Item Name | D92: QTY | E92: Price | F92: Department
A93: 1 | B93: 29/12/2025 | C93: Ch- Hara Masala | D93: 1 | E93: =D93*225 -> 225 | F93: Maintences
A94: 2 | B94: 29/12/2025 | C94: Roti | D94: 6 | E94: =D94*15 -> 90 | F94: Maintences
A95: 3 | B95: 29/12/2025 | C95: Salad | D95: 1 | E95: 20 | F95: Maintences
A96: Grand Total Amount | E96: =SUM(E93:E95) -> 335
A98: Preapred By | F98: Clint Signature
A100: SR# | B100: Date | C100: Item Name | D100: QTY | E100: Price | F100: Department
A101: 1 | B101: 30/12/2025 | C101: Ch- Pulao | D101: 2 | E101: =D101*250 -> 500 | F101: Maintences
A102: Grand Total Amount | E102: =SUM(E101:E101) -> 500
A104: Preapred By | F104: Clint Signature
A106: SR# | B106: Date | C106: Item Name | D106: QTY | E106: Price | F106: Department
A107: 1 | B107: 31/12/2025 | C107: Ch- Karahi | D107: 2 | E107: =D107*225 -> 450 | F107: Maintences
A108: 2 | B108: 31/12/2025 | C108: Sp- Dall Fry | D108: 1 | E108: =D108*180 -> 180 | F108: Maintences
A109: 3 | B109: 31/12/2025 | C109: Roti | D109: 8 | E109: =D109*15 -> 120 | F109: Maintences
A110: Grand Total Amount | E110: =SUM(E107:E109) -> 750
A112: Preapred By | F112: Clint Signature
A114: SR# | B114: Date | C114: Item Name | D114: QTY | E114: Price | F114: Department
A115: 1 | B115: 46029 | C115: Beef Pulao | D115: 3 | E115: =D115*320 -> 960 | F115: Maintences
A116: 2 | B116: 46029 | C116: Chicken Curry | D116: 2 | E116: =D116*110 -> 220 | F116: Maintences
A117: 3 | B117: 46029 | C117: Roti | D117: 6 | E117: =D117*15 -> 90 | F117: Maintences
A118: 4 | B118: 46029 | C118: Salad | D118: 2 | E118: =D118*30 -> 60 | F118: Maintences
A119: 5 | B119: 46029 | C119: Chicken Karahi | D119: 5 | E119: =D119*220 -> 1100 | F119: Maintences
A120: 6 | B120: 46029 | C120: Roti | D120: 10 | E120: =D120*15 -> 150 | F120: Maintences
A121: Grand Total Amount | E121: =SUM(E115:E120) -> 2580
A123: Preapred By | F123: Clint Signature
A125: SR# | B125: Date | C125: Item Name | D125: QTY | E125: Price | F125: Department
A126: 1 | B126: 46035 | C126: Sp- Veg Pulao | D126: 3 | E126: =D126*250 -> 750 | F126: Maintences
A127: 2 | B127: 46035 | C127: Raita | D127: 0.25 | E127: =D127*400 -> 100 | F127: Maintences
A128: 3 | B128: 46035 | C128: Salad | D128: 1 | E128: 50 | F128: Maintences
A129: Grand Total Amount | E129: =SUM(E126:E128) -> 900
...

Sheet Summary Of Farhan Sb Maintenc
A1: SUMMARY OF MAINTENCES DEPART
A2: SR# | B2: Date | C2: Name | D2: Amount | E2: Depart
A3: 1 | B3: 46011 | C3: Farhan Sb | D3: 440 | E3: Maintences
A4: 2 | B4: 46013 | C4: Farhan Sb | D4: 370 | E4: Maintences
A5: 3 | B5: 46013 | C5: Farhan Sb | D5: 670 | E5: Maintences
A6: 4 | B6: 46014 | C6: Farhan Sb | D6: 515 | E6: Maintences
A7: 5 | B7: 46014 | C7: Farhan Sb | D7: 795 | E7: Maintences
A8: 6 | B8: 46015 | C8: Farhan Sb | D8: 945 | E8: Maintences
A9: 7 | B9: 46015 | C9: Farhan Sb | D9: 450 | E9: Maintences
A10: 8 | B10: 46016 | C10: Farhan Sb | D10: 785 | E10: Maintences
A11: 9 | B11: 46020 | C11: Farhan Sb | D11: 335 | E11: Maintences
A12: 10 | B12: 46021 | C12: Farhan Sb | D12: 500 | E12: Maintences
A13: 11 | B13: 46022 | C13: Farhan Sb | D13: 750 | E13: Maintences
A14: Grand Total Amount | D14: =SUM(D3:D13) -> 6555
A16: SUMMARY OF MAINTENCES DEPART
A17: SR# | B17: Date | C17: Name | D17: Amount | E17: Depart
A18: 1 | B18: 46029 | C18: Farhan Sb | D18: 2580 | E18: Maintences
A19: 2 | B19: 46035 | C19: Farhan Sb | D19: 900 | E19: Maintences
A20: 3 | B20: 46037 | C20: Farhan Sb | D20: 620 | E20: Maintences
A21: Grand Total Amount | D21: =SUM(D18:D20) -> 4100
A22: Preapred By | E22: Clint Signature
A27: Admin Sig

Sheet Senior Mess 
A1: LUNCH DYING DEPART | I1: LUNCH DYING DEPART
A2: SR# | B2: Date | C2: Name | D2: Item Name | E2: QTY | F2: Price | G2: Department | I2: SR# | J2: Date | K2: Name | L2: Item Name | M2: QTY | N2: Price | O2: Department
A3: 1 | B3: 16/12/2025 | C3: Daniyal | D3: 4 Karahi, 4 Chawal, 4 Dall,15 Roti | F3: 800+400+320+180 | G3: Dying Depart | I3: 1 | J3: 17/12/2025 | K3: Daniyal | L3: 6 Chicken Qorma+ 18 Roti+ 2 Dahi + Salad | N3: 1200+270+100+40 | O3: Dying Depart
A4: 2 | B4: 16/12/2025 | C4: Azeem | G4: Dying Depart | I4: 2 | J4: 17/12/2025 | K4: Azeem | O4: Dying Depart
A5: 3 | B5: 16/12/2025 | C5: Uaman | G5: Dying Depart | I5: 3 | J5: 17/12/2025 | K5: Uaman | O5: Dying Depart
A6: 4 | B6: 16/12/2025 | C6: Maroof | G6: Dying Depart | I6: 4 | J6: 17/12/2025 | K6: Maroof | O6: Dying Depart
A7: 5 | B7: 16/12/2025 | C7: Nasir | G7: Dying Depart | I7: 5 | J7: 17/12/2025 | K7: Nasir | O7: Dying Depart
A8: 6 | B8: 16/12/2025 | C8: Mueez | G8: Dying Depart | I8: 6 | J8: 17/12/2025 | K8: Mueez | O8: Dying Depart
A9: Grand Total Amount | F9: 1700 | I9: Grand Total Amount | N9: 1610
A11: Preapred By | G11: Clint Signature | I11: Preapred By | O11: Clint Signature
A13: DINNER DYING DEPART | I13: DINNER DYING DEPART
A14: SR# | B14: Date | C14: Name | D14: Item Name | E14: QTY | F14: Price | G14: Department | I14: SR# | J14: Date | K14: Name | L14: Item Name | M14: QTY | N14: Price | O14: Department
A15: 1 | B15: 16/12/2025 | C15: Ali Raza | D15: 3 Sabzi+ 10Roti | F15: 240+150 | G15: Dying Depart | I15: 1 | J15: 17/12/2025 | K15: Daniyal | L15: 1 Sabzi+13 Roti+ 1 Salad | N15: 80+195+20 | O15: Dying Depart
A16: 2 | B16: 16/12/2025 | C16: Azeem | G16: Dying Depart | I16: 2 | J16: 17/12/2025 | K16: Maroof | O16: Dying Depart
A17: 3 | B17: 16/12/2025 | C17: Uaman | G17: Dying Depart | I17: 3 | J17: 17/12/2025 | K17: Yaseen | O17: Dying Depart
A18: Grand Total Amount | F18: 390 | I18: 4 | J18: 17/12/2025 | K18: Ali Raza | O18: Dying Depart
I19: 5 | J19: 17/12/2025 | K19: Azeem | O19: Dying Depart
A20: Preapred By | G20: Clint Signature | O20: Dying Depart
I21: Grand Total Amount | N21: 295
I23: Preapred By | O23: Clint Signature
A27: LUNCH DYING DEPART | I27: DINNER DYING DEPART
A28: SR# | B28: Date | C28: Name | D28: Item Name | E28: QTY | F28: Price | G28: Department | I28: SR# | J28: Date | K28: Name | L28: Item Name | M28: QTY | N28: Price | O28: Department
A29: 1 | B29: 17/12/2025 | C29: Munawar | D29: Chicken Qorma 6+ Roti 15+ Salad 2 Bowl | F29: 1200+225+120 | G29: Dying Depart | I29: 1 | J29: 17/12/2025 | K29: Munawar | L29: Egg 2, Chicken Karahi 4, Chicken Stew 4, Biryani 5, | N29: 50+800+800+900 | O29: Dying Depart
A30: 2 | B30: 17/12/2025 | C30: Waqas | G30: Dying Depart | I30: 2 | J30: 17/12/2025 | K30: Waqas | O30: Dying Depart
A31: 3 | B31: 17/12/2025 | C31: Jhandad | G31: Dying Depart | I31: 3 | J31: 17/12/2025 | K31: Jhandad | O31: Dying Depart
A32: 4 | B32: 17/12/2025 | C32: Rafeeq | G32: Dying Depart | I32: 4 | J32: 17/12/2025 | K32: Rafeeq | O32: Dying Depart
A33: 5 | B33: 17/12/2025 | C33: Shakeel | G33: Dying Depart | I33: 5 | J33: 17/12/2025 | K33: Shakeel | O33: Dying Depart
A34: 6 | B34: 17/12/2025 | C34: Aqaib | G34: Dying Depart | I34: 6 | J34: 17/12/2025 | K34: Aqaib | O34: Dying Depart
A35: Grand Total Amount | F35: =1200+225+120 -> 1545 | I35: Grand Total Amount | N35: =50+800+800+900 -> 2550
A37: Preapred By | G37: Clint Signature | I37: Preapred By | O37: Clint Signature
A43: LUNCH DYING DEPART | I43: DINNER DYING DEPART
A44: SR# | B44: Date | C44: Name | D44: Item Name | E44: QTY | F44: Price | G44: Department | I44: SR# | J44: Date | K44: Name | L44: Item Name | M44: QTY | N44: Price | O44: Department
A45: 1 | B45: 18/12/2025 | C45: Daniyal | D45: Roti 15+ Chicken Stew 3+ Pulao 2+ Biryani 1+ Salad | F45: 225+600+240+180+20 | G45: Dying Depart | I45: 1 | J45: 18/12/2025 | K45: Daniyal | L45: Chicken Karahi 3+ Dall 1+ Roti 18 | N45: 600+80+270 | O45: Dying Depart
A46: 2 | B46: 18/12/2025 | G46: Dying Depart | I46: 2 | J46: 18/12/2025 | O46: Dying Depart
A47: 3 | B47: 18/12/2025 | G47: Dying Depart | I47: 3 | J47: 18/12/2025 | O47: Dying Depart
A48: 4 | B48: 18/12/2025 | G48: Dying Depart | I48: 4 | J48: 18/12/2025 | O48: Dying Depart
A49: 5 | B49: 18/12/2025 | G49: Dying Depart | I49: 5 | J49: 18/12/2025 | O49: Dying Depart
A50: 6 | B50: 18/12/2025 | G50: Dying Depart | I50: 6 | J50: 18/12/2025 | O50: Dying Depart
A51: Grand Total Amount | F51: =225+600+240+180+20 -> 1265 | I51: Grand Total Amount | N51: =600+80+270 -> 950
A53: Preapred By | G53: Clint Signature | I53: Preapred By | O53: Clint Signature
A56: LUNCH DYING DEPART
A57: SR# | B57: Date | C57: Name | D57: Item Name | E57: QTY | F57: Price | G57: Department
A58: 1 | B58: 19/12/2025 | C58: Munawar | D58: Biryani 5+ Salad bowl 2+ Rita 1kg | F58: 900+200+500 | G58: Dying Depart
A59: 2 | B59: 19/12/2025 | C59: Waqas | G59: Dying Depart
A60: 3 | B60: 19/12/2025 | C60: Jhandad | G60: Dying Depart
A61: 4 | B61: 19/12/2025 | C61: Rafeeq | G61: Dying Depart
A62: 5 | B62: 19/12/2025 | C62: Aqaib | G62: Dying Depart
A63: Grand Total Amount | G63: Dying Depart
F64: =900+200+500 -> 1600
A65: Preapred By
G66: Clint Signature
A68: LUNCH DYING DEPART | I68: DINNER DYING DEPART
A69: SR# | B69: Date | C69: Name | D69: Item Name | E69: QTY | F69: Price | G69: Department | I69: SR# | J69: Date | K69: Name | L69: Item Name | M69: QTY | N69: Price | O69: Department
A70: 1 | B70: 19/12/2025 | C70: Daniyal | D70: Raita 1 bowl + Salad 1+Biryani 6 | F70: 500+20+1080 | G70: Dying Depart | I70: 1 | J70: 19/12/2025 | K70: Daniyal | L70: Dall Fry 2+ karahi 3+ roti 21+ Dahi | N70: 100+200+540+315 | O70: Dying Depart
A71: 2 | B71: 19/12/2025 | G71: Dying Depart | I71: 2 | J71: 19/12/2025 | O71: Dying Depart
A72: 3 | B72: 19/12/2025 | G72: Dying Depart | I72: 3 | J72: 19/12/2025 | O72: Dying Depart
A73: 4 | B73: 19/12/2025 | G73: Dying Depart | I73: 4 | J73: 19/12/2025 | O73: Dying Depart
A74: 5 | B74: 19/12/2025 | G74: Dying Depart | I74: 5 | J74: 19/12/2025 | O74: Dying Depart
A75: 6 | B75: 19/12/2025 | G75: Dying Depart | I75: 6 | J75: 19/12/2025 | O75: Dying Depart
A76: Grand Total Amount | F76: =500+20+1080 -> 1600 | I76: Grand Total Amount | N76: =100+200+540+315 -> 1155
A78: Preapred By | G78: Clint Signature | I78: Preapred By | O78: Clint Signature
A83: LUNCH DYING DEPART | I83: LUNCH DYING DEPART
A84: SR# | B84: Date | C84: Name | D84: Item Name | E84: QTY | F84: Price | G84: Department | I84: SR# | J84: Date | K84: Name | L84: Item Name | M84: QTY | N84: Price | O84: Department
A85: 1 | B85: 20/12/2025 | C85: Waqas | D85: Sabzi 2+ Karahi 3+ Salad 1+ Roti 15+ Dahi | F85: 160+600+100+225+50 | G85: Dying Depart | I85: 1 | J85: 20/12/2025 | K85: Daniyal | L85: Karahi 3+ Roti 12+ Salad 2 | N85: 600+180+40 | O85: Dying Depart
A86: 2 | B86: 20/12/2025 | C86: Jhandad | G86: Dying Depart | I86: 2 | J86: 20/12/2025 | O86: Dying Depart
A87: 3 | B87: 20/12/2025 | C87: Rafeeq | G87: Dying Depart | I87: 3 | J87: 20/12/2025 | O87: Dying Depart
A88: 4 | B88: 20/12/2025 | C88: Shakeel | G88: Dying Depart | I88: 4 | J88: 20/12/2025 | O88: Dying Depart
A89: 5 | B89: 20/12/2025 | C89: Aqaib | G89: Dying Depart | I89: 5 | J89: 20/12/2025 | O89: Dying Depart
A90: Grand Total Amount | F90: =160+600+100+225+50 -> 1135 | I90: Grand Total Amount | N90: =600+180+40 -> 820
A92: Preapred By | G92: Clint Signature | I92: Preapred By | O92: Clint Signature
A96: LUNCH DYING DEPART | I96: DINNER DYING DEPART
A97: SR# | B97: Date | C97: Name | D97: Item Name | E97: QTY | F97: Price | G97: Department | I97: SR# | J97: Date | K97: Name | L97: Item Name | M97: QTY | N97: Price | O97: Department
A98: 1 | B98: 20/12/2025 | C98: Nasir | D98: Karahi 1+ Roti 3 | F98: 200+45 | G98: Dying Depart | I98: 1 | J98: 20/12/2025 | K98: Daniyal | L98: Dall 3+ Karahi 1+ Roti 16 | N98: 240+200+240 | O98: Dying Depart
A99: 2 | B99: 20/12/2025 | C99: Mueez | G99: Dying Depart | I99: 2 | J99: 20/12/2025 | O99: Dying Depart
A100: Grand Total Amount | F100: =200+45 -> 245 | I100: 3 | J100: 20/12/2025 | O100: Dying Depart
I101: 4 | J101: 20/12/2025 | O101: Dying Depart
A102: Preapred By | G102: Clint Signature | I102: 5 | J102: 20/12/2025 | O102: Dying Depart
I103: Grand Total Amount | N103: =240+200+240 -> 680
I105: Preapred By | O105: Clint Signature
A108: LUNCH DYING DEPART | I108: LUNCH DYING DEPART
A109: SR# | B109: Date | C109: Name | D109: Item Name | E109: QTY | F109: Price | G109: Department | I109: SR# | J109: Date | K109: Name | L109: Item Name | M109: QTY | N109: Price | O109: Department
A110: 1 | B110: 21/12/2025 | C110: Aqib Sab | D110: Dall 1+ Chawal 1+ Salad 1 | F110: 80+100+20 | G110: Dying Depart | I110: 1 | J110: 21/12/2025 | K110: Daniyal | L110: Dall 2+ Roti 10+ Salad 2+ Channa chat 2 | N110: 160+150+40+240 | O110: Dying Depart
A111: 2 | B111: 21/12/2025 | G111: Dying Depart | I111: 2 | J111: 21/12/2025 | O111: Dying Depart
A112: 3 | B112: 21/12/2025 | G112: Dying Depart | I112: 3 | J112: 21/12/2025 | O112: Dying Depart
A113: Grand Total Amount | F113: =80+100+20 -> 200 | I113: 4 | J113: 21/12/2025 | O113: Dying Depart
I114: 5 | J114: 21/12/2025 | O114: Dying Depart
A115: Preapred By | G115: Clint Signature | I115: Grand Total Amount | N115: =160+150+40+240 -> 590
I117: Preapred By | O117: Clint Signature
A119: LUNCH DYING DEPART | I119: DINNER DYING DEPART
A120: SR# | B120: Date | C120: Name | D120: Item Name | E120: QTY | F120: Price | G120: Department | I120: SR# | J120: Date | K120: Name | L120: Item Name | M120: QTY | N120: Price | O120: Department
A121: 1 | B121: 22/12/2025 | C121: Munawar | D121: Chicken Karahi 4+ Roti 12+ Salad 1 Bowl+Egg | F121: 800+180+400+100 | G121: Dying Depart | I121: 1 | J121: 22/12/2025 | K121: Munawar | L121: Chicken Karahi 1+ Roti 4+ Veg Pulao | N121: 200+60+120 | O121: Dying Depart
A122: 2 | B122: 22/12/2025 | C122: Waqas | G122: Dying Depart | I122: 2 | J122: 22/12/2025 | K122: Waqas | O122: Dying Depart
A123: 3 | B123: 22/12/2025 | C123: Jhandad | G123: Dying Depart | I123: 3 | J123: 22/12/2025 | K123: Jhandad | O123: Dying Depart
A124: 6 | B124: 22/12/2025 | C124: Aqaib | G124: Dying Depart | I124: 6 | J124: 22/12/2025 | K124: Aqaib | O124: Dying Depart
A125: Grand Total Amount | F125: =800+180+400+100 -> 1480 | I125: Grand Total Amount | N125: =200+60+120 -> 380
A127: Preapred By | G127: Clint Signature | I127: Preapred By | O127: Clint Signature
A129: LUNCH DYING DEPART | I129: DINNER DYING DEPART
A130: SR# | B130: Date | C130: Name | D130: Item Name | E130: QTY | F130: Price | G130: Department | I130: SR# | J130: Date | K130: Name | L130: Item Name | M130: QTY | N130: Price | O130: Department
A131: 1 | B131: 22/12/2025 | C131: Daniyal | D131: Karahi 2+ Anda Channa 2+ Roti 18+ Salad 2 | F131: 400+220+270+40 | G131: Dying Depart | I131: 1 | J131: 22/12/2025 | K131: Daniyal | L131: Dall 3+ Pulao 4+ Roti 9+ Chai 1 | N131: 240+480+135+35 | O131: Dying Depart
A132: 2 | B132: 22/12/2025 | G132: Dying Depart | I132: 2 | J132: 22/12/2025 | O132: Dying Depart
...

Sheet Aqib,waqas,jhandad,rqfeeq Data
A1: LUNCH DYING DEPART
A2: SR# | B2: Date | C2: Name | D2: Item Name | E2: Price | F2: Department
A3: 1 | B3: 46020 | C3: Waqas Sb | D3: Ch- Hara Masala 1+ Salad 1+ Roti 4+ Egg Ghotala 1.5 | E3: 225+20+60+75 | F3: Dying Depart
A4: 2 | B4: 46020 | F4: Dying Depart
A5: 3 | B5: 46020 | F5: Dying Depart
A6: 4 | B6: 46020 | F6: Dying Depart
A7: 5 | B7: 46020 | F7: Dying Depart
A8: Grand Total Amount | E8: =225+20+60+75 -> 380
A9: Preapred By | F9: Clint Signature
A10: LUNCH DYING DEPART
A11: SR# | B11: Date | C11: Name | D11: Item Name | E11: Price | F11: Department
A12: 1 | B12: 46020 | C12: Aqaib Sb | D12: Ch- Hara Masala 1+ Salad 1+ Roti 4+ Egg Ghotala 1.5 | E12: 225+20+60+75 | F12: Dying Depart
A13: 2 | B13: 46020 | F13: Dying Depart
A14: 3 | B14: 46020 | F14: Dying Depart
A15: 4 | B15: 46020 | F15: Dying Depart
A16: 5 | B16: 46020 | F16: Dying Depart
A17: Grand Total Amount | E17: =225+20+60+75 -> 380
A18: Preapred By | F18: Clint Signature
A19: LUNCH DYING DEPART
A20: SR# | B20: Date | C20: Name | D20: Item Name | E20: Price | F20: Department
A21: 1 | B21: 46020 | C21: Jahandad Sb | D21: Ch- Hara Masala 1+ Salad 1+ Roti 4+ Egg Ghotala 1.5 | E21: 225+20+60+75 | F21: Dying Depart
A22: 2 | B22: 46020 | F22: Dying Depart
A23: 3 | B23: 46020 | F23: Dying Depart
A24: 4 | B24: 46020 | F24: Dying Depart
A25: 5 | B25: 46020 | F25: Dying Depart
A26: Grand Total Amount | E26: =225+20+60+75 -> 380
A27: Preapred By | F27: Clint Signature
A28: LUNCH DYING DEPART
A29: SR# | B29: Date | C29: Name | D29: Item Name | E29: Price | F29: Department
A30: 1 | B30: 46020 | C30: Rafeeq Sb | D30: Ch- Hara Masala 1+ Salad 1+ Roti 3+ Egg Ghotala 1.5 | E30: 225+20+45+75 | F30: Dying Depart
A31: 2 | B31: 46020 | F31: Dying Depart
A32: 3 | B32: 46020 | F32: Dying Depart
A33: 4 | B33: 46020 | F33: Dying Depart
A34: 5 | B34: 46020 | F34: Dying Depart
A35: Grand Total Amount | E35: =225+20+45+75 -> 365
A36: Preapred By | F36: Clint Signature
A37: LUNCH DYING DEPART
A38: SR# | B38: Date | C38: Name | D38: Item Name | E38: Price | F38: Department
A39: 1 | B39: 46021 | C39: Waqas Sb | D39: Dahi+ Salad+ Ch- Pulao | E39: 100+50+250 | F39: Dying Depart
A40: 2 | B40: 46021 | F40: Dying Depart
A41: 3 | B41: 46021 | F41: Dying Depart
A42: 4 | B42: 46021 | F42: Dying Depart
A43: 5 | B43: 46021 | F43: Dying Depart
A44: Grand Total Amount | E44: =100+50+250 -> 400
A45: Preapred By | F45: Clint Signature
A46: LUNCH DYING DEPART
A47: SR# | B47: Date | C47: Name | D47: Item Name | E47: Price | F47: Department
A48: 1 | B48: 46021 | C48: Aqaib Sb | D48: Dahi+ Salad+ Ch- Pulao | E48: 100+50+250 | F48: Dying Depart
A49: 2 | B49: 46021 | F49: Dying Depart
A50: 3 | B50: 46021 | F50: Dying Depart
A51: 4 | B51: 46021 | F51: Dying Depart
A52: 5 | B52: 46021 | F52: Dying Depart
A53: Grand Total Amount | E53: =100+50+250 -> 400
A54: Preapred By | F54: Clint Signature
A55: LUNCH DYING DEPART
A56: SR# | B56: Date | C56: Name | D56: Item Name | E56: Price | F56: Department
A57: 1 | B57: 46021 | C57: Jahandad Sb | D57: Dahi+ Salad+ Ch- Pulao | E57: 100+50+250 | F57: Dying Depart
A58: 2 | B58: 46021 | F58: Dying Depart
A59: 3 | B59: 46021 | F59: Dying Depart
A60: 4 | B60: 46021 | F60: Dying Depart
A61: 5 | B61: 46021 | F61: Dying Depart
A62: Grand Total Amount | E62: =100+50+250 -> 400
A63: Preapred By | F63: Clint Signature
A64: LUNCH DYING DEPART
A65: SR# | B65: Date | C65: Name | D65: Item Name | E65: Price | F65: Department
A66: 1 | B66: 46021 | C66: Rafeeq Sb | D66: Dahi+ Salad+ Ch- Pulao | E66: 100+50+250 | F66: Dying Depart
A67: 2 | B67: 46021 | F67: Dying Depart
A68: 3 | B68: 46021 | F68: Dying Depart
A69: 4 | B69: 46021 | F69: Dying Depart
A70: 5 | B70: 46021 | F70: Dying Depart
A71: Grand Total Amount | E71: =100+50+250 -> 400
A72: Preapred By | F72: Clint Signature
A73: LUNCH DYING DEPART
A74: SR# | B74: Date | C74: Name | D74: Item Name | E74: Price | F74: Department
A75: 1 | B75: 46022 | C75: Waqas Sb | D75: Salad + Roti 4+ Egg Ghotala 1.5 | E75: 50+60+75 | F75: Dying Depart
A76: 2 | B76: 46022 | F76: Dying Depart
A77: 3 | B77: 46022 | F77: Dying Depart
A78: 4 | B78: 46022 | F78: Dying Depart
A79: 5 | B79: 46022 | F79: Dying Depart
A80: Grand Total Amount | E80: =50+60+75 -> 185
A81: Preapred By | F81: Clint Signature
A82: LUNCH DYING DEPART
A83: SR# | B83: Date | C83: Name | D83: Item Name | E83: Price | F83: Department
A84: 1 | B84: 46022 | C84: Aqaib Sb | D84: Salad + Roti 4+ Egg Ghotala 1.5 | E84: 50+60+75 | F84: Dying Depart
A85: 2 | B85: 46022 | F85: Dying Depart
A86: 3 | B86: 46022 | F86: Dying Depart
A87: 4 | B87: 46022 | F87: Dying Depart
A88: 5 | B88: 46022 | F88: Dying Depart
A89: Grand Total Amount | E89: =50+60+75 -> 185
A90: Preapred By | F90: Clint Signature
A91: LUNCH DYING DEPART
A92: SR# | B92: Date | C92: Name | D92: Item Name | E92: Price | F92: Department
A93: 1 | B93: 46022 | C93: Jahandad Sb | D93: Salad + Roti 4+ Egg Ghotala 1.5 | E93: 50+60+75 | F93: Dying Depart
A94: 2 | B94: 46022 | F94: Dying Depart
A95: 3 | B95: 46022 | F95: Dying Depart
A96: 4 | B96: 46022 | F96: Dying Depart
A97: 5 | B97: 46022 | F97: Dying Depart
A98: Grand Total Amount | E98: =50+60+75 -> 185
A99: Preapred By | F99: Clint Signature
A100: LUNCH DYING DEPART
...

Sheet Aqib,Waqas,Jhandad,Rafeeq Sumry
A1: SUMMARY
A2: SR# | B2: Date | C2: Name | D2: Amount | E2: Signature | F2: Received Amount Date
A3: 1 | B3: 17 Dec to 31 Dec 2025 | C3: Waqas Sb | D3: =3892.5+D12 -> 4857.5
A4: 2 | B4: 17 Dec to 31 Dec 2025 | C4: Jhandad Sb | D4: =3893.5+D14 -> 4858.5
A5: 3 | B5: 17 Dec to 31 Dec 2025 | C5: Rafeeq Sb | D5: =3894.5+D15 -> 4829.5
A6: 4 | B6: 17 Dec to 31 Dec 2025 | C6: Aqaib Sb | D6: =3895.5+D13 -> 4860.5
A7: Total Amount | D7: =SUM(D3:D6) -> 19406
A8: Preapred BY | F8: Clint Signature
A10: SUMMARY | H10: SUMMARY
A11: SR# | B11: Date | C11: Name | D11: Amount | E11: Signature | F11: Received Amount Date | H11: SR# | I11: Date | J11: Name | K11: Amount | L11: Signature | M11: Received Amount Date
A12: 1 | B12: 29Dec to 31 Dec 2025 | C12: Waqas Sb | D12: ='Aqib,waqas,jhandad,rqfeeq Data'!E8+'Aqib,waqas,jhandad,rqfeeq Data'!E44+'Aqib,waqas,jhandad,rqfeeq Data'!E80 -> 965 | H12: 1 | I12: 17 Dec 2025 to 15 Jan 2026 | J12: Waqas Sb | K12: =D3+D12+D20+D28+D41+D50+D59+D67+D75+D81+D89+D97+D105 -> 9588
A13: 2 | B13: 29Dec to 31 Dec 2025 | C13: Aqaib Sb | D13: ='Aqib,waqas,jhandad,rqfeeq Data'!E17+'Aqib,waqas,jhandad,rqfeeq Data'!E53+'Aqib,waqas,jhandad,rqfeeq Data'!E89 -> 965 | H13: 2 | I13: 17 Dec 2025 to 15 Jan 2026 | J13: Jhandad Sb | K13: =D4+D14+D22+D30+D44+D52+D60+D69+D76+D83+D90 -> 9861
A14: 3 | B14: 29Dec to 31 Dec 2025 | C14: Jhandad Sb | D14: ='Aqib,waqas,jhandad,rqfeeq Data'!E26+'Aqib,waqas,jhandad,rqfeeq Data'!E62+'Aqib,waqas,jhandad,rqfeeq Data'!E98 -> 965 | H14: 3 | I14: 17 Dec 2025 to 15 Jan 2026 | J14: Rafeeq Sb | K14: =D5+D15+D23+D31+D45+D51+D68+D82+D98+D106 -> 8728
A15: 4 | B15: 29Dec to 31 Dec 2025 | C15: Rafeeq Sb | D15: ='Aqib,waqas,jhandad,rqfeeq Data'!E35+'Aqib,waqas,jhandad,rqfeeq Data'!E71+'Aqib,waqas,jhandad,rqfeeq Data'!E107 -> 935 | H15: 4 | I15: 17 Dec 2025 to 15 Jan 2026 | J15: Aqaib Sb | K15: =D6+D13+D21+D29+D36+D42+D43+D53+D61+D70+D84+D91 -> 9524.5
A16: Total Amount | D16: =SUM(D12:D15) -> 3830 | H16: 5 | I16: 17 Dec 2025 to 15 Jan 2026 | J16: Shakeel Sb | K16: =D54 -> 370
H17: 6 | I17: 46036 | J17: Munawar Sb | K17: 100
A18: SUMMARY | H18: Total Amount | K18: =SUM(K12:K17) -> 38171.5
A19: SR# | B19: Date | C19: Name | D19: Amount | E19: Signature | F19: Received Amount Date | H19: Preapred BY | M19: Clint Signature
A20: 1 | B20: 46024 | C20: Waqas Sb | D20: 470
A21: 2 | B21: 46024 | C21: Aqaib Sb | D21: =470+120 -> 590
A22: 3 | B22: 46024 | C22: Jhandad Sb | D22: 470
A23: 4 | B23: 46024 | C23: Rafeeq Sb | D23: 470
A24: Total Amount | D24: =SUM(D20:D23) -> 2000
A26: SUMMARY
A27: SR# | B27: Date | C27: Name | D27: Amount | E27: Signature | F27: Received Amount Date
A28: 1 | B28: 46025 | C28: Waqas Sb | D28: 428
A29: 2 | B29: 46025 | C29: Aqaib Sb | D29: 428
A30: 3 | B30: 46025 | C30: Jhandad Sb | D30: 428
A31: 4 | B31: 46025 | C31: Rafeeq Sb | D31: 428
A32: Total Amount | D32: =SUM(D28:D31) -> 1712
A34: SUMMARY
A35: SR# | B35: Date | C35: Name | D35: Amount | E35: Signature | F35: Received Amount Date
A36: 1 | B36: 46026 | C36: Aqaib Sb | D36: =260+195 -> 455
A37: Total Amount | D37: =SUM(D36:D36) -> 455
A39: SUMMARY
A40: SR# | B40: Date | C40: Name | D40: Amount | E40: Signature | F40: Received Amount Date
A41: 1 | B41: 46027 | C41: Waqas Sb | D41: 310
A42: 2 | B42: 46027 | C42: Aqaib Sb | D42: 311
B43: 46027 | C43: Aqaib Sb | D43: 225
A44: 3 | B44: 46027 | C44: Jhandad Sb | D44: 312
A45: 4 | B45: 46027 | C45: Rafeeq Sb | D45: 313
A46: Total Amount | D46: =SUM(D41:D45) -> 1471
A48: SUMMARY
A49: SR# | B49: Date | C49: Name | D49: Amount | E49: Signature | F49: Received Amount Date
A50: 1 | B50: 46028 | C50: Waqas Sb | D50: 320
A51: 2 | B51: 46028 | C51: Rafeeq Sb | D51: 320
A52: 3 | B52: 46028 | C52: Jhandad Sb | D52: 320
A53: 4 | B53: 46028 | C53: Aqaib Sb | D53: 320
A54: 5 | B54: 46028 | C54: Shakeel Sb | D54: 370
A55: Total Amount | D55: =SUM(D50:D54) -> 1650
A57: SUMMARY
A58: SR# | B58: Date | C58: Name | D58: Amount | E58: Signature | F58: Received Amount Date
A59: 1 | B59: 46030 | C59: Waqas Sb | D59: 280
A60: 3 | B60: 46030 | C60: Jhandad Sb | D60: 280
A61: 4 | B61: 46030 | C61: Aqaib Sb | D61: 280
A62: Total Amount | D62: =SUM(D59:D61) -> 840
A63: Preapred BY | F63: Clint Signature
A65: SUMMARY
A66: SR# | B66: Date | C66: Name | D66: Amount | E66: Signature | F66: Received Amount Date
A67: 1 | B67: 46031 | C67: Waqas Sb | D67: 370
A68: 2 | B68: 46031 | C68: Rafeeq Sb | D68: 370
A69: 3 | B69: 46031 | C69: Jhandad Sb | D69: 1330
A70: 4 | B70: 46031 | C70: Aqaib Sb | D70: 370
A71: Total Amount | D71: =SUM(D67:D70) -> 2440
A73: SUMMARY
A74: SR# | B74: Date | C74: Name | D74: Amount | E74: Signature | F74: Received Amount Date
A75: 1 | B75: 46032 | C75: Waqas Sb | D75: 265
A76: 3 | B76: 46032 | C76: Jhandad Sb | D76: 265
A77: Total Amount | D77: =SUM(D75:D76) -> 530
A79: SUMMARY
A80: SR# | B80: Date | C80: Name | D80: Amount | E80: Signature | F80: Received Amount Date
A81: 1 | B81: 46034 | C81: Waqas Sb | D81: ='Aqib,waqas,jhandad,rqfeeq Data'!E439 -> 272.5
A82: 2 | B82: 46034 | C82: Rafeeq Sb | D82: ='Aqib,waqas,jhandad,rqfeeq Data'!E448 -> 272.5
A83: 3 | B83: 46034 | C83: Jhandad Sb | D83: ='Aqib,waqas,jhandad,rqfeeq Data'!E457 -> 272.5
A84: 4 | B84: 46034 | C84: Aqaib Sb | D84: ='Aqib,waqas,jhandad,rqfeeq Data'!E475 -> 360
A85: Total Amount | D85: =SUM(D81:D84) -> 1177.5
A87: SUMMARY
A88: SR# | B88: Date | C88: Name | D88: Amount | E88: Signature | F88: Received Amount Date
A89: 1 | B89: 46035 | C89: Waqas Sb | D89: 360
A90: 2 | B90: 46035 | C90: Jhandad Sb | D90: 360
A91: 3 | B91: 46035 | C91: Aqaib Sb | D91: 360
A92: Total Amount | D92: =SUM(D89:D91) -> 1080
A93: Preapred BY | F93: Clint Signature
A95: SUMMARY
A96: SR# | B96: Date | C96: Name | D96: Amount | E96: Signature | F96: Received Amount Date
A97: 1 | B97: 46036 | C97: Waqas Sb | D97: 450
A98: 2 | B98: 46036 | C98: Rafeeq Sb | D98: 550
A99: 3 | B99: 46036 | C99: Munawar Sb | D99: 100
A100: Total Amount | D100: =SUM(D97:D99) -> 1100
A101: Preapred BY | F101: Clint Signature
A103: SUMMARY
A104: SR# | B104: Date | C104: Name | D104: Amount | E104: Signature | F104: Received Amount Date
A105: 1 | B105: 46037 | C105: Waqas Sb | D105: 240
A106: 2 | B106: 46037 | C106: Rafeeq Sb | D106: 240
A107: Total Amount | D107: =SUM(D105:D106) -> 480
A108: Preapred BY | F108: Clint Signature
A110: SUMMARY
A111: SR# | B111: Date | C111: Name | D111: Amount | E111: Signature | F111: Received Amount Date
A112: 1 | B112: 46038 | C112: Waqas Sb | D112: 610
A113: 2 | B113: 46038 | C113: Rafeeq Sb | D113: 610
...

Sheet Daniyal Meal Data 
A1: LUNCH DYING DEPART
A2: SR# | B2: Date | C2: Name | D2: Item Name | E2: QTY | F2: Price | G2: Department
A3: 1 | B3: 16/12/2025 | C3: Daniyal | D3: 4 Karahi, 4 Chawal, 4 Dall,15 Roti | F3: 800+400+320+180 | G3: Dying Depart
A4: 2 | B4: 16/12/2025 | C4: Azeem | G4: Dying Depart
A5: 3 | B5: 16/12/2025 | C5: Uaman | G5: Dying Depart
A6: 4 | B6: 16/12/2025 | C6: Maroof | G6: Dying Depart
A7: 5 | B7: 16/12/2025 | C7: Nasir | G7: Dying Depart
A8: 6 | B8: 16/12/2025 | C8: Mueez | G8: Dying Depart
A9: Grand Total Amount | F9: 1700
A11: Preapred By | G11: Clint Signature
A13: LUNCH DYING DEPART
A14: SR# | B14: Date | C14: Name | D14: Item Name | E14: QTY | F14: Price | G14: Department
A15: 1 | B15: 17/12/2025 | C15: Daniyal | D15: 6 Chicken Qorma+ 18 Roti+ 2 Dahi + Salad | F15: 1200+270+100+40 | G15: Dying Depart
A16: 2 | B16: 17/12/2025 | C16: Azeem | G16: Dying Depart
A17: 3 | B17: 17/12/2025 | C17: Uaman | G17: Dying Depart
A18: 4 | B18: 17/12/2025 | C18: Maroof | G18: Dying Depart
A19: 5 | B19: 17/12/2025 | C19: Nasir | G19: Dying Depart
A20: 6 | B20: 17/12/2025 | C20: Mueez | G20: Dying Depart
A21: Grand Total Amount | F21: 1610
A23: Preapred By | G23: Clint Signature
A25: DINNER DYING DEPART
A26: SR# | B26: Date | C26: Name | D26: Item Name | E26: QTY | F26: Price | G26: Department
A27: 1 | B27: 17/12/2025 | C27: Daniyal | D27: 1 Sabzi+13 Roti+ 1 Salad | F27: 80+195+20 | G27: Dying Depart
A28: 2 | B28: 17/12/2025 | C28: Maroof | G28: Dying Depart
A29: 3 | B29: 17/12/2025 | C29: Yaseen | G29: Dying Depart
A30: 4 | B30: 17/12/2025 | C30: Ali Raza | G30: Dying Depart
A31: 5 | B31: 17/12/2025 | C31: Azeem | G31: Dying Depart
G32: Dying Depart
A33: Grand Total Amount | F33: 295
A35: Preapred By | G35: Clint Signature
A37: LUNCH DYING DEPART
A38: SR# | B38: Date | C38: Name | D38: Item Name | E38: QTY | F38: Price | G38: Department
A39: 1 | B39: 18/12/2025 | C39: Daniyal | D39: Roti 15+ Chicken Stew 3+ Pulao 2+ Biryani 1+ Salad | F39: 225+600+240+180+20 | G39: Dying Depart
A40: 2 | B40: 18/12/2025 | G40: Dying Depart
A41: 3 | B41: 18/12/2025 | G41: Dying Depart
A42: 4 | B42: 18/12/2025 | G42: Dying Depart
A43: 5 | B43: 18/12/2025 | G43: Dying Depart
A44: 6 | B44: 18/12/2025 | G44: Dying Depart
A45: Grand Total Amount | F45: =225+600+240+180+20 -> 1265
A47: Preapred By | G47: Clint Signature
A49: DINNER DYING DEPART
A50: SR# | B50: Date | C50: Name | D50: Item Name | E50: QTY | F50: Price | G50: Department
A51: 1 | B51: 18/12/2025 | C51: Daniyal | D51: Chicken Karahi 3+ Dall 1+ Roti 18 | F51: 600+80+270 | G51: Dying Depart
A52: 2 | B52: 18/12/2025 | G52: Dying Depart
A53: 3 | B53: 18/12/2025 | G53: Dying Depart
A54: 4 | B54: 18/12/2025 | G54: Dying Depart
A55: 5 | B55: 18/12/2025 | G55: Dying Depart
A56: 6 | B56: 18/12/2025 | G56: Dying Depart
A57: Grand Total Amount | F57: =600+80+270 -> 950
A59: Preapred By | G59: Clint Signature
A61: LUNCH DYING DEPART
A62: SR# | B62: Date | C62: Name | D62: Item Name | E62: QTY | F62: Price | G62: Department
A63: 1 | B63: 19/12/2025 | C63: Daniyal | D63: Raita 1 bowl + Salad 1+Biryani 6 | F63: 500+20+1080 | G63: Dying Depart
A64: 2 | B64: 19/12/2025 | G64: Dying Depart
A65: 3 | B65: 19/12/2025 | G65: Dying Depart
A66: 4 | B66: 19/12/2025 | G66: Dying Depart
A67: 5 | B67: 19/12/2025 | G67: Dying Depart
A68: 6 | B68: 19/12/2025 | G68: Dying Depart
A69: Grand Total Amount | F69: =500+20+1080 -> 1600
A71: Preapred By | G71: Clint Signature
A73: DINNER DYING DEPART
A74: SR# | B74: Date | C74: Name | D74: Item Name | E74: QTY | F74: Price | G74: Department
A75: 1 | B75: 19/12/2025 | C75: Daniyal | D75: Dall Fry 2+ karahi 3+ roti 21+ Dahi | F75: 100+200+540+315 | G75: Dying Depart
A76: 2 | B76: 19/12/2025 | G76: Dying Depart
A77: 3 | B77: 19/12/2025 | G77: Dying Depart
A78: 4 | B78: 19/12/2025 | G78: Dying Depart
A79: 5 | B79: 19/12/2025 | G79: Dying Depart
A80: 6 | B80: 19/12/2025 | G80: Dying Depart
A81: Grand Total Amount | F81: =100+200+540+315 -> 1155
A83: Preapred By | G83: Clint Signature
A85: LUNCH DYING DEPART
A86: SR# | B86: Date | C86: Name | D86: Item Name | E86: QTY | F86: Price | G86: Department
A87: 1 | B87: 20/12/2025 | C87: Daniyal | D87: Karahi 3+ Roti 12+ Salad 2 | F87: 600+180+40 | G87: Dying Depart
A88: 2 | B88: 20/12/2025 | G88: Dying Depart
A89: 3 | B89: 20/12/2025 | G89: Dying Depart
A90: 4 | B90: 20/12/2025 | G90: Dying Depart
A91: 5 | B91: 20/12/2025 | G91: Dying Depart
A92: Grand Total Amount | F92: =600+180+40 -> 820
A94: Preapred By | G94: Clint Signature
A98: DINNER DYING DEPART
A99: SR# | B99: Date | C99: Name | D99: Item Name | E99: QTY | F99: Price | G99: Department
A100: 1 | B100: 20/12/2025 | C100: Daniyal | D100: Dall 3+ Karahi 1+ Roti 16 | F100: 240+200+240 | G100: Dying Depart
A101: 2 | B101: 20/12/2025 | G101: Dying Depart
A102: 3 | B102: 20/12/2025 | G102: Dying Depart
A103: 4 | B103: 20/12/2025 | G103: Dying Depart
A104: 5 | B104: 20/12/2025 | G104: Dying Depart
A105: Grand Total Amount | F105: =240+200+240 -> 680
A107: Preapred By | G107: Clint Signature
A110: LUNCH DYING DEPART
A111: SR# | B111: Date | C111: Name | D111: Item Name | E111: QTY | F111: Price | G111: Department
A112: 1 | B112: 21/12/2025 | C112: Daniyal | D112: Dall 2+ Roti 10+ Salad 2+ Channa chat 2 | F112: 160+150+40+240 | G112: Dying Depart
A113: 2 | B113: 21/12/2025 | G113: Dying Depart
A114: 3 | B114: 21/12/2025 | G114: Dying Depart
A115: 4 | B115: 21/12/2025 | G115: Dying Depart
A116: 5 | B116: 21/12/2025 | G116: Dying Depart
A117: Grand Total Amount | F117: =160+150+40+240 -> 590
A119: Preapred By | G119: Clint Signature
A121: LUNCH DYING DEPART
A122: SR# | B122: Date | C122: Name | D122: Item Name | E122: QTY | F122: Price | G122: Department
A123: 1 | B123: 22/12/2025 | C123: Daniyal | D123: Karahi 2+ Anda Channa 2+ Roti 18+ Salad 2 | F123: 400+220+270+40 | G123: Dying Depart
...

Sheet Daniyal Summary Daying Dept
A1: Mujtaba And Brothers (Canteen Bill)
A2: SR# | B2: Date | C2: Name | D2: Amount | E2: Signature | F2: Received Amount Date | G2: Received Amount | H2: Balance Amount
A3: 1 | B3: 17 Dec to 31 Dec 2025 | C3: Daniyal Sb | D3: ='Daniyal Meal Data '!F9+'Daniyal Meal Data '!F21+'Daniyal Meal Data '!F33+'Daniyal Meal Data '!F45+'Daniyal Meal Data '!F57+'Daniyal Meal Data '!F69+'Daniyal Meal Data '!F81+'Daniyal Meal Data '!F92+'Daniyal Meal Data '!F105+'Daniyal Meal Data '!F117+'Daniyal Meal Data '!F128+'Daniyal Meal Data '!F139+'Daniyal Meal Data '!F150+'Daniyal Meal Data '!F161+'Daniyal Meal Data '!F172+'Daniyal Meal Data '!F183+'Daniyal Meal Data '!F194+'Daniyal Meal Data '!F205+'Daniyal Meal Data '!F216+'Daniyal Meal Data '!F227+'Daniyal Meal Data '!F238+'Daniyal Meal Data '!F249 -> 28659 | G3: 30000 | H3: =G3-D7 -> 1341
A4: 2 | B4: 17 Dec to 31 Dec 2025
A5: 3 | B5: 17 Dec to 31 Dec 2025
A6: 4 | B6: 17 Dec to 31 Dec 2025
A7: Total Amount | D7: =SUM(D3:D6) -> 28659
A9: SUMMARY
A10: SR# | B10: Date | C10: Name | D10: Amount | E10: Signature | F10: Received Amount Date
A11: 1 | B11: 01/02/2026 And 2-Jan-2026 | C11: Daniyal Sb | D11: =2340+3170 -> 5510
A12: 2 | B12: 01/02/2026 And 2-Jan-2026
A13: 3 | B13: 01/02/2026 And 2-Jan-2026
A14: 4 | B14: 01/02/2026 And 2-Jan-2026
A15: Total Amount | D15: =SUM(D11:D14) -> 5510
A17: SUMMARY
A18: SR# | B18: Date | C18: Name | D18: Amount | E18: Signature | F18: Received Amount Date
A19: 1 | B19: 03-Jan-2026 And 4-Jan-2026 | C19: Daniyal Sb | D19: 1230+570+495
A20: 2 | B20: 03-Jan-2026 And 4-Jan-2026
A21: 3 | B21: 03-Jan-2026 And 4-Jan-2026
A22: 4 | B22: 03-Jan-2026 And 4-Jan-2026
A23: Total Amount | D23: =1230+570+495 -> 2295
A25: SUMMARY
A26: SR# | B26: Date | C26: Name | D26: Amount | E26: Signature | F26: Received Amount Date
A27: 1 | B27: 46027 | C27: Daniyal Sb | D27: 880+540+525+60
A28: 2 | B28: 46027
A29: 3 | B29: 46027
A30: 4 | B30: 46027
A31: Total Amount | D31: =880+540+525+60 -> 2005
A33: SUMMARY
A34: SR# | B34: Date | C34: Name | D34: Amount | E34: Signature | F34: Received Amount Date
A35: 1 | B35: 46027 | C35: Daniyal | D35: 360+200+90+30+165+810
A36: 2 | B36: 46027
A37: 3 | B37: 46027
A38: 4 | B38: 46027
A39: Total Amount | D39: =360+200+90+30+165+810 -> 1655
A41: SUMMARY
A42: SR# | B42: Date | C42: Name | D42: Amount | E42: Signature | F42: Received Amount Date
A43: 1 | B43: 46028 | C43: Daniyal | D43: 360+200+90+30+165+810
A44: 2 | B44: 46028
A45: 3 | B45: 46028
A46: 4 | B46: 46028
A47: Total Amount | D47: =360+200+90+30+165+810 -> 1655
A49: SUMMARY
A50: SR# | B50: Date | C50: Name | D50: Amount | E50: Signature | F50: Received Amount Date
A51: 1 | B51: 46029 | C51: Daniyal | D51: 640+225+90+440+150+320
A52: 2 | B52: 46029
A53: 3 | B53: 46029
A54: 4 | B54: 46029
A55: Total Amount | D55: =640+225+90+440+150+320 -> 1865
A57: SUMMARY
A58: SR# | B58: Date | C58: Name | D58: Amount | E58: Signature | F58: Received Amount Date
A59: 1 | B59: 46030 | C59: Daniyal | D59: 360+440+270+60+660+240+180
A60: 2 | B60: 46030
A61: 3 | B61: 46030
A62: 4 | B62: 46030
A63: Total Amount | D63: =360+440+270+60+660+240+180 -> 2210
A64: Preapred BY | F64: Clint Signature
A66: SUMMARY
A67: SR# | B67: Date | C67: Name | D67: Amount | E67: Signature | F67: Received Amount Date
A68: 1 | B68: 46031 | C68: Daniyal | D68: 960+60+100+240+1100+440+80
A69: 2 | B69: 46031
A70: 3 | B70: 46031
A71: 4 | B71: 46031
A72: Total Amount | D72: =960+60+100+240+1100+440+80 -> 2980
A73: Preapred BY | F73: Clint Signature
A75: SUMMARY
A76: SR# | B76: Date | C76: Name | D76: Amount | E76: Signature | F76: Received Amount Date
A77: 1 | B77: 46032 | C77: Daniyal | D77: 90+660+180+100+850+900+90+80
A78: 2 | B78: 46032
A79: 3 | B79: 46032
A80: 4 | B80: 46032
A81: Total Amount | D81: =90+660+180+100+850+900+90+80 -> 2950
A82: Preapred BY | F82: Clint Signature
A84: SUMMARY
A85: SR# | B85: Date | C85: Name | D85: Amount | E85: Signature | F85: Received Amount Date
A86: 1 | B86: 46033 | C86: Daniyal | D86: 195
A87: 2 | B87: 46033
A88: 3 | B88: 46033
A89: 4 | B89: 46033
A90: Total Amount | D90: 195
A91: Preapred BY | F91: Clint Signature
A93: SUMMARY
A94: SR# | B94: Date | C94: Name | D94: Amount | E94: Signature | F94: Received Amount Date
A95: 1 | B95: 46034 | C95: Daniyal | D95: 660+165+90+680+200+75
A96: 2 | B96: 46034
A97: 3 | B97: 46034
A98: 4 | B98: 46034
A99: Total Amount | D99: =660+165+90+680+200+75 -> 1870
A100: Preapred BY | F100: Clint Signature
A102: SUMMARY
A103: SR# | B103: Date | C103: Name | D103: Amount | E103: Signature | F103: Received Amount Date
A104: 1 | B104: 46035 | C104: Daniyal | D104: 900+90+1080+240
A105: 2 | B105: 46035
A106: 3 | B106: 46035
A107: 4 | B107: 46035
A108: Total Amount | D108: =900+90+1080+240 -> 2310
A109: Preapred BY | F109: Clint Signature
A111: SUMMARY
A112: SR# | B112: Date | C112: Name | D112: Amount | E112: Signature | F112: Received Amount Date
A113: 1 | B113: 46036 | C113: Daniyal | D113: 90+230+1600+320+225
...

Sheet Mueez, Nasir Dying Dept
A1: LUNCH DYING DEPART | H1: LUNCH DYING DEPART
A2: SR# | B2: Date | C2: Name | D2: Item Name | E2: Price | F2: Department | H2: SR# | I2: Date | J2: Name | K2: Item Name | L2: Price | M2: Department
A3: 1 | B3: 46034 | C3: Mueez Sb | D3: Sp-Ch- Qorma 1+ Roti 3 | E3: 220+45 | F3: Dying Depart | H3: 1 | I3: 46034 | J3: Nasir Sb | K3: Sp-Ch- Qorma 1+ Roti 2 | L3: 220+30 | M3: Dying Depart
A4: 2 | B4: 46034 | F4: Dying Depart | H4: 2 | I4: 46034 | M4: Dying Depart
A5: 3 | B5: 46034 | F5: Dying Depart | H5: 3 | I5: 46034 | M5: Dying Depart
A6: 4 | B6: 46034 | F6: Dying Depart | H6: 4 | I6: 46034 | M6: Dying Depart
A7: 5 | B7: 46034 | F7: Dying Depart | H7: 5 | I7: 46034 | M7: Dying Depart
A8: Grand Total Amount | E8: =220+45 -> 265 | H8: Grand Total Amount | L8: =220+30 -> 250
A10: Preapred By | F10: Clint Signature | H10: Preapred By | M10: Clint Signature

Sheet Mueez, Nasir Summry 
A1: SUMMARY | H1: SUMMARY
A2: SR# | B2: Date | C2: Name | D2: Amount | E2: Signature | F2: Received Amount Date | H2: SR# | I2: Date | J2: Name | K2: Amount | L2: Signature | M2: Received Amount Date
A3: 1 | B3: 46034 | C3: Mueez Sb | D3: 220+45 | H3: 1 | I3: 46034 | J3: Nasir Sb | K3: 220+30
A4: 2 | B4: 46034 | H4: 2 | I4: 46034
A5: 3 | B5: 46034 | H5: 3 | I5: 46034
A6: 4 | B6: 46034 | H6: 4 | I6: 46034
A7: Total Amount | D7: =220+45 -> 265 | H7: Total Amount | K7: =220+30 -> 250
A8: Preapred BY | F8: Clint Signature | H8: Preapred BY | M8: Clint Signature

Sheet HR
A1: SR# | B1: Date | C1: Item Name | D1: QTY | E1: Price | F1: Department | H1: SR# | I1: Date | J1: Item Name | K1: QTY | L1: Price | M1: Department
A2: 1 | B2: 17/12/2025 | C2: Roti | D2: 14 | E2: 210 | F2: HR | H2: 1 | I2: 16/12/2025 | J2: Dall | K2: 1 | L2: 80 | M2: Flow HCM
A3: 2 | B3: 17/12/2025 | C3: Chicken Qorma | D3: 4 | E3: 800 | F3: HR | H3: 2 | I3: 16/12/2025 | J3: Karahi | K3: 1 | L3: 200 | M3: Flow HCM
A4: 4 | B4: 17/12/2025 | C4: Cold Drink | D4: 1 | E4: 180 | F4: HR | H4: 4 | I4: 16/12/2025 | J4: Roti | K4: 7 | L4: 105 | M4: Flow HCM
A5: Grand Total Amount | E5: =SUM(E2:E4) -> 1190 | H5: 5 | I5: 16/12/2025 | J5: Salad | K5: 1 | L5: 20 | M5: Flow HCM
H6: Grand Total Amount | L6: =SUM(L2:L5) -> 405
A7: Preapred By | F7: Clint Signature
H8: Preapred By | M8: Clint Signature
A9: SR# | B9: Date | C9: Item Name | D9: QTY | E9: Price | F9: Department
A10: 1 | B10: 19/12/2025 | C10: Biryani | D10: 8 | E10: 1440 | F10: HR
A11: 2 | B11: 19/12/2025 | C11: Salad | D11: 2 | E11: 40 | F11: HR
F12: HR
A13: Grand Total Amount | E13: =SUM(E10:E12) -> 1480
A15: Preapred By | F15: Clint Signature
A18: SR# | B18: Date | C18: Item Name | D18: QTY | E18: Price | F18: Department
A19: 1 | B19: 22/12/2025 | C19: Ch- Karahi | D19: 4 | E19: 800 | F19: HR
A20: 2 | B20: 22/12/2025 | C20: Roti | D20: 15 | E20: 225 | F20: HR
A21: 3 | B21: 22/12/2025 | C21: Salad | D21: 1 | E21: 20 | F21: HR
A22: Grand Total Amount | E22: =SUM(E19:E21) -> 1045
A24: Preapred By | F24: Clint Signature
A26: SR# | B26: Date | C26: Item Name | D26: QTY | E26: Price | F26: Department
A27: 1 | B27: 45658 | C27: Roti | D27: 14 | E27: =D27*15 -> 210 | F27: HR
A28: Grand Total Amount | E28: =SUM(E27:E27) -> 210
A30: Preapred By | F30: Clint Signature
A32: SR# | B32: Date | C32: Item Name | D32: QTY | E32: Price | F32: Department
A33: 1 | B33: 46028 | C33: Veg Pulao | D33: 2 | E33: =D33*180 -> 360 | F33: HR
A34: 2 | B34: 46028 | C34: Roti | D34: 7 | E34: =D34*15 -> 105 | F34: HR
A35: 3 | B35: 46028 | C35: Dall | D35: 3 | E35: =D35*80 -> 240 | F35: HR
A36: 4 | B36: 46028 | C36: Salad | D36: 2 | E36: =D36*30 -> 60 | F36: HR
A37: Grand Total Amount | E37: =SUM(E33:E36) -> 765
A39: Preapred By | F39: Clint Signature
A41: SR# | B41: Date | C41: Item Name | D41: QTY | E41: Price | F41: Department
A42: 1 | B42: 46035 | C42: Sp- Dall Fry | D42: 1 | E42: =D42*180 -> 180 | F42: HR
A43: 2 | B43: 46035 | C43: Roti | D43: 4 | E43: =D43*15 -> 60 | F43: HR
A44: 3 | B44: 46035 | C44: Sp- Veg Pulao | D44: 1 | E44: =D44*250 -> 250 | F44: HR
A45: 4 | B45: 46035 | C45: Salad | D45: 1 | E45: =D45*30 -> 30 | F45: HR
A46: Grand Total Amount | E46: =SUM(E42:E45) -> 520
A48: Preapred By | F48: Clint Signature
A50: SR# | B50: Date | C50: Item Name | D50: QTY | E50: Price | F50: Department
A51: 1 | B51: 46035 | C51: Sp- Veg Pulao | D51: 5 | E51: =D51*250 -> 1250 | F51: HR
A52: 2 | B52: 46035 | C52: Salad | D52: 1 | E52: =D52*30 -> 30 | F52: HR
A53: Grand Total Amount | E53: =SUM(E51:E52) -> 1280
A55: Preapred By | F55: Clint Signature
A57: SR# | B57: Date | C57: Item Name | D57: QTY | E57: Price | F57: Department
A58: 1 | B58: 46036 | C58: Sp- Ch- Pulao | D58: 1 | E58: =D58*320 -> 320 | F58: HR
A59: 2 | B59: 46036 | C59: Dahi | D59: 1 | E59: 50 | F59: HR
A60: 3 | B60: 46036 | C60: Salad | D60: 1 | E60: 30 | F60: HR
A61: Grand Total Amount | E61: =SUM(E58:E60) -> 400
A63: Preapred By | F63: Clint Signature
A65: SR# | B65: Date | C65: Item Name | D65: QTY | E65: Price | F65: Department
A66: 1 | B66: 46036 | C66: Dall Fry | D66: 2 | E66: =D66*180 -> 360 | F66: HR
A67: 2 | B67: 46036 | C67: Roti | D67: 9 | E67: =D67*15 -> 135 | F67: HR
A68: Grand Total Amount | E68: =SUM(E66:E67) -> 495
A70: Preapred By | F70: Clint Signature
A72: SR# | B72: Date | C72: Item Name | D72: QTY | E72: Price | F72: Department
A73: 1 | B73: 46037 | C73: Sp- sabzi | D73: 1 | E73: =D73*180 -> 180 | F73: HR
A74: 2 | B74: 46037 | C74: Roti | D74: 3 | E74: =D74*15 -> 45 | F74: HR
A75: 3 | B75: 46037 | C75: Salad | D75: 1 | E75: 30 | F75: HR
A76: Grand Total Amount | E76: =SUM(E73:E75) -> 255
A78: Preapred By | F78: Clint Signature

Sheet Summary of HR Depart 
A1: SUMMARY OF HR DEPART
A2: SR# | B2: Date | C2: Name | D2: Amount | E2: Depart
A3: 1 | B3: 46023 | C3: Basim Sb | D3: 210 | E3: HR
A4: 2 | B4: 46028 | C4: Basim Sb | D4: 765 | E4: HR
A5: 3 | B5: 46035 | C5: Basim Sb | D5: 1280 | E5: HR
A6: 4 | B6: 46035 | C6: Basim Sb | D6: 520 | E6: HR
A7: 5 | B7: 46036 | C7: Basim Sb | D7: 495 | E7: HR
A8: 6 | B8: 46036 | C8: Basim Sb | D8: 400 | E8: HR
A9: 7 | B9: 46037 | C9: Basim Sb | D9: 255 | E9: HR
A10: Grand Total Amount | D10: =SUM(D3:D9) -> 3925
A11: Preapred By | E11: Clint Signature
A15: Admin sig

Sheet Guest House
A1: SR# | B1: Date | C1: Item Name | D1: QTY | E1: Price | F1: Department
A2: 1 | B2: 16/12/2025 | C2: Egg | D2: 1 | E2: 50 | F2: Guest House (5)
A3: 2 | B3: 16/12/2025 | C3: Cake Rus | D3: 1 | E3: 120 | F3: Guest House (5)
A4: 4 | B4: 16/12/2025 | C4: Cake | D4: 1 | E4: 30 | F4: Guest House (5)
A5: Grand Total Amount | E5: =SUM(E2:E4) -> 200
A7: Preapred By | F7: Clint Signature
A10: SR# | B10: Date | C10: Item Name | D10: QTY | E10: Price | F10: Department
A11: 1 | B11: 18/12/2025 | C11: Cake Rus | E11: 120 | F11: Guest House (5)
A12: 2 | B12: 18/12/2025 | C12: Fruit Cake | D12: 1 | E12: 80 | F12: Guest House (5)
A13: 4 | B13: 18/12/2025 | C13: Egg | D13: 1 | E13: 50 | F13: Guest House (5)
A14: Grand Total Amount | E14: =SUM(E11:E13) -> 250
A16: Preapred By | F16: Clint Signature
A19: SR# | B19: Date | C19: Item Name | D19: QTY | E19: Price | F19: Department
A20: 1 | B20: 24/12/2025 | C20: Egg Fry | D20: 1 | E20: 50 | F20: Guest House (5)
A21: 2 | B21: 24/12/2025 | C21: Cake Rus | D21: 1 | E21: 120 | F21: Guest House (5)
A22: 3 | B22: 24/12/2025 | C22: Cake | D22: 1 | E22: 80 | F22: Guest House (5)
A23: Grand Total Amount | E23: =SUM(E20:E22) -> 250
A25: Preapred By | F25: Clint Signature
A27: SR# | B27: Date | C27: Item Name | D27: QTY | E27: Price | F27: Department
A28: 1 | B28: 25/12/2025 | C28: Egg Boil | D28: 1 | E28: 50 | F28: Guest House (5)
A29: 2 | B29: 25/12/2025 | C29: Cake Rus | D29: 1 | E29: 120 | F29: Guest House (5)
A30: 3 | B30: 25/12/2025 | C30: Cake Fruit | D30: 1 | E30: 80 | F30: Guest House (5)
A31: 4 | B31: 25/12/2025 | C31: Fruit Chat | D31: 1 | E31: 120 | F31: Guest House (5)
A32: 5 | B32: 25/12/2025 | C32: Channa Chat | D32: 1 | E32: 120 | F32: Guest House (5)
A33: Grand Total Amount | E33: =SUM(E28:E32) -> 490
A35: Preapred By | F35: Clint Signature
A37: SR# | B37: Date | C37: Item Name | D37: QTY | E37: Price | F37: Department
A38: 1 | B38: 26/12/2025 | C38: Egg Boil | D38: 1 | E38: 50 | F38: Guest House (5)
A39: 2 | B39: 26/12/2025 | C39: Biscut | D39: 1 | E39: 220 | F39: Guest House (5)
A40: 3 | B40: 26/12/2025 | C40: Cake Rus | D40: 1 | E40: 120 | F40: Guest House (5)
A41: 4 | B41: 26/12/2025 | C41: Channa Chat | D41: 1 | E41: 120 | F41: Guest House (5)
A42: Grand Total Amount | E42: =SUM(E38:E41) -> 510
A44: Preapred By | F44: Clint Signature
A46: SR# | B46: Date | C46: Item Name | D46: QTY | E46: Price | F46: Department
A47: 1 | B47: 27/12/2025 | C47: Egg Boil | D47: 1 | E47: 50 | F47: Guest House (5)
A48: 2 | B48: 27/12/2025 | C48: Fruit Cake | D48: 1 | E48: =D48*80 -> 80 | F48: Guest House (5)
A49: 3 | B49: 27/12/2025 | C49: Cake Rus | D49: 1 | E49: 120 | F49: Guest House (5)
A50: Grand Total Amount | E50: =SUM(E47:E49) -> 250
A52: Preapred By | F52: Clint Signature
A54: SR# | B54: Date | C54: Item Name | D54: QTY | E54: Price | F54: Department
A55: 1 | B55: 28/12/2025 | C55: Mix Biscut | D55: 1 | E55: 220 | F55: Guest House (5)
A56: 2 | B56: 28/12/2025 | C56: Egg Boil | D56: 1 | E56: 50 | F56: Guest House (5)
A57: 3 | B57: 28/12/2025 | C57: Cake Rus | D57: 1 | E57: 120 | F57: Guest House (5)
A58: Grand Total Amount | E58: =SUM(E55:E57) -> 390
A60: Preapred By | F60: Clint Signature
A62: SR# | B62: Date | C62: Item Name | D62: QTY | E62: Price | F62: Department
A63: 1 | B63: 29/12/2025 | C63: Fruit Cake | D63: 1 | E63: 80 | F63: Guest House (5)
A64: 2 | B64: 29/12/2025 | C64: Egg Boil | D64: 1 | E64: 50 | F64: Guest House (5)
A65: 3 | B65: 29/12/2025 | C65: Cake Rus | D65: 1 | E65: 120 | F65: Guest House (5)
A66: Grand Total Amount | E66: =SUM(E63:E65) -> 250
A68: Preapred By | F68: Clint Signature
A70: SR# | B70: Date | C70: Item Name | D70: QTY | E70: Price | F70: Department
A71: 1 | B71: 30/12/2025 | C71: Fruit Cake | D71: 1 | E71: 80 | F71: Guest House (5)
A72: 2 | B72: 30/12/2025 | C72: Egg Boil | D72: 1 | E72: 50 | F72: Guest House (5)
A73: 3 | B73: 30/12/2025 | C73: Cake Rus | D73: 1 | E73: 120 | F73: Guest House (5)
A74: Grand Total Amount | E74: =SUM(E71:E73) -> 250
A76: Preapred By | F76: Clint Signature
A78: SR# | B78: Date | C78: Item Name | D78: QTY | E78: Price | F78: Department
A79: 1 | B79: 31/12/2025 | C79: Egg Boil | D79: 1 | E79: =D79*50 -> 50 | F79: Guest House (5)
A80: 2 | B80: 31/12/2025 | C80: Cake Rus | D80: 1 | E80: =D80*120 -> 120 | F80: Guest House (5)
A81: 3 | B81: 31/12/2025 | C81: Fruit Cake | D81: 1 | E81: =D81*80 -> 80 | F81: Guest House (5)
A82: Grand Total Amount | E82: =SUM(E79:E81) -> 250
A84: Preapred By | F84: Clint Signature
A86: SR# | B86: Date | C86: Item Name | D86: QTY | E86: Price | F86: Department
A87: 1 | B87: 46023 | C87: Egg | D87: 1 | E87: 50 | F87: Guest House (5)
A88: 2 | B88: 46023 | C88: Mix Biscut | D88: 1 | E88: 220 | F88: Guest House (5)
A89: 3 | B89: 46023 | C89: Cake Rus | D89: 1 | E89: 120 | F89: Guest House (5)
A90: 4 | B90: 46023 | C90: Roti | D90: 6 | E90: =D90*15 -> 90 | F90: Guest House (5)
A91: 5 | B91: 46023 | C91: Sp- Sabzi | D91: 2 | E91: =D91*180 -> 360 | F91: Guest House (5)
A92: 6 | B92: 46023 | C92: Salad | D92: 1 | E92: 30 | F92: Guest House (5)
A93: Grand Total Amount | E93: =SUM(E87:E92) -> 870
A95: Preapred By | F95: Clint Signature
A97: SR# | B97: Date | C97: Item Name | D97: QTY | E97: Price | F97: Department
A98: 1 | B98: 46029 | C98: Mix Biscut | D98: 1 | E98: 220 | F98: Guest House (5)
A99: 2 | B99: 46029 | C99: Cake Rus | D99: 1 | E99: 120 | F99: Guest House (5)
A100: 3 | B100: 46029 | C100: Milk | D100: 2 Box | E100: =2*100 -> 200 | F100: Guest House (5)
A101: Grand Total Amount | E101: =SUM(E98:E100) -> 540
A103: Preapred By | F103: Clint Signature
A105: SR# | B105: Date | C105: Item Name | D105: QTY | E105: Price | F105: Department
A106: 1 | B106: 46030 | C106: Egg Fry | D106: 2 | E106: =D106*50 -> 100 | F106: Guest House (5) Steaching
A107: 2 | B107: 46030 | C107: Sp- Tea | D107: 4 | E107: =D107*35 -> 140 | F107: Guest House (5) Steaching
A108: 3 | B108: 46030 | C108: Cake | D108: 1 | E108: 120 | F108: Guest House (5) Steaching
A109: 4 | B109: 46030 | C109: Fruit Cake | D109: 1 | E109: 80 | F109: Guest House (5) Steaching
A110: Grand Total Amount | E110: =SUM(E106:E109) -> 440
A112: Preapred By | F112: Clint Signature
A114: SR# | B114: Date | C114: Item Name | D114: QTY | E114: Price | F114: Department
A115: 1 | B115: 46031 | C115: Egg Fry | D115: 1 | E115: =D115*50 -> 50 | F115: Steaching
A116: 2 | B116: 46031 | C116: Cake Rus | D116: 2 | E116: =D116*60 -> 120 | F116: Steaching
A117: 3 | B117: 46031 | C117: Mix Biscut | D117: 2 | E117: =D117*110 -> 220 | F117: Steaching
A118: 4 | B118: 46031 | C118: Sp- Ch- Biryani | D118: 4 | E118: =D118*320 -> 1280 | F118: Steaching
A119: 5 | B119: 46031 | C119: Salad | D119: 1 | E119: 30 | F119: Steaching
A120: 6 | B120: 46031 | C120: Dahi | D120: 0.5 | E120: =D120*400 -> 200 | F120: Steaching
A121: 7 | B121: 46031 | C121: Cold Drink | D121: 1 | E121: =D121*70 -> 70 | F121: Steaching
A122: Grand Total Amount | E122: =SUM(E115:E121) -> 1970
A124: Preapred By | F124: Clint Signature
A126: SR# | B126: Date | C126: Item Name | D126: QTY | E126: Price | F126: Department
A127: 1 | B127: 46032 | C127: Egg Fry | D127: 1 | E127: =D127*50 -> 50 | F127: Guest House (5) Steaching
A128: 2 | B128: 46032 | C128: Cake Rus | E128: 120 | F128: Guest House (5) Steaching
A129: 3 | B129: 46032 | C129: Cake | D129: 1 | E129: 80 | F129: Guest House (5) Steaching
A130: Grand Total Amount | E130: =SUM(E127:E129) -> 250
...

Sheet Guest House Summary 
A1: SUMMARY OF GUEST HOUSE
A2: SR# | B2: Date | C2: Name | D2: Amount | E2: Depart
A3: 1 | B3: 46007 | C3: Amanat Sb | D3: 200 | E3: Guest House
A4: 2 | B4: 46008 | C4: Amanat Sb | D4: 530 | E4: Guest House
A5: 3 | B5: 46009 | C5: Amanat Sb | D5: 250 | E5: Guest House
A6: 4 | B6: 46015 | C6: Amanat Sb | D6: 250 | E6: Guest House
A7: 5 | B7: 46016 | C7: Amanat Sb | D7: 490 | E7: Guest House
A8: 6 | B8: 46017 | C8: Amanat Sb | D8: 510 | E8: Guest House
A9: 7 | B9: 46018 | C9: Amanat Sb | D9: 250 | E9: Guest House
A10: 8 | B10: 46019 | C10: Amanat Sb | D10: 390 | E10: Guest House
A11: 9 | B11: 46020 | C11: Amanat Sb | D11: 250 | E11: Guest House
A12: 10 | B12: 46021 | C12: Amanat Sb | D12: 250 | E12: Guest House
A13: 11 | B13: 46022 | C13: Amanat Sb | D13: 250 | E13: Guest House
A14: Grand Total Amount | D14: =SUM(D3:D13) -> 3620
A16: SUMMARY OF GUEST HOUSE
A17: SR# | B17: Date | C17: Name | D17: Amount | E17: Depart
A18: 1 | B18: 46023 | C18: Amanat Sb | D18: ='Guest House'!E93 -> 870 | E18: Guest House
A19: 2 | B19: 46029 | C19: Amanat Sb | D19: ='Guest House'!E101 -> 540 | E19: Guest House
A20: 3 | B20: 46030 | C20: Amanat Sb | D20: ='Guest House'!E110 -> 440 | E20: Guest House
A21: 4 | B21: 46031 | C21: Amanat Sb | D21: ='Guest House'!E122 -> 1970 | E21: Guest House
A22: 5 | B22: 46032 | C22: Amanat Sb | D22: ='Guest House'!E130 -> 250 | E22: Guest House
A23: 6 | B23: 46033 | C23: Amanat Sb | D23: ='Guest House'!E138 -> 390 | E23: Guest House
A24: 7 | B24: 46034 | C24: Amanat Sb | D24: ='Guest House'!E146 -> 390 | E24: Guest House
A25: 8 | B25: 46035 | C25: Amanat Sb | D25: ='Guest House'!E154 -> 390 | E25: Guest House
A26: 9 | B26: 46036 | C26: Amanat Sb | D26: ='Guest House'!E162 -> 390 | E26: Guest House
A27: 10 | B27: 46037 | C27: Amanat Sb | D27: ='Guest House'!E170 -> 250 | E27: Guest House
A28: Grand Total Amount | D28: =SUM(D18:D27) -> 5880
A29: Preapred By | E29: Clint Signature
A33: Admin Sig

Sheet Milk Purchase 
A1: SR# | B1: Date | C1: Item Name | D1: Day | E1: QTY | F1: Unit | G1: Price | H1: Amount | I1: Wate Roti | J1: Unit | K1: Price | L1: Amount | M1: Payment
A2: 1 | B2: 16/12/2025 | C2: Milk | D2: Tuesday | E2: 20 | F2: Litter | G2: 220 | H2: =G2*E2 -> 4400 | M2: Clear
A3: 2 | B3: 17/12/2025 | C3: Milk | D3: Wednesday | E3: 10 | F3: Litter | G3: 220 | H3: =G3*E3 -> 2200 | I3: 35 | J3: Kg | K3: 30 | L3: =K3*I3 -> 1050 | M3: Clear
A4: 3 | B4: 18/12/2025 | C4: Milk | D4: Thursday | E4: 10 | F4: Litter | G4: 220 | H4: =G4*E4 -> 2200 | L4: =K4*I4 -> 0 | M4: Clear
A5: 4 | B5: 19/12/2025 | C5: Youget | D5: Friday | E5: 8 | F5: Kg | G5: 320 | H5: =G5*E5 -> 2560 | I5: 40 | J5: Kg | K5: 30 | L5: =K5*I5 -> 1200 | M5: Clear
A6: 5 | B6: 19/12/2025 | C6: Milk | D6: Friday | E6: 15 | F6: Litter | G6: 220 | H6: =G6*E6 -> 3300 | L6: =K6*I6 -> 0 | M6: Clear
A7: 6 | B7: 46013 | C7: Milk | D7: Monday | E7: 10 | F7: Litter | G7: 220 | H7: =G7*E7 -> 2200 | I7: 50 | J7: Kg | K7: 30 | L7: =K7*I7 -> 1500 | M7: Clear
A8: 7 | B8: 46014 | C8: Milk | D8: Tuesday | E8: 10 | F8: Litter | G8: 220 | H8: =G8*E8 -> 2200 | L8: =K8*I8 -> 0 | M8: Clear
A9: 8 | B9: 46015 | C9: Milk | D9: Wednesday | E9: 10 | F9: Litter | G9: 220 | H9: =G9*E9 -> 2200 | I9: 45 | J9: Kg | K9: 30 | L9: =K9*I9 -> 1350 | M9: Clear
A10: 9 | B10: 46016 | C10: Milk | D10: Thursday | E10: 20 | F10: Litter | G10: 220 | H10: =G10*E10 -> 4400 | L10: =K10*I10 -> 0 | M10: Clear
A11: 10 | B11: 46017 | C11: Milk | D11: Friday | E11: 10 | F11: Litter | G11: 220 | H11: =G11*E11 -> 2200 | I11: 20 | J11: Kg | K11: 30 | L11: =K11*I11 -> 600 | M11: Clear
A12: 11 | B12: 46018 | C12: Milk | D12: Saturday | E12: 10 | F12: Litter | G12: 220 | H12: =G12*E12 -> 2200 | L12: =K12*I12 -> 0 | M12: Clear
A13: 12 | B13: 46019 | C13: Milk | D13: Sunday | E13: 10 | F13: Litter | G13: 220 | H13: =G13*E13 -> 2200 | L13: =K13*I13 -> 0 | M13: Clear
A14: 13 | B14: 46020 | C14: Milk | D14: Monday | E14: 10 | F14: Litter | G14: 220 | H14: =G14*E14 -> 2200 | L14: =K14*I14 -> 0 | M14: Clear
A15: 14 | B15: 46021 | C15: Milk | D15: Tuesday | E15: 12 | F15: Litter | G15: 220 | H15: =G15*E15 -> 2640 | L15: =K15*I15 -> 0 | M15: Clear
A16: 15 | B16: 46022 | C16: Milk | D16: Wednesday | E16: 11 | F16: Litter | G16: 220 | H16: =G16*E16 -> 2420 | L16: =K16*I16 -> 0 | M16: Clear
A17: 16 | B17: 46023 | C17: Milk | D17: Thursday | E17: 10 | F17: Litter | G17: 220 | H17: =G17*E17 -> 2200 | L17: =K17*I17 -> 0 | M17: Clear
A18: 17 | B18: 46024 | C18: Milk | D18: Friday | E18: 16 | F18: Litter | G18: 220 | H18: =G18*E18 -> 3520 | L18: =K18*I18 -> 0 | M18: Clear
A19: 18 | B19: 46025 | C19: Milk | D19: Saturday | E19: 14 | F19: Litter | G19: 220 | H19: =G19*E19 -> 3080 | L19: =K19*I19 -> 0 | M19: Clear
A20: 19 | B20: 46026 | C20: Milk | D20: Sunday | E20: 10 | F20: Litter | G20: 220 | H20: =G20*E20 -> 2200 | L20: =K20*I20 -> 0 | M20: Clear
A21: 20 | B21: 46027 | C21: Milk | D21: Monday | E21: 10 | F21: Litter | G21: 220 | H21: =G21*E21 -> 2200 | I21: 15 | J21: Kg | K21: 30 | L21: =K21*I21 -> 450 | M21: Clear
A22: 21 | B22: 46028 | C22: Milk | D22: Tuesday | E22: 10 | F22: Litter | G22: 220 | H22: =G22*E22 -> 2200 | L22: =K22*I22 -> 0 | M22: Clear
A23: 22 | B23: 46029 | C23: Milk | D23: Wednesday | E23: 11 | F23: Litter | G23: 220 | H23: =G23*E23 -> 2420 | I23: 31 | J23: Kg | K23: 30 | L23: =K23*I23 -> 930 | M23: Clear
A24: 23 | B24: 46030 | C24: Milk | D24: Thursday | E24: 10 | F24: Litter | G24: 220 | H24: =G24*E24 -> 2200 | M24: Clear
A25: 24 | B25: 46031 | C25: Milk | D25: Friday | E25: 10 | F25: Litter | G25: 220 | H25: =G25*E25 -> 2200 | M25: Clear
A26: 25 | B26: 46032 | C26: Milk | D26: Saturday | E26: 10 | F26: Litter | G26: 220 | H26: =G26*E26 -> 2200 | M26: Clear
A27: 26 | B27: 46034 | C27: Milk | D27: Monday | E27: 10 | F27: Litter | G27: 220 | H27: =G27*E27 -> 2200 | M27: Clear
A28: 27 | B28: 46035 | C28: Milk | D28: Tuesday | E28: 10 | F28: Litter | G28: 220 | H28: =G28*E28 -> 2200 | M28: Clear
A29: 28 | B29: 46036 | C29: Milk | D29: Wednesday | E29: 11 | F29: Litter | G29: 220 | H29: =G29*E29 -> 2420 | M29: Clear
A30: 29 | B30: 46037 | C30: Milk | D30: Thursday | E30: 11 | F30: Litter | G30: 220 | H30: =G30*E30 -> 2420 | M30: Clear
A31: 30 | B31: 46038 | C31: Milk | D31: Friday | E31: 12 | F31: Litter | G31: 220 | H31: =G31*E31 -> 2640 | M31: Clear
A32: 31 | B32: 46039 | C32: Milk | D32: Saturday | E32: 12 | F32: Litter | G32: 220 | H32: =G32*E32 -> 2640 | M32: Clear
A33: 32 | B33: 46041 | C33: Milk | D33: Monday | E33: 14 | F33: Litter | G33: 220 | H33: =G33*E33 -> 3080 | M33: Clear
A34: 33 | B34: 46042 | C34: Milk | D34: Tuesday | E34: 12 | F34: Litter | G34: 220 | H34: =G34*E34 -> 2640
I37: =SUM(I2:I25) -> 236 | L37: =SUM(L3:L25) -> 7080
A39: Grand Total Amount | H39: =SUM(H2:H38) -> 84180
A41: Mujtaba And Borthers
A42: SR# | B42: Date | C42: Item Name | D42: Day | E42: QTY | F42: Unit | G42: Price | H42: Amount
A43: 1 | B43: 46032 | C43: Milk | D43: Saturday | E43: 10 | F43: Litter | G43: 220 | H43: =G43*E43 -> 2200
A44: 2 | B44: 46034 | C44: Milk | D44: Monday | E44: 10 | F44: Litter | G44: 220 | H44: =G44*E44 -> 2200
A45: 3 | B45: 46035 | C45: Milk | D45: Tuesday | E45: 10 | F45: Litter | G45: 220 | H45: =G45*E45 -> 2200
A46: 4 | B46: 46036 | C46: Milk | D46: Wednesday | E46: 10 | F46: Litter | G46: 220 | H46: =G46*E46 -> 2200
A47: 5 | B47: 46037 | C47: Milk | D47: Thursday | E47: 16 | F47: Litter | G47: 220 | H47: =G47*E47 -> 3520
A48: 6 | B48: 46038 | C48: Milk | D48: Friday | E48: 13 | F48: Litter | G48: 220 | H48: =G48*E48 -> 2860
A49: 7 | B49: 46039 | C49: Milk | D49: Saturday | E49: 12 | F49: Litter | G49: 220 | H49: =G49*E49 -> 2640
A50: 8 | B50: 46041 | C50: Milk | D50: Monday | E50: 14 | F50: Litter | G50: 220 | H50: =G50*E50 -> 3080
A51: Grand Total Amount | H51: =SUM(H43:H50) -> 20900
A53: Preapred By | H53: Received By

Sheet Fabric W.House
A1: SR# | B1: Date | C1: Item Name | D1: QTY | E1: Price | F1: Department
A2: 1 | B2: 46024 | C2: Sp- Biryani | D2: 2 | E2: =D2*320 -> 640 | F2: Fabric W. House
A3: 2 | B3: 46024 | C3: Cold Drink | D3: 2 | E3: =D3*70 -> 140 | F3: Fabric W. House
A4: 3 | B4: 46024 | C4: Salad | D4: 2 | E4: =D4*30 -> 60 | F4: Fabric W. House
A5: Grand Total Amount | E5: =SUM(E2:E4) -> 840
A7: Preapred By | F7: Clint Signature
A9: SUMMARY OF FBRIC W. HOUSE DEPART
A10: SR# | B10: Date | C10: Name | D10: Amount | E10: Depart
A11: 1 | B11: 46024 | C11: Arsalan Sb | D11: 840 | E11: Fabric W. House
A12: Grand Total Amount | D12: =SUM(D11:D11) -> 840
A13: Preapred By | E13: Clint Signature
A17: Admin Sig
